Workbook

Sheet 理论测算 
A1: 2026-2030年盈利测算表-测算框架
A2: 项目 | B2: 2024年 | C2: 2025年 | E2: 2026年 | G2: 2027年 | I2: 2028年 | K2: 2029年 | M2: 2030年 | O2: 十五五 平均增量 | P2: 十五五 累计增量 | Q2: 十五五 复合增速
C3: 余额 | D3: 年增 | E3: 余额 | F3: 年增 | G3: 余额 | H3: 年增 | I3: 余额 | J3: 年增 | K3: 余额 | L3: 年增 | M3: 余额 | N3: 年增
A4: 一、盈利结果
A5: （一）并表口径
A6: 归母净利润 | C6: 706.18 | D6: 20.42 | E6: =D33 -> 767.86252 | F6: =E6-C6 -> 61.682516 | G6: =E33 -> 854.5966 | H6: =G6-E6 -> 86.734079 | I6: =F33 -> 943.23317 | J6: =I6-G6 -> 88.636571 | K6: =G33 -> 1049.0656 | L6: =K6-I6 -> 105.8324 | M6: =H33 -> 1175.2513 | N6: =M6-K6 -> 126.1857 | O6: =P6/5 -> 93.814252 | P6: =M6-C6 -> 469.07126 | Q6: =(M6/C6)^(1/5)-1 -> 0.1072433
A7: 营业净收入 | C7: 2124.75 | D7: -11.71 | E7: =E8+E9 -> 2190.1054 | F7: =E7-C7 -> 65.355413 | G7: =G8+G9 -> 2299.1969 | H7: =G7-E7 -> 109.09149 | I7: =I8+I9 -> 2400.0048 | J7: =I7-G7 -> 100.80785 | K7: =K8+K9 -> 2497.9422 | L7: =K7-I7 -> 97.937396 | M7: =M8+M9 -> 2598.0386 | N7: =M7-K7 -> 100.09648 | O7: =P7/5 -> 94.657726 | P7: =M7-C7 -> 473.28863 | Q7: =(M7/C7)^(1/5)-1 -> 0.041040327
A8: 其中：利息净收入 | C8: 1444.69 | D8: -22.1 | E8: =(C11+E11)/2*E17*E18 -> 1500.0032 | F8: =E8-C8 -> 55.313197 | G8: =(E11+G11)/2*G17*G18 -> 1586.2159 | H8: =G8-E8 -> 86.212747 | I8: =(G11+I11)/2*I17*I18 -> 1667.7633 | J8: =I8-G8 -> 81.547361 | K8: =(I11+K11)/2*K17*K18 -> 1748.3097 | L8: =K8-I8 -> 80.546407 | M8: =(K11+M11)/2*M17*M18 -> 1831.3574 | N8: =M8-K8 -> 83.047718 | O8: =P8/5 -> 77.333486 | P8: =M8-C8 -> 386.66743 | Q8: =(M8/C8)^(1/5)-1 -> 0.04857546
A9: 非利息净收入 | C9: 680.06 | D9: 10.39 | E9: =E19*E8/(1-E19) -> 690.10222 | F9: =E9-C9 -> 10.042216 | G9: =G19*G8/(1-G19) -> 712.98096 | H9: =G9-E9 -> 22.878744 | I9: =I19*I8/(1-I19) -> 732.24145 | J9: =I9-G9 -> 19.260491 | K9: =K19*K8/(1-K19) -> 749.63244 | L9: =K9-I9 -> 17.390989 | M9: =M19*M8/(1-M19) -> 766.6812 | N9: =M9-K9 -> 17.04876 | O9: =P9/5 -> 17.32424 | P9: =M9-C9 -> 86.6212 | Q9: =(M9/C9)^(1/5)-1 -> 0.024267792
A10: 二、一级核心指标
A11: 总资产 | B11: 95327.22 | C11: 101310.28 | D11: 5989.36 | E11: =C11+F11 -> 108000.28 | F11: 6690 | G11: =E11+H11 -> 113200.28 | H11: 5200 | I11: =G11+J11 -> 118600.28 | J11: 5400 | K11: =I11+L11 -> 124200.28 | L11: 5600 | M11: =K11+N11 -> 130000.28 | N11: =5800 -> 5800 | O11: =P11/5 -> 5738 | P11: =M11-C11 -> 28690 | Q11: =(M11/C11)^(1/5)-1 -> 0.05113417
A12: ROE | C12: 0.0939 | D12: =C12-9.79% -> -0.004 | E12: =D46 -> 0.097100174 | F12: =E12-C12 -> 0.003200174 | G12: =E46 -> 0.10142433 | H12: =G12-E12 -> 0.0043241576 | I12: =F46 -> 0.10111302 | J12: =I12-G12 -> -0.00031130948 | K12: =G46 -> 0.10323922 | L12: =K12-I12 -> 0.0021262007 | M12: =H46 -> 0.10650149 | N12: =M12-K12 -> 0.0032622683 | O12: =P12/5 -> 0.0025202982 | P12: =M12-C12 -> 0.012601491
A13: RAROC | C13: 0.0881 | D13: -0.0034 | E13: =D64 -> 0.087525447 | F13: =E13-C13 -> -0.00057455281 | G13: =E64 -> 0.089659256 | H13: =G13-E13 -> 0.0021338091 | I13: =F64 -> 0.092664086 | J13: =I13-G13 -> 0.0030048296 | K13: =G64 -> 0.096843159 | L13: =K13-I13 -> 0.0041790736 | M13: =H64 -> 0.10226377 | N13: =M13-K13 -> 0.0054206079 | O13: =P13/5 -> 0.0028327535 | P13: =M13-C13 -> 0.014163767
A14: 风险加权资产 | C14: 76843.388 | D14: 6156.0257 | E14: =D53 -> 84743.388 | F14: =E14-C14 -> 7900 | G14: =E53 -> 90586.397 | H14: =G14-E14 -> 5843.0085 | I14: =F53 -> 96449.519 | J14: =I14-G14 -> 5863.1221 | K14: =G53 -> 102384.74 | L14: =K14-I14 -> 5935.2183 | M14: =H53 -> 108345.06 | N14: =M14-K14 -> 5960.3227 | O14: =P14/5 -> 6300.3343 | P14: =M14-C14 -> 31501.672 | Q14: =(M14/C14)^(1/5)-1 -> 0.071125902
A15: 核心一级资本充足率 | C15: 0.0948 | D15: -0.0024 | E15: =D54 -> 0.092188918 | F15: =E15-C15 -> -0.002611082 | G15: =E54 -> 0.0959149 | H15: =G15-E15 -> 0.0037259824 | I15: =F54 -> 0.097522797 | J15: =I15-G15 -> 0.0016078964 | K15: =G54 -> 0.099495276 | L15: =K15-I15 -> 0.0019724795 | M15: =H54 -> 0.10195561 | N15: =M15-K15 -> 0.0024603314 | O15: =P15/5 -> 0.0014311215 | P15: =M15-C15 -> 0.0071556077
A16: 三、二级核心指标
A17: 生息资产占比（日均） | C17: 0.9008 | E17: =C17+F17 -> 0.8958 | F17: -0.005 | G17: =E17+H17 -> 0.8908 | H17: -0.005 | I17: =G17+J17 -> 0.8828 | J17: -0.008 | K17: =I17+L17 -> 0.8728 | L17: -0.01 | M17: =K17+N17 -> 0.8628 | N17: -0.01 | O17: =P17/5 -> -0.0076 | P17: =M17-C17 -> -0.038
A18: 净息差 | C18: 0.0163 | D18: -0.0014 | E18: 0.016 | F18: =E18-C18 -> -0.0003 | G18: 0.0161 | H18: =G18-E18 -> 0.0001 | I18: 0.0163 | J18: =I18-G18 -> 0.0002 | K18: 0.0165 | L18: =K18-I18 -> 0.0002 | M18: 0.0167 | N18: =M18-K18 -> 0.0002 | O18: =P18/5 -> 8e-05 | P18: =M18-C18 -> 0.0004
A19: 非息收入占比 | C19: 0.3201 | D19: 0.0067 | E19: =C19+F19 -> 0.3151 | F19: -0.005 | G19: =E19+H19 -> 0.3101 | H19: -0.005 | I19: =G19+J19 -> 0.3051 | J19: -0.005 | K19: =I19+L19 -> 0.3001 | L19: -0.005 | M19: =K19+N19 -> 0.2951 | N19: -0.005 | O19: =P19/5 -> -0.005 | P19: =M19-C19 -> -0.025
A20: 成本收入比 | C20: 0.31607954 | D20: -0.0088 | E20: =C20+F20 -> 0.30997954 | F20: -0.0061 | G20: =E20+H20 -> 0.30497954 | H20: -0.005 | I20: =G20+J20 -> 0.29997954 | J20: -0.005 | K20: =I20+L20 -> 0.29497954 | L20: -0.005 | M20: =K20+N20 -> 0.28997954 | N20: -0.005 | O20: =P20/5 -> -0.00522 | P20: =M20-C20 -> -0.0261
A21: 风险成本率 | C21: 0.2737828 | E21: =L37 -> 0.26117464 | F21: =E21-C21 -> -0.012608155 | G21: =M37 -> 0.24530304 | H21: =G21-E21 -> -0.015871599 | I21: =N37 -> 0.22916621 | J21: =I21-G21 -> -0.016136832 | K21: =O37 -> 0.20737069 | L21: =K21-I21 -> -0.021795518 | M21: =P37 -> 0.18013589 | N21: =M21-K21 -> -0.027234805 | O21: =P21/5 -> -0.018729382 | P21: =M21-C21 -> -0.093646908
A22: 税务成本率 | C22: 0.069255206 | E22: =C22+F22 -> 0.069255206 | F22: 0 | G22: =E22+H22 -> 0.069255206 | H22: 0 | I22: =G22+J22 -> 0.069255206 | J22: 0 | K22: =I22+L22 -> 0.069255206 | L22: 0 | M22: =K22+N22 -> 0.069255206 | N22: 0 | O22: =P22/5 -> 0 | P22: =M22-C22 -> 0
A23: 其他（营业外收支率） | C23: 0.0044193435 | E23: =C23+F23 -> 0.0044193435 | F23: 0 | G23: =E23+H23 -> 0.0044193435 | H23: 0 | I23: =G23+J23 -> 0.0044193435 | J23: 0 | K23: =I23+L23 -> 0.0044193435 | L23: 0 | M23: =K23+N23 -> 0.0044193435 | N23: 0 | O23: =P23/5 -> 0 | P23: =M23-C23 -> 0
A24: 综合风险权重 | C24: =C63 -> 0.75026761 | E24: =D63 -> 0.77199534 | F24: =E24-C24 -> 0.021727722 | G24: =E63 -> 0.79262812 | H24: =G24-E24 -> 0.020632787 | I24: =F63 -> 0.80688293 | J24: =I24-G24 -> 0.014254808 | K24: =G63 -> 0.81892009 | L24: =K24-I24 -> 0.012037156 | M24: =H63 -> 0.82899029 | N24: =M24-K24 -> 0.010070206 | O24: =P24/5 -> 0.015744536 | P24: =M24-C24 -> 0.078722678
A25: 四、权益端
A26: 归母净资产 | C26: 8288.13 | D26: 395.49 | E26: =D49 -> 8752.6256 | F26: =E26-C26 -> 464.49564 | G26: =E49 -> 9874.0248 | H26: =G26-E26 -> 1121.3992 | I26: =F49 -> 10984.107 | J26: =I26-G26 -> 1110.082 | K26: =G49 -> 12056.157 | L26: =K26-I26 -> 1072.0502 | M26: =H49 -> 13206.913 | N26: =M26-K26 -> 1150.7557 | O26: =P26/5 -> 983.75655 | P26: =M26-C26 -> 4918.7828 | Q26: =(M26/C26)^(1/5)-1 -> 0.097662812
A27: 其中：归属母公司普通股股东净资产 | C27: =C48 -> 7238.13 | D27: =D26 -> 395.49 | E27: =D48 -> 7702.6256 | F27: =E27-C27 -> 464.49564 | G27: =E48 -> 8624.0248 | H27: =G27-E27 -> 921.3992 | I27: =F48 -> 9334.1069 | J27: =I27-G27 -> 710.08201 | K27: =G48 -> 10106.157 | L27: =K27-I27 -> 772.05018 | M27: =H48 -> 10956.913 | N27: =M27-K27 -> 850.75573 | O27: =P27/5 -> 743.75655 | P27: =M27-C27 -> 3718.7828 | Q27: =(M27/C27)^(1/5)-1 -> 0.086456556
J29: 规划报告参数
A30: 项目 | B30: 2024年 | C30: 2025年 | D30: 2026年 | E30: 2027年 | F30: 2028年 | G30: 2029年 | H30: 2030年
A31: 总资产 | B31: =B11 -> 95327.22 | C31: =C11 -> 101310.28 | D31: =E11 -> 108000.28 | E31: =G11 -> 113200.28 | F31: =I11 -> 118600.28 | G31: =K11 -> 124200.28 | H31: =M11 -> 130000.28 | J31: 集团净利润 | K31: 714.9 | L31: 809.1 | M31: 890.3 | N31: 979.9 | O31: 1079.3 | P31: 1189.9
A32: 净利润 | C32: =(1-C20-C21-C22-C23)*C7 -> 714.9 | D32: =(1-E20-E21-E22-E23)*E7 -> 777.86252 | E32: =(1-G20-G21-G22-G23)*G7 -> 864.5966 | F32: =(1-I20-I21-I22-I23)*I7 -> 953.23317 | G32: =(1-K20-K21-K22-K23)*K7 -> 1059.0656 | H32: =(1-M20-M21-M22-M23)*M7 -> 1185.2513 | J32: 归母净利润 | K32: 706.2 | L32: 799.2 | M32: 879.5 | N32: 967.9 | O32: 1066.2 | P32: 1175.4
A33: 归母净利润 | C33: =C6 -> 706.18 | D33: =D32-10 -> 767.86252 | E33: =E32-10 -> 854.5966 | F33: =F32-10 -> 943.23317 | G33: =G32-10 -> 1049.0656 | H33: =H32-10 -> 1175.2513 | J33: 总资产 | K33: 101310 | L33: 108662 | M33: 113750 | N33: 118422 | O33: 123191 | P33: 127484
A34: 优先股、永续债分红 | D34: -38.34 | E34: -25.2 | F34: -30 | G34: -39.6 | H34: -46.8 | J34: RWA/总资产 | K34: 0.7585 | L34: 0.7486 | M34: 0.7371 | N34: 0.7249 | O34: 0.7129 | P34: 0.7021
A35: 分红率 | D35: 0.307 | E35: 0.307 | F35: 0.307 | G35: 0.307 | H35: 0.307 | J35: 净息差 | K35: 0.0163 | L35: 0.016 | M35: 0.0161 | N35: 0.0163 | O35: 0.0165 | P35: 0.0167
A36: 现金分红 | D36: =-(C33+D34)*D35 -> -205.02688 | E36: =-(D33+E34)*E35 -> -227.99739 | F36: =-(E33+F34)*F35 -> -253.15115 | G36: =-(F33+G34)*G35 -> -277.41538 | H36: =-(G33+H34)*H35 -> -307.69553 | J36: 信用减值（亿元） | K36: 582 | L36: 572 | M36: 564 | N36: 550 | O36: 518 | P36: 468
A37: 第一次分红 | D37: =D36/2 -> -102.51344 | E37: =E36/2 -> -113.9987 | F37: =F36/2 -> -126.57558 | G37: =G36/2 -> -138.70769 | H37: =H36/2 -> -153.84776 | J37: 风险成本率 | K37: =K36/C7 -> 0.27391458 | L37: =L36/E7 -> 0.26117464 | M37: =M36/G7 -> 0.24530304 | N37: =N36/I7 -> 0.22916621 | O37: =O36/K7 -> 0.20737069 | P37: =P36/M7 -> 0.18013589
A38: 剩余月份 | D38: 6 | E38: 6 | F38: 6 | G38: 6 | H38: 6 | J38: ROE | K38: 0.0939 | L38: 0.092 | M38: 0.093 | N38: 0.096 | O38: 0.099 | P38: 0.1025
A39: 影响1 | D39: =D37*D38/12 -> -51.25672 | E39: =E37*E38/12 -> -56.999348 | F39: =F37*F38/12 -> -63.287789 | G39: =G37*G38/12 -> -69.353845 | H39: =H37*H38/12 -> -76.923882 | J39: RAROC | K39: 0.0881 | L39: 0.093 | M39: 0.098 | N39: 0.105 | O39: 0.113 | P39: 0.122
A40: 第二次分红 | D40: =D37 -> -102.51344 | E40: =E37 -> -113.9987 | F40: =F37 -> -126.57558 | G40: =G37 -> -138.70769 | H40: =H37 -> -153.84776 | J40: 核心一级资本充足率 | K40: 0.0948 | L40: 0.097 | M40: 0.1 | N40: 0.103 | O40: 0.106 | P40: 0.111
A41: 剩余月份 | D41: 1 | E41: 1 | F41: 1 | G41: 1 | H41: 1 | J41: 成本收入比 | K41: 0.3161 | L41: 0.31 | M41: 0.305 | N41: 0.3 | O41: 0.295 | P41: 0.29
A42: 影响2 | D42: =D40*D41/12 -> -8.5427867 | E42: =E40*E41/12 -> -9.4998914 | F42: =F40*F41/12 -> -10.547965 | G42: =G40*G41/12 -> -11.558974 | H42: =H40*H41/12 -> -12.820647
A43: 配股 | D43: 0 | E43: 400 | F43: 0 | G43: 0 | H43: 0
A44: 剩余月份 | D44: 0 | E44: 5 | F44: 0 | G44: 0 | H44: 0
A45: 影响3 | D45: =D43*D44/12 -> 0 | E45: =E43*E44/12 -> 166.66667 | F45: =F43*F44/12 -> 0 | G45: =G43*G44/12 -> 0 | H45: =H43*H44/12 -> 0
A46: ROE1 | C46: 0.093948605 | D46: =(D33+D34)/(C49+(D33+D34+D60)/2+D39+D42+D45-350-700) -> 0.097100174 | E46: =(E33+E34)/(D49+(E33+E34+E60)/2+E39+E42+E45-350-700) -> 0.10142433 | F46: =(F33+F34)/(E49+(F33+F34+F60)/2+F39+F42+F45-350-700-SUM($D$58:E58)) -> 0.10111302 | G46: =(G33+G34)/(F49+(G33+G34+G60)/2+G39+G42+G45-350-700-SUM($D$58:F58)) -> 0.10323922 | H46: =(H33+H34)/(G49+(H33+H34+H60)/2+H39+H42+H45-350-700-SUM($D$58:G58)) -> 0.10650149
A47: ROE2 | C47: 0.093948605 | D47: =(D33+D34)/(C48+(D33+D34+D60)/2+D39+D42+D45) -> 0.097100174 | E47: =(E33+E34)/(D48+(E33+E34+E60)/2+E39+E42+E45) -> 0.10142433 | F47: =(F33+F34)/(E48+(F33+F34+F60)/2+F39+F42+F45) -> 0.10111302 | G47: =(G33+G34)/(F48+(G33+G34+G60)/2+G39+G42+G45) -> 0.10323922 | H47: =(H33+H34)/(G48+(H33+H34+H60)/2+H39+H42+H45) -> 0.10650149
A48: 归母普通股净资产 | C48: =C49-1050 -> 7238.13 | D48: =D49-1050-D58 -> 7702.6256 | E48: =E49-1050-D58-E58 -> 8624.0248 | F48: =F49-1050-D58-E58-F58 -> 9334.1069 | G48: =G49-1050-D58-E58-F58-G58 -> 10106.157 | H48: =H49-1050-D58-E58-F58-G58-H58 -> 10956.913
A49: 归母净资产 | C49: =C26 -> 8288.13 | D49: =C49+(D33+D34+D36)+D57+D58+D60 -> 8752.6256 | E49: =D49+(E33+E34+E36)+E57+E58+E60 -> 9874.0248 | F49: =E49+(F33+F34+F36)+F57+F58+F60 -> 10984.107 | G49: =F49+(G33+G34+G36)+G57+G58+G60 -> 12056.157 | H49: =G49+(H33+H34+H36)+H57+H58+H60 -> 13206.913
A50: 核心一级资本净额 | C50: 7286.085 | D50: =C50+D57+D60+D61+D62 -> 7812.4013 | E50: =D50+E57+E60+E61+E62 -> 8688.5852 | F50: =E50+F57+F60+F61+F62 -> 9406.0268 | G50: =F50+G57+G60+G61+G62 -> 10186.798 | H50: =G50+H57+H60+H61+H62 -> 11046.386
A51: 一级资本净额 | C51: 8377.1782 | D51: =C51+D57+D58+D60+D61+D62 -> 8903.4945 | E51: =D51+E57+E58+E60+E61+E62 -> 9979.6784 | F51: =E51+F57+F58+F60+F61+F62 -> 11097.12 | G51: =F51+G57+G58+G60+G61+G62 -> 12177.891 | H51: =G51+H57+H58+H60+H61+H62 -> 13337.48
A52: 资本净额 | C52: 9839.6792 | D52: =C52+D57+D58+D59+D60+D61+D62 -> 10445.995 | E52: =D52+E57+E58+E59+E60+E61+E62 -> 11802.179 | F52: =E52+F57+F58+F59+F60+F61+F62 -> 12919.621 | G52: =F52+G57+G58+G59+G60+G61+G62 -> 14000.392 | H52: =G52+H57+H58+H59+H60+H61+H62 -> 15159.981
A53: 风险加权资产 | B53: 70687.36 | C53: 76843.388 | D53: 84743.388 | E53: 90586.397 | F53: 96449.519 | G53: 102384.74 | H53: 108345.06
A54: 核心一级资本充足率 | C54: 0.094817331 | D54: =D50/D$53 -> 0.092188918 | E54: =E50/E$53 -> 0.0959149 | F54: =F50/F$53 -> 0.097522797 | G54: =G50/G$53 -> 0.099495276 | H54: =H50/H$53 -> 0.10195561
A55: 一级资本充足率 | C55: 0.10901625 | D55: =D51/D$53 -> 0.10506418 | E55: =E51/E$53 -> 0.11016752 | F55: =F51/F$53 -> 0.11505625 | G55: =G51/G$53 -> 0.11894244 | H55: =H51/H$53 -> 0.12310187
A56: 总资本充足率 | C56: 0.12804848 | D56: =D52/D$53 -> 0.1232662 | E56: =E52/E$53 -> 0.13028644 | F56: =F52/F$53 -> 0.13395216 | G56: =G52/G$53 -> 0.13674296 | H56: =H52/H$53 -> 0.13992314
A57: 资本工具变动-核心一级 | D57: 0 | E57: 400 | F57: 0 | G57: 0 | H57: 0
A58: 资本工具变动-其他一级 | D58: 0 | E58: 200 | F58: 400 | G58: 300 | H58: 300
A59: 资本工具变动-二级 | D59: 80 | E59: 280 | F59: 0 | G59: 0 | H59: 0
A60: 资本公积波动 | D60: -60 | E60: -80 | F60: 50 | G60: 40 | H60: 30
A61: 少数股东资本 | D61: 61.820625 | E61: -45.21525 | F61: 7.3596 | G61: 8.7207 | H61: 8.832975
A62: 内生资本补充 | D62: =D33+D34+D36 -> 524.49564 | E62: =E33+E34+E36 -> 601.3992 | F62: =F33+F34+F36 -> 660.08201 | G62: =G33+G34+G36 -> 732.05018 | H62: =H33+H34+H36 -> 820.75573
A63: 综合风险权重 | C63: =AVERAGE(B53:C53)/AVERAGE(B31:C31) -> 0.75026761 | D63: =AVERAGE(C53:D53)/AVERAGE(C31:D31) -> 0.77199534 | E63: =AVERAGE(D53:E53)/AVERAGE(D31:E31) -> 0.79262812 | F63: =AVERAGE(E53:F53)/AVERAGE(E31:F31) -> 0.80688293 | G63: =AVERAGE(F53:G53)/AVERAGE(F31:G31) -> 0.81892009 | H63: =AVERAGE(G53:H53)/AVERAGE(G31:H31) -> 0.82899029
A64: RAROC | C64: 0.088105 | D64: =D32/(AVERAGE(C53:D53)*11%) -> 0.087525447 | E64: =E32/(AVERAGE(D53:E53)*11%) -> 0.089659256 | F64: =F32/(AVERAGE(E53:F53)*11%) -> 0.092664086 | G64: =G32/(AVERAGE(F53:G53)*11%) -> 0.096843159 | H64: =H32/(AVERAGE(G53:H53)*11%) -> 0.10226377

Sheet 汇总展示表
A1: 三种情景对比情况（V0708)
A2: 项目 | B2: 指标 | C2: 2025实际 | D2: 积极情景
D3: 2026年 | E3: 2027年 | F3: 2028年 | G3: 2029年 | H3: 2030年 | I3: 十五五总增量/累计变化 | J3: 复合增速
A4: 财务结果 | B4: 一、盈利结果
B5: （一）并表口径
B6: 归母净利润 | C6: ='2026-2030年盈利测算表'!L6 -> 706.18 | D6: ='2026-2030年盈利测算表'!N6 -> 757.81904 | E6: ='2026-2030年盈利测算表'!P6 -> 810.60057 | F6: ='2026-2030年盈利测算表'!R6 -> 866.01284 | G6: ='2026-2030年盈利测算表'!T6 -> 927.36198 | H6: ='2026-2030年盈利测算表'!V6 -> 985.20062 | I6: ='2026-2030年盈利测算表'!X6 -> 279.02062 | J6: ='2026-2030年盈利测算表'!Y6 -> 0.06886253
B7: 营业净收入 | C7: ='2026-2030年盈利测算表'!L7 -> 2124.75 | D7: ='2026-2030年盈利测算表'!N7 -> 2219.8843 | E7: ='2026-2030年盈利测算表'!P7 -> 2344.467 | F7: ='2026-2030年盈利测算表'!R7 -> 2461.359 | G7: ='2026-2030年盈利测算表'!T7 -> 2591.0856 | H7: ='2026-2030年盈利测算表'!V7 -> 2707.3909 | I7: ='2026-2030年盈利测算表'!X7 -> 582.64091 | J7: ='2026-2030年盈利测算表'!Y7 -> 0.049659947
B8: 其中：利息净收入 | C8: ='2026-2030年盈利测算表'!L8 -> 1444.69 | D8: ='2026-2030年盈利测算表'!N8 -> 1487.1203 | E8: ='2026-2030年盈利测算表'!P8 -> 1594.5546 | F8: ='2026-2030年盈利测算表'!R8 -> 1671.7017 | G8: ='2026-2030年盈利测算表'!T8 -> 1751.2832 | H8: ='2026-2030年盈利测算表'!V8 -> 1811.7919 | I8: ='2026-2030年盈利测算表'!X8 -> 367.10188 | J8: ='2026-2030年盈利测算表'!Y8 -> 0.046325305
B9: 非利息净收入 | C9: ='2026-2030年盈利测算表'!L9 -> 680.06 | D9: ='2026-2030年盈利测算表'!N9 -> 732.76405 | E9: ='2026-2030年盈利测算表'!P9 -> 749.91237 | F9: ='2026-2030年盈利测算表'!R9 -> 789.65734 | G9: ='2026-2030年盈利测算表'!T9 -> 839.80245 | H9: ='2026-2030年盈利测算表'!V9 -> 895.59903 | I9: ='2026-2030年盈利测算表'!X9 -> 215.53903 | J9: ='2026-2030年盈利测算表'!Y9 -> 0.056606496
B10: （二）本行口径
B11: 净利润 | C11: ='2026-2030年盈利测算表'!L11 -> 647.01 | D11: ='2026-2030年盈利测算表'!N11 -> 685.87278 | E11: ='2026-2030年盈利测算表'!P11 -> 718.39854 | F11: ='2026-2030年盈利测算表'!R11 -> 762.80085 | G11: ='2026-2030年盈利测算表'!T11 -> 811.01314 | H11: ='2026-2030年盈利测算表'!V11 -> 855.33941 | I11: ='2026-2030年盈利测算表'!X11 -> 208.32941 | J11: ='2026-2030年盈利测算表'!Y11 -> 0.057415076
B12: 营业净收入（本行） | C12: ='2026-2030年盈利测算表'!L12 -> 1941.64 | D12: ='2026-2030年盈利测算表'!N12 -> 2027.8379 | E12: ='2026-2030年盈利测算表'!P12 -> 2090.0167 | F12: ='2026-2030年盈利测算表'!R12 -> 2184.245 | G12: ='2026-2030年盈利测算表'!T12 -> 2286.2919 | H12: ='2026-2030年盈利测算表'!V12 -> 2374.435 | I12: ='2026-2030年盈利测算表'!X12 -> 432.79497 | J12: ='2026-2030年盈利测算表'!Y12 -> 0.041066122
B13: 其中：利息净收入 | C13: ='2026-2030年盈利测算表'!L13 -> 1359.33 | D13: ='2026-2030年盈利测算表'!N13 -> 1398.7484 | E13: ='2026-2030年盈利测算表'!P13 -> 1456.7307 | F13: ='2026-2030年盈利测算表'!R13 -> 1520.0171 | G13: ='2026-2030年盈利测算表'!T13 -> 1582.4091 | H13: ='2026-2030年盈利测算表'!V13 -> 1625.5724 | I13: ='2026-2030年盈利测算表'!X13 -> 266.24242 | J13: ='2026-2030年盈利测算表'!Y13 -> 0.036421192
B14: 非利息净收入 | C14: ='2026-2030年盈利测算表'!L14 -> 582.31 | D14: ='2026-2030年盈利测算表'!N14 -> 629.08942 | E14: ='2026-2030年盈利测算表'!P14 -> 633.28595 | F14: ='2026-2030年盈利测算表'!R14 -> 664.22788 | G14: ='2026-2030年盈利测算表'!T14 -> 703.88282 | H14: ='2026-2030年盈利测算表'!V14 -> 748.86255 | I14: ='2026-2030年盈利测算表'!X14 -> 166.55255 | J14: ='2026-2030年盈利测算表'!Y14 -> 0.051597566
B15: 二、一级核心指标（并表）
B16: 总资产 | C16: ='2026-2030年盈利测算表'!L16 -> 101316.58 | D16: ='2026-2030年盈利测算表'!N16 -> 107999.58 | E16: ='2026-2030年盈利测算表'!P16 -> 114699.58 | F16: ='2026-2030年盈利测算表'!R16 -> 119599.58 | G16: ='2026-2030年盈利测算表'!T16 -> 124699.58 | H16: ='2026-2030年盈利测算表'!V16 -> 129999.58 | I16: ='2026-2030年盈利测算表'!X16 -> 28683 | J16: ='2026-2030年盈利测算表'!Y16 -> 0.051119966
B17: ROE | C17: ='2026-2030年盈利测算表'!L17 -> 0.0939 | D17: ='2026-2030年盈利测算表'!N17 -> 0.095294354 | E17: ='2026-2030年盈利测算表'!P17 -> 0.095069286 | F17: ='2026-2030年盈利测算表'!R17 -> 0.0922937 | G17: ='2026-2030年盈利测算表'!T17 -> 0.091916814 | H17: ='2026-2030年盈利测算表'!V17 -> 0.091152488 | I17: ='2026-2030年盈利测算表'!X17 -> -0.0027475118
B18: RAROC | C18: ='2026-2030年盈利测算表'!L18 -> 0.0881 | D18: ='2026-2030年盈利测算表'!N18 -> 0.087980207 | E18: ='2026-2030年盈利测算表'!P18 -> 0.087539869 | F18: ='2026-2030年盈利测算表'!R18 -> 0.087814458 | G18: ='2026-2030年盈利测算表'!T18 -> 0.089743652 | H18: ='2026-2030年盈利测算表'!V18 -> 0.090961541 | I18: ='2026-2030年盈利测算表'!X18 -> 0.0028615414
B19: 核心一级资本充足率 | C19: ='2026-2030年盈利测算表'!L19 -> 0.0948 | D19: ='2026-2030年盈利测算表'!N19 -> 0.095730282 | E19: ='2026-2030年盈利测算表'!P19 -> 0.099696284 | F19: ='2026-2030年盈利测算表'!R19 -> 0.10129985 | G19: ='2026-2030年盈利测算表'!T19 -> 0.10303652 | H19: ='2026-2030年盈利测算表'!V19 -> 0.10472588 | I19: ='2026-2030年盈利测算表'!X19 -> 0.0099258831
B20: 三、二级核心指标（并表）
B21: 生息资产日均 | C21: ='2026-2030年盈利测算表'!L21 -> 88562.26 | D21: ='2026-2030年盈利测算表'!N21 -> 92357.244 | E21: ='2026-2030年盈利测算表'!P21 -> 100806.96 | F21: ='2026-2030年盈利测算表'!R21 -> 106212.59 | G21: ='2026-2030年盈利测算表'!T21 -> 110798.4 | H21: ='2026-2030年盈利测算表'!V21 -> 115610.38 | I21: ='2026-2030年盈利测算表'!X21 -> 27048.122 | J21: ='2026-2030年盈利测算表'!Y21 -> 0.054750232
B22: 生息资产占比（日均） | C22: ='2026-2030年盈利测算表'!L22 -> 0.90073889 | D22: ='2026-2030年盈利测算表'!N22 -> 0.91384354 | E22: ='2026-2030年盈利测算表'!P22 -> 0.91260154 | F22: ='2026-2030年盈利测算表'!R22 -> 0.91416923 | G22: ='2026-2030年盈利测算表'!T22 -> 0.91566453 | H22: ='2026-2030年盈利测算表'!V22 -> 0.91707937 | I22: ='2026-2030年盈利测算表'!X22 -> 0.016340478
B23: 净息差 | C23: ='2026-2030年盈利测算表'!L23 -> 0.016312705 | D23: ='2026-2030年盈利测算表'!N23 -> 0.016101826 | E23: ='2026-2030年盈利测算表'!P23 -> 0.015817902 | F23: ='2026-2030年盈利测算表'!R23 -> 0.015739205 | G23: ='2026-2030年盈利测算表'!T23 -> 0.015806033 | H23: ='2026-2030年盈利测算表'!V23 -> 0.015671533 | I23: ='2026-2030年盈利测算表'!X23 -> -0.00064117211
B24: 非息收入占比 | C24: ='2026-2030年盈利测算表'!L24 -> 0.32006589 | D24: ='2026-2030年盈利测算表'!N24 -> 0.3300911 | E24: ='2026-2030年盈利测算表'!P24 -> 0.31986476 | F24: ='2026-2030年盈利测算表'!R24 -> 0.32082168 | G24: ='2026-2030年盈利测算表'!T24 -> 0.32411219 | H24: ='2026-2030年盈利测算表'!V24 -> 0.33079783 | I24: ='2026-2030年盈利测算表'!X24 -> 0.010731936
B25: 成本收入比 | C25: ='2026-2030年盈利测算表'!L25 -> 0.31607954 | D25: ='2026-2030年盈利测算表'!N25 -> 0.31607954 | E25: ='2026-2030年盈利测算表'!P25 -> 0.31557954 | F25: ='2026-2030年盈利测算表'!R25 -> 0.31507954 | G25: ='2026-2030年盈利测算表'!T25 -> 0.31457954 | H25: ='2026-2030年盈利测算表'!V25 -> 0.31407954 | I25: ='2026-2030年盈利测算表'!X25 -> -0.002
B26: 风险成本率 | C26: ='2026-2030年盈利测算表'!L26 -> 0.2737828 | D26: ='2026-2030年盈利测算表'!N26 -> 0.2687828 | E26: ='2026-2030年盈利测算表'!P26 -> 0.2637828 | F26: ='2026-2030年盈利测算表'!R26 -> 0.2587828 | G26: ='2026-2030年盈利测算表'!T26 -> 0.2537828 | H26: ='2026-2030年盈利测算表'!V26 -> 0.2487828 | I26: ='2026-2030年盈利测算表'!X26 -> -0.025
B27: 税务成本率 | C27: ='2026-2030年盈利测算表'!L27 -> 0.069255206 | D27: ='2026-2030年盈利测算表'!N27 -> 0.069255206 | E27: ='2026-2030年盈利测算表'!P27 -> 0.069255206 | F27: ='2026-2030年盈利测算表'!R27 -> 0.069255206 | G27: ='2026-2030年盈利测算表'!T27 -> 0.069255206 | H27: ='2026-2030年盈利测算表'!V27 -> 0.069255206 | I27: ='2026-2030年盈利测算表'!X27 -> 0
B28: 综合风险权重 | C28: ='2026-2030年盈利测算表'!L28 -> 0.75026761 | D28: ='2026-2030年盈利测算表'!N28 -> 0.75809131 | E28: ='2026-2030年盈利测算表'!P28 -> 0.7653228 | F28: ='2026-2030年盈利测算表'!R28 -> 0.77412488 | G28: ='2026-2030年盈利测算表'!T28 -> 0.77735417 | H28: ='2026-2030年盈利测算表'!V28 -> 0.78102084 | I28: ='2026-2030年盈利测算表'!X28 -> 0.030753229
B29: 其中：本行 | C29: =资本!L93 -> 0.73882582 | D29: =资本!M93 -> 0.73527171 | E29: =资本!N93 -> 0.73753298 | F29: =资本!O93 -> 0.74437169 | G29: =资本!P93 -> 0.74742416 | H29: =资本!Q93 -> 0.75164085 | I29: =H29-C29 -> 0.012815038
B30: 子公司 | C30: =子公司!L121 -> 1.0143933 | D30: =子公司!N121 -> 1.0991803 | E30: =子公司!P121 -> 1.0730382 | F30: =子公司!R121 -> 1.0663262 | G30: =子公司!T121 -> 1.0553433 | H30: =子公司!V121 -> 1.0337519 | I30: =H30-C30 -> 0.019358611
B31: 本行规模占比 | C31: ='2026-2030年盈利测算表'!L199 -> 0.93938183 | D31: ='2026-2030年盈利测算表'!N199 -> 0.93874939 | E31: ='2026-2030年盈利测算表'!P199 -> 0.91930027 | F31: ='2026-2030年盈利测算表'!R199 -> 0.91531591 | G31: ='2026-2030年盈利测算表'!T199 -> 0.91077129 | H31: ='2026-2030年盈利测算表'!V199 -> 0.90536625 | I31: =H31-C31 -> -0.034015574
B32: 四、其他指标（本行）
B33: 净息差 | C33: ='2026-2030年盈利测算表'!L30 -> 0.016376089 | D33: ='2026-2030年盈利测算表'!N30 -> 0.016226546 | E33: ='2026-2030年盈利测算表'!P30 -> 0.015620824 | F33: ='2026-2030年盈利测算表'!R30 -> 0.015656156 | G33: ='2026-2030年盈利测算表'!T30 -> 0.016 | H33: ='2026-2030年盈利测算表'!V30 -> 0.015529954 | I33: ='2026-2030年盈利测算表'!X30 -> -0.00084613518
B34: 生息资产日均 | C34: ='2026-2030年盈利测算表'!L53 -> 83007 | D34: ='2026-2030年盈利测算表'!N53 -> 86201.245 | E34: ='2026-2030年盈利测算表'!P53 -> 93255.692 | F34: ='2026-2030年盈利测算表'!R53 -> 97087.509 | G34: ='2026-2030年盈利测算表'!T53 -> 100835.36 | H34: ='2026-2030年盈利测算表'!V53 -> 104673.36 | I34: ='2026-2030年盈利测算表'!X53 -> 21666.36 | J34: ='2026-2030年盈利测算表'!Y53 -> 0.047476503
B35: 信贷资产占比（一般贷款/总资产，时点，人民币） | C35: ='2026-2030年盈利测算表'!L32 -> 0.56379388 | D35: ='2026-2030年盈利测算表'!N32 -> 0.56215249 | E35: ='2026-2030年盈利测算表'!P32 -> 0.56811999 | F35: ='2026-2030年盈利测算表'!R32 -> 0.57145845 | G35: ='2026-2030年盈利测算表'!T32 -> 0.57188144 | H35: ='2026-2030年盈利测算表'!V32 -> 0.56995208 | I35: ='2026-2030年盈利测算表'!X32 -> 0.0061581994
B36: 自营存款占比（时点，人民币） | C36: ='2026-2030年盈利测算表'!L33 -> 0.66132456 | D36: ='2026-2030年盈利测算表'!N33 -> 0.65691877 | E36: ='2026-2030年盈利测算表'!P33 -> 0.6767207 | F36: ='2026-2030年盈利测算表'!R33 -> 0.69682107 | G36: ='2026-2030年盈利测算表'!T33 -> 0.7168917 | H36: ='2026-2030年盈利测算表'!V33 -> 0.73792925 | I36: ='2026-2030年盈利测算表'!X33 -> 0.076604693
B37: 零售存款占比（日均） | C37: ='2026-2030年盈利测算表'!L34 -> 0.28711748 | D37: ='2026-2030年盈利测算表'!N34 -> 0.29448384 | E37: ='2026-2030年盈利测算表'!P34 -> 0.30511638 | F37: ='2026-2030年盈利测算表'!R34 -> 0.31361856 | G37: ='2026-2030年盈利测算表'!T34 -> 0.32224574 | H37: ='2026-2030年盈利测算表'!V34 -> 0.33095178 | I37: ='2026-2030年盈利测算表'!X34 -> 0.0438343
B38: 人民币市场化负债占比（日均） | C38: ='2026-2030年盈利测算表'!L37 -> 0.33330385 | D38: ='2026-2030年盈利测算表'!N37 -> 0.32185827 | E38: ='2026-2030年盈利测算表'!P37 -> 0.33462483 | F38: ='2026-2030年盈利测算表'!R37 -> 0.31515159 | G38: ='2026-2030年盈利测算表'!T37 -> 0.2950099 | H38: ='2026-2030年盈利测算表'!V37 -> 0.27277382 | I38: ='2026-2030年盈利测算表'!X37 -> -0.060530025
B39: 存贷比（一般性贷款/自营存款，人民币时点） | C39: ='2026-2030年盈利测算表'!L38 -> 0.95724308 | D39: ='2026-2030年盈利测算表'!N38 -> 0.94141015 | E39: ='2026-2030年盈利测算表'!P38 -> 0.92584271 | F39: ='2026-2030年盈利测算表'!R38 -> 0.91450875 | G39: ='2026-2030年盈利测算表'!T38 -> 0.89807765 | H39: ='2026-2030年盈利测算表'!V38 -> 0.8774872 | I39: ='2026-2030年盈利测算表'!X38 -> -0.079755884
B40: 日均存贷比（一般性贷款/自营存款） | C40: ='2026-2030年盈利测算表'!L39 -> 0.96637441 | D40: ='2026-2030年盈利测算表'!N39 -> 0.95797941 | E40: ='2026-2030年盈利测算表'!P39 -> 0.94317034 | F40: ='2026-2030年盈利测算表'!R39 -> 0.92941109 | G40: ='2026-2030年盈利测算表'!T39 -> 0.91345717 | H40: ='2026-2030年盈利测算表'!V39 -> 0.89089007 | I40: ='2026-2030年盈利测算表'!X39 -> -0.075484342
B41: 外币资负差（负债-资产，时点，亿美元） | C41: ='2026-2030年盈利测算表'!L40 -> 0.52633377 | D41: ='2026-2030年盈利测算表'!N40 -> -134.47367 | E41: ='2026-2030年盈利测算表'!P40 -> -114.47367 | F41: ='2026-2030年盈利测算表'!R40 -> -44.473666 | G41: ='2026-2030年盈利测算表'!T40 -> 25.526334 | H41: ='2026-2030年盈利测算表'!V40 -> 95.526334 | I41: ='2026-2030年盈利测算表'!X40 -> 95
B42: 风险加权资产 | C42: ='2026-2030年盈利测算表'!L41 -> 70317.595 | D42: ='2026-2030年盈利测算表'!N41 -> 74206.805 | E42: ='2026-2030年盈利测算表'!P41 -> 78335.352 | F42: ='2026-2030年盈利测算表'!R41 -> 81640.87 | G42: ='2026-2030年盈利测算表'!T41 -> 85067.514 | H42: ='2026-2030年盈利测算表'!V41 -> 88764.252 | I42: ='2026-2030年盈利测算表'!X41 -> 18446.657 | J42: ='2026-2030年盈利测算表'!Y41 -> 0.047694872
B43: AC类投资收益率 | C43: ='2026-2030年盈利测算表'!L42 -> 0.023086202 | D43: ='2026-2030年盈利测算表'!N42 -> 0.020921025 | E43: ='2026-2030年盈利测算表'!P42 -> 0.019838999 | F43: ='2026-2030年盈利测算表'!R42 -> 0.020036364 | G43: ='2026-2030年盈利测算表'!T42 -> 0.019690909 | H43: ='2026-2030年盈利测算表'!V42 -> 0.019 | I43: ='2026-2030年盈利测算表'!X42 -> -0.0040862023
B44: FVOCI及FVTPL类综合收益率（含公允价值变动） | C44: ='2026-2030年盈利测算表'!L43 -> 0.02610136 | D44: ='2026-2030年盈利测算表'!N43 -> 0.028273079 | E44: ='2026-2030年盈利测算表'!P43 -> 0.022780585 | F44: ='2026-2030年盈利测算表'!R43 -> 0.023453633 | G44: ='2026-2030年盈利测算表'!T43 -> 0.024428886 | H44: ='2026-2030年盈利测算表'!V43 -> 0.025429763 | I44: ='2026-2030年盈利测算表'!X43 -> -0.00067159723
B45: 核心一级资本充足率 | C45: ='2026-2030年盈利测算表'!L44 -> 0.089842865 | D45: ='2026-2030年盈利测算表'!N44 -> 0.091420724 | E45: ='2026-2030年盈利测算表'!P44 -> 0.095382528 | F45: ='2026-2030年盈利测算表'!R44 -> 0.09688138 | G45: ='2026-2030年盈利测算表'!T44 -> 0.09855918 | H45: ='2026-2030年盈利测算表'!V44 -> 0.10017424 | I45: ='2026-2030年盈利测算表'!X44 -> 0.010331371
B46: 金市RAROC | C46: =板块!F58 -> 0.25503569 | D46: =板块!H58 -> 0.24120484 | E46: =板块!J58 -> 0.22831657 | F46: =板块!L58 -> 0.22395712 | G46: =板块!N58 -> 0.21972907 | H46: =板块!P58 -> 0.21553787 | I46: =H46-C46 -> -0.03949782
B47: PVBP单位产出（AC和FVOCI） | C47: ='2026-2030年盈利测算表'!L198 -> 66.286583 | D47: ='2026-2030年盈利测算表'!N198 -> 54.532887 | E47: ='2026-2030年盈利测算表'!P198 -> 52.997758 | F47: ='2026-2030年盈利测算表'!R198 -> 51.073207 | G47: ='2026-2030年盈利测算表'!T198 -> 48.347417 | H47: ='2026-2030年盈利测算表'!V198 -> 45.230335 | I47: =H47-C47 -> -21.056248
B48: LCR | C48: ='2026-2030年盈利测算表'!L45 -> 1.4678879 | D48: ='2026-2030年盈利测算表'!N45 -> 1.5490348 | E48: ='2026-2030年盈利测算表'!P45 -> 1.5859068 | F48: ='2026-2030年盈利测算表'!R45 -> 1.6092104 | G48: ='2026-2030年盈利测算表'!T45 -> 1.6146604 | H48: ='2026-2030年盈利测算表'!V45 -> 1.6262955 | I48: ='2026-2030年盈利测算表'!X45 -> 0.15840764
B49: NSFR | C49: ='2026-2030年盈利测算表'!L46 -> 1.0472498 | D49: ='2026-2030年盈利测算表'!N46 -> 1.0740923 | E49: ='2026-2030年盈利测算表'!P46 -> 1.0970978 | F49: ='2026-2030年盈利测算表'!R46 -> 1.1205338 | G49: ='2026-2030年盈利测算表'!T46 -> 1.1458257 | H49: ='2026-2030年盈利测算表'!V46 -> 1.1741752 | I49: ='2026-2030年盈利测算表'!X46 -> 0.1269254
B50: △EVE | C50: ='2026-2030年盈利测算表'!L47 -> 0.1049 | D50: ='2026-2030年盈利测算表'!N47 -> 0.11154854 | E50: ='2026-2030年盈利测算表'!P47 -> 0.10817813 | F50: ='2026-2030年盈利测算表'!R47 -> 0.11248077 | G50: ='2026-2030年盈利测算表'!T47 -> 0.11366561 | H50: ='2026-2030年盈利测算表'!V47 -> 0.1154522 | I50: ='2026-2030年盈利测算表'!X47 -> 0.010552199
A51: 项目 | B51: 指标 | C51: 2025实际 | D51: 积极情景
D52: 2026年 | E52: 2027年 | F52: 2028年 | G52: 2029年 | H52: 2030年 | I52: 十五五总增量/累计变化
A53: 重要参数 | B53: 10年期国债收益率 | C53: ='2026-2030年盈利测算表'!L48 -> 0.0185 | D53: ='2026-2030年盈利测算表'!N48 -> 0.0175 | E53: ='2026-2030年盈利测算表'!P48 -> 0.0175 | F53: ='2026-2030年盈利测算表'!R48 -> 0.0175 | G53: ='2026-2030年盈利测算表'!T48 -> 0.0175 | H53: ='2026-2030年盈利测算表'!V48 -> 0.0175 | I53: =H53-C53 -> -0.001
B54: 金市RAROC目标（不含AC和FVOCI投资收益） | C54: =板块!F133 -> 0.18394832 | D54: =板块!H133 -> 0.18394832 | E54: =板块!J133 -> 0.18194832 | F54: =板块!L133 -> 0.17994832 | G54: =板块!N133 -> 0.17794832 | H54: =板块!P133 -> 0.17594832 | I54: =H54-C54 -> -0.008
B55: AC类投资收益 | C55: =中收测算表!$Y$8 -> 44.5 | D55: =中收测算表!$Y$9 -> 40 | E55: =中收测算表!$Y$10 -> 35 | F55: =中收测算表!$Y$11 -> 35 | G55: =中收测算表!$Y$12 -> 35 | H55: =中收测算表!$Y$13 -> 35 | I55: =H55-C55 -> -9.5
B56: FVOCI类投资收益 | C56: =中收测算表!$W$8 -> 73.6 | D56: =中收测算表!$W$9 -> 70 | E56: =中收测算表!$W$10 -> 60 | F56: =中收测算表!$W$11 -> 60 | G56: =中收测算表!$W$12 -> 60 | H56: =中收测算表!$W$13 -> 60 | I56: =H56-C56 -> -13.6
B57: 并表RWA增量 | D57: =资本!F55 -> 4989.2106 | E57: =资本!J55 -> 6771.5467 | F57: =资本!N55 -> 4168.5182 | G57: =资本!R55 -> 4361.6439 | H57: =资本!V55 -> 4656.738 | I57: =SUM(D57:H57) -> 24947.657 | J57: -
B58: 本行RWA增量 | D58: =资本!F53 -> 3889.2106 | E58: =资本!J53 -> 4128.5467 | F58: =资本!N53 -> 3305.5182 | G58: =资本!R53 -> 3426.6439 | H58: =资本!V53 -> 3696.738 | I58: =SUM(D58:H58) -> 18446.657 | J58: -
B59: ——金市RWA增量 | D59: =资本!G51 -> 1613.1173 | E59: =资本!K51 -> 865.14361 | F59: =资本!O51 -> 748.82456 | G59: =资本!S51 -> 784.76023 | H59: =资本!W51 -> 857.96341 | I59: =SUM(D59:H59) -> 4869.8091 | J59: -
B60: ——表外业务RWA增量 | D60: =资本!G33 -> 287.54156 | E60: =资本!K33 -> 294.77678 | F60: =资本!O33 -> 313.89618 | G60: =资本!S33 -> 334.30514 | H60: =资本!W33 -> 356.09931 | I60: =SUM(D60:H60) -> 1586.619 | J60: -
B61: ——抵债资产和资管回表RWA增量 | D61: =资本!G43+资本!G44 -> -200 | E61: =资本!K43+资本!K44 -> -200 | F61: =资本!O43+资本!O44 -> -200 | G61: =资本!S43+资本!S44 -> -200 | H61: =资本!W43+资本!W44 -> -200 | I61: =SUM(D61:H61) -> -1000 | J61: -
B62: ——交易对手信用风险和市场风险RWA增量 | D62: =资本!G42 -> 200.1 | E62: =资本!K42 -> 230.115 | F62: =资本!O42 -> 264.63225 | G62: =资本!S42 -> 304.32709 | H62: =资本!W42 -> 349.97615 | I62: =SUM(D62:H62) -> 1349.1505 | J62: -
B63: 子公司RWA增量 | D63: =资本!F54 -> 1100 | E63: =资本!J54 -> 2643 | F63: =资本!N54 -> 863 | G63: =资本!R54 -> 935 | H63: =资本!V54 -> 960 | I63: =SUM(D63:H63) -> 6501 | J63: -
B64: 每年新投中长期贷款规模 | D64: =息差测算表!L6 -> 800 | E64: =息差测算表!M6 -> 1000 | F64: =息差测算表!N6 -> 1200 | G64: =息差测算表!O6 -> 1400 | H64: =息差测算表!P6 -> 1600 | I64: =SUM(D64:H64) -> 6000 | J64: -
B65: 每年福费廷置换流贷规模 | D65: =息差测算表!L17 -> 250 | E65: =息差测算表!M17 -> 250 | F65: =息差测算表!N17 -> 250 | G65: =息差测算表!O17 -> 250 | H65: =息差测算表!P17 -> 250 | I65: =SUM(D65:H65) -> 1250 | J65: -
B66: PVBP增量（AC） | D66: =中收测算表!AE15 -> 0.5 | E66: =中收测算表!AF15 -> 0.25 | F66: =中收测算表!AG15 -> 0.25 | G66: =中收测算表!AH15 -> 0.25 | H66: =中收测算表!AI15 -> 0.25 | I66: =SUM(D66:H66) -> 1.5 | J66: -
B67: PVBP增量（FVOCI） | D67: =中收测算表!AE16 -> 0.91 | E67: =中收测算表!AF16 -> 0.45 | F67: =中收测算表!AG16 -> 0.45 | G67: =中收测算表!AH16 -> 0.45 | H67: =中收测算表!AI16 -> 0.45 | I67: =SUM(D67:H67) -> 2.71 | J67: -
A68: 项目 | B68: 指标 | C68: 2025实际余额 | D68: 2026增量 | E68: 2027增量 | F68: 2028增量 | G68: 2029增量 | H68: 2030增量 | I68: 十五五总增量/累计变化 | J68: 复合增速
A69: 规模假设 | B69: 资产端
B70: 1.人民币各项贷款（时点） | C70: ='2026-2030年盈利测算表'!L57 -> 57741.413 | D70: ='2026-2030年盈利测算表'!O57 -> 1700 | E70: ='2026-2030年盈利测算表'!Q57 -> 2000 | F70: ='2026-2030年盈利测算表'!S57 -> 2300 | G70: ='2026-2030年盈利测算表'!U57 -> 2500 | H70: ='2026-2030年盈利测算表'!W57 -> 2500 | I70: ='2026-2030年盈利测算表'!X57 -> 11000 | J70: ='2026-2030年盈利测算表'!Y57 -> 0.035490716
B71: 1.1.对公一般贷款（时点） | C71: ='2026-2030年盈利测算表'!L60 -> 29293.131 | D71: ='2026-2030年盈利测算表'!O60 -> 3000 | E71: ='2026-2030年盈利测算表'!Q60 -> 2750 | F71: ='2026-2030年盈利测算表'!S60 -> 2500 | G71: ='2026-2030年盈利测算表'!U60 -> 2250 | H71: ='2026-2030年盈利测算表'!W60 -> 2000 | I71: ='2026-2030年盈利测算表'!X60 -> 12500 | J71: ='2026-2030年盈利测算表'!Y60 -> 0.073662594
B72: 日均 | C72: ='2026-2030年盈利测算表'!L61 -> 28337.351 | D72: ='2026-2030年盈利测算表'!O61 -> 3000 | E72: ='2026-2030年盈利测算表'!Q61 -> 2680 | F72: ='2026-2030年盈利测算表'!S61 -> 2440 | G72: ='2026-2030年盈利测算表'!U61 -> 2190 | H72: ='2026-2030年盈利测算表'!W61 -> 1970 | I72: ='2026-2030年盈利测算表'!X61 -> 12280 | J72: ='2026-2030年盈利测算表'!Y61 -> 0.074658477
B73: 1.2.个人贷款（时点） | C73: ='2026-2030年盈利测算表'!L63 -> 18334.921 | D73: ='2026-2030年盈利测算表'!O63 -> -150 | E73: ='2026-2030年盈利测算表'!Q63 -> 0 | F73: ='2026-2030年盈利测算表'!S63 -> 100 | G73: ='2026-2030年盈利测算表'!U63 -> 100 | H73: ='2026-2030年盈利测算表'!W63 -> 100 | I73: ='2026-2030年盈利测算表'!X63 -> 150 | J73: ='2026-2030年盈利测算表'!Y63 -> 0.0016308937
B74: 1.3.信用卡贷款（时点） | C74: ='2026-2030年盈利测算表'!L66 -> 4615.1776 | D74: ='2026-2030年盈利测算表'!O66 -> -200 | E74: ='2026-2030年盈利测算表'!Q66 -> -100 | F74: ='2026-2030年盈利测算表'!S66 -> 0 | G74: ='2026-2030年盈利测算表'!U66 -> 0 | H74: ='2026-2030年盈利测算表'!W66 -> 0 | I74: ='2026-2030年盈利测算表'!X66 -> -300 | J74: ='2026-2030年盈利测算表'!Y66 -> -0.013352428
B75: 1.4.票据贴现（时点） | C75: ='2026-2030年盈利测算表'!L69 -> 2013.4008 | D75: ='2026-2030年盈利测算表'!O69 -> -500 | E75: ='2026-2030年盈利测算表'!Q69 -> -200 | F75: ='2026-2030年盈利测算表'!S69 -> 0 | G75: ='2026-2030年盈利测算表'!U69 -> 0 | H75: ='2026-2030年盈利测算表'!W69 -> 0 | I75: ='2026-2030年盈利测算表'!X69 -> -700 | J75: ='2026-2030年盈利测算表'!Y69 -> -0.081892771
B76: 日均 | C76: ='2026-2030年盈利测算表'!L70 -> 2620.9618 | D76: ='2026-2030年盈利测算表'!O70 -> -1053 | E76: ='2026-2030年盈利测算表'!Q70 -> -100 | F76: ='2026-2030年盈利测算表'!S70 -> 0 | G76: ='2026-2030年盈利测算表'!U70 -> 0 | H76: ='2026-2030年盈利测算表'!W70 -> 0 | I76: ='2026-2030年盈利测算表'!X70 -> -1153 | J76: ='2026-2030年盈利测算表'!Y70 -> -0.10946537
B77: 1.5.非银贷款（时点） | C77: ='2026-2030年盈利测算表'!L71 -> 3484.7825 | D77: =D70-D71-D73-D74-D75 -> -450 | E77: =E70-E71-E73-E74-E75 -> -450 | F77: =F70-F71-F73-F74-F75 -> -300 | G77: =G70-G71-G73-G74-G75 -> 150 | H77: =H70-H71-H73-H74-H75 -> 400 | I77: =SUM(D77:H77) -> -650
B78: 日均 | C78: ='2026-2030年盈利测算表'!L72 -> 3413.31 | D78: ='2026-2030年盈利测算表'!O72 -> -232 | E78: ='2026-2030年盈利测算表'!Q72 -> -371.5275 | F78: ='2026-2030年盈利测算表'!S72 -> -375 | G78: ='2026-2030年盈利测算表'!U72 -> -75 | H78: ='2026-2030年盈利测算表'!W72 -> 275 | I78: ='2026-2030年盈利测算表'!X72 -> -778.5275 | J78: ='2026-2030年盈利测算表'!Y72 -> -0.050458813
B79: 2.人民币非信贷业务
B80: 2.1 债券投资
B81: 2.1.1金市自营债券（人民币，时点，AC和FVOCI） | C81: ='2026-2030年盈利测算表'!L78 -> 12358 | D81: ='2026-2030年盈利测算表'!O78 -> 1500 | E81: ='2026-2030年盈利测算表'!Q78 -> 1000 | F81: ='2026-2030年盈利测算表'!S78 -> 1000 | G81: ='2026-2030年盈利测算表'!U78 -> 1000 | H81: ='2026-2030年盈利测算表'!W78 -> 1000 | I81: ='2026-2030年盈利测算表'!X78 -> 5500 | J81: ='2026-2030年盈利测算表'!Y78 -> 0.076408022
B82: 2.1.2司库债券（时点） | C82: ='2026-2030年盈利测算表'!L81 -> 5027 | D82: ='2026-2030年盈利测算表'!O81 -> 0 | E82: ='2026-2030年盈利测算表'!Q81 -> 0 | F82: ='2026-2030年盈利测算表'!S81 -> 0 | G82: ='2026-2030年盈利测算表'!U81 -> 0 | H82: ='2026-2030年盈利测算表'!W81 -> 0 | I82: ='2026-2030年盈利测算表'!X81 -> 0 | J82: ='2026-2030年盈利测算表'!Y81 -> 0
B83: 2.2结构化融资（时点） | C83: ='2026-2030年盈利测算表'!L84 -> 2043 | D83: ='2026-2030年盈利测算表'!O84 -> 0 | E83: ='2026-2030年盈利测算表'!Q84 -> 0 | F83: ='2026-2030年盈利测算表'!S84 -> 0 | G83: ='2026-2030年盈利测算表'!U84 -> 0 | H83: ='2026-2030年盈利测算表'!W84 -> 0 | I83: ='2026-2030年盈利测算表'!X84 -> 0 | J83: ='2026-2030年盈利测算表'!Y84 -> 0
B84: 2.4TPL（时点） | C84: ='2026-2030年盈利测算表'!L95 -> 6631 | D84: ='2026-2030年盈利测算表'!O95 -> 200 | E84: ='2026-2030年盈利测算表'!Q95 -> 100 | F84: ='2026-2030年盈利测算表'!S95 -> 100 | G84: ='2026-2030年盈利测算表'!U95 -> 100 | H84: ='2026-2030年盈利测算表'!W95 -> 100 | I84: ='2026-2030年盈利测算表'!X95 -> 600 | J84: ='2026-2030年盈利测算表'!Y95 -> 0.01747528
B85: 2.5其他非生息资产（时点） | C85: ='2026-2030年盈利测算表'!L97 -> 2275.1655 | D85: ='2026-2030年盈利测算表'!O97 -> 0 | E85: ='2026-2030年盈利测算表'!Q97 -> 0 | F85: ='2026-2030年盈利测算表'!S97 -> 0 | G85: ='2026-2030年盈利测算表'!U97 -> 0 | H85: ='2026-2030年盈利测算表'!W97 -> 0 | I85: ='2026-2030年盈利测算表'!X97 -> 0 | J85: ='2026-2030年盈利测算表'!Y97 -> 0
B86: 3.外币贷款（时点） | C86: ='2026-2030年盈利测算表'!L100 -> 143.59 | D86: ='2026-2030年盈利测算表'!O100 -> 20 | E86: ='2026-2030年盈利测算表'!Q100 -> 50 | F86: ='2026-2030年盈利测算表'!S100 -> 50 | G86: ='2026-2030年盈利测算表'!U100 -> 50 | H86: ='2026-2030年盈利测算表'!W100 -> 50 | I86: ='2026-2030年盈利测算表'!X100 -> 220 | J86: ='2026-2030年盈利测算表'!Y100 -> 0.20419702
B87: 4.外币非信贷业务
B88: 4.1外币债券（时点） | C88: ='2026-2030年盈利测算表'!L105 -> 75.51 | D88: ='2026-2030年盈利测算表'!O105 -> 150 | E88: ='2026-2030年盈利测算表'!Q105 -> 5 | F88: ='2026-2030年盈利测算表'!S105 -> -45 | G88: ='2026-2030年盈利测算表'!U105 -> -45 | H88: ='2026-2030年盈利测算表'!W105 -> -45 | I88: ='2026-2030年盈利测算表'!X105 -> 20 | J88: ='2026-2030年盈利测算表'!Y105 -> 0.048114852
B89: 4.2.外币同业资产（时点） | C89: ='2026-2030年盈利测算表'!L107 -> 97 | D89: ='2026-2030年盈利测算表'!O107 -> 0 | E89: ='2026-2030年盈利测算表'!Q107 -> 0 | F89: ='2026-2030年盈利测算表'!S107 -> 0 | G89: ='2026-2030年盈利测算表'!U107 -> 0 | H89: ='2026-2030年盈利测算表'!W107 -> 0 | I89: ='2026-2030年盈利测算表'!X107 -> 0 | J89: ='2026-2030年盈利测算表'!Y107 -> 0
B90: 4.3 外币非生息资产
B91: 4.3.1 长期股权投资（时点） | C91: ='2026-2030年盈利测算表'!L111 -> 25 | D91: ='2026-2030年盈利测算表'!O111 -> 0 | E91: ='2026-2030年盈利测算表'!Q111 -> 0 | F91: ='2026-2030年盈利测算表'!S111 -> 0 | G91: ='2026-2030年盈利测算表'!U111 -> 0 | H91: ='2026-2030年盈利测算表'!W111 -> 0 | I91: ='2026-2030年盈利测算表'!X111 -> 0 | J91: ='2026-2030年盈利测算表'!Y111 -> 0
B92: 4.3.1.1 长期股权投资（日均） | C92: ='2026-2030年盈利测算表'!L112 -> 25 | D92: ='2026-2030年盈利测算表'!O112 -> 0 | E92: ='2026-2030年盈利测算表'!Q112 -> 0 | F92: ='2026-2030年盈利测算表'!S112 -> 0 | G92: ='2026-2030年盈利测算表'!U112 -> 0 | H92: ='2026-2030年盈利测算表'!W112 -> 0 | I92: ='2026-2030年盈利测算表'!X112 -> 0 | J92: ='2026-2030年盈利测算表'!Y112 -> 0
B93: 4.3.2 外币FVTPL（时点） | C93: ='2026-2030年盈利测算表'!L113 -> 17.65 | D93: ='2026-2030年盈利测算表'!O113 -> 5 | E93: ='2026-2030年盈利测算表'!Q113 -> 5 | F93: ='2026-2030年盈利测算表'!S113 -> 5 | G93: ='2026-2030年盈利测算表'!U113 -> 5 | H93: ='2026-2030年盈利测算表'!W113 -> 5 | I93: ='2026-2030年盈利测算表'!X113 -> 25 | J93: ='2026-2030年盈利测算表'!Y113 -> 0.19298468
B94: 附：海外分行资产（时点） | C94: ='2026-2030年盈利测算表'!L115 -> 34.438243 | D94: ='2026-2030年盈利测算表'!O115 -> 30 | E94: ='2026-2030年盈利测算表'!Q115 -> 30 | F94: ='2026-2030年盈利测算表'!S115 -> 35 | G94: ='2026-2030年盈利测算表'!U115 -> 35 | H94: ='2026-2030年盈利测算表'!W115 -> 36 | I94: ='2026-2030年盈利测算表'!X115 -> 166 | J94: ='2026-2030年盈利测算表'!Y115 -> 0.42228922
B95: 负债端
B96: 1.1.对公存款（时点） | C96: ='2026-2030年盈利测算表'!L127 -> 38909.669 | D96: ='2026-2030年盈利测算表'!O127 -> 1600 | E96: ='2026-2030年盈利测算表'!Q127 -> 1700 | F96: ='2026-2030年盈利测算表'!S127 -> 1800 | G96: ='2026-2030年盈利测算表'!U127 -> 1900 | H96: ='2026-2030年盈利测算表'!W127 -> 2000 | I96: ='2026-2030年盈利测算表'!X127 -> 9000 | J96: ='2026-2030年盈利测算表'!Y127 -> 0.04249295
B97: 对公存款（日均） | C97: ='2026-2030年盈利测算表'!L128 -> 38055.867 | D97: ='2026-2030年盈利测算表'!O128 -> 1300 | E97: ='2026-2030年盈利测算表'!Q128 -> 1700 | F97: ='2026-2030年盈利测算表'!S128 -> 1900 | G97: ='2026-2030年盈利测算表'!U128 -> 1900 | H97: ='2026-2030年盈利测算表'!W128 -> 2100 | I97: ='2026-2030年盈利测算表'!X128 -> 8900 | J97: ='2026-2030年盈利测算表'!Y128 -> 0.042926371
B98: 对公活期占比（日均） | C98: ='2026-2030年盈利测算表'!L35 -> 0.45808969 | D98: ='2026-2030年盈利测算表'!N35 -> 0.43431898 | E98: ='2026-2030年盈利测算表'!P35 -> 0.43703864 | F98: ='2026-2030年盈利测算表'!R35 -> 0.43982351 | G98: ='2026-2030年盈利测算表'!T35 -> 0.44237246 | H98: ='2026-2030年盈利测算表'!V35 -> 0.44494973 | I98: =H98-C98 -> -0.01313996
B99: 1.2.零售存款（时点） | C99: ='2026-2030年盈利测算表'!L133 -> 15566.18 | D99: ='2026-2030年盈利测算表'!O133 -> 1600 | E99: ='2026-2030年盈利测算表'!Q133 -> 1700 | F99: ='2026-2030年盈利测算表'!S133 -> 1800 | G99: ='2026-2030年盈利测算表'!U133 -> 1900 | H99: ='2026-2030年盈利测算表'!W133 -> 2000 | I99: ='2026-2030年盈利测算表'!X133 -> 9000 | J99: ='2026-2030年盈利测算表'!Y133 -> 0.095547256
B100: 零售存款（日均） | C100: ='2026-2030年盈利测算表'!L134 -> 15327.216 | D100: ='2026-2030年盈利测算表'!O134 -> 1100 | E100: ='2026-2030年盈利测算表'!Q134 -> 1600 | F100: ='2026-2030年盈利测算表'!S134 -> 1600 | G100: ='2026-2030年盈利测算表'!U134 -> 1700 | H100: ='2026-2030年盈利测算表'!W134 -> 1900 | I100: ='2026-2030年盈利测算表'!X134 -> 7900 | J100: ='2026-2030年盈利测算表'!Y134 -> 0.086692765
...

Sheet 2026-2030年盈利测算表
A1: 2026-2030年盈利测算表（积极情景） | AA1: 公式问题 | AB1: 回复
A2: 项目 | B2: 2020年 | D2: 2021年 | F2: 2022年 | H2: 2023年 | J2: 2024年 | L2: 2025年 | N2: 2026年 | P2: 2027年 | R2: 2028年 | T2: 2029年 | V2: 2030年 | X2: 十五五 总增量 | Y2: 十五五 复合增速
B3: 余额 | C3: 年增 | D3: 余额 | E3: 年增 | F3: 余额 | G3: 年增 | H3: 余额 | I3: 年增 | J3: 余额 | K3: 年增 | L3: 余额 | M3: 年增 | N3: 余额 | O3: 年增 | P3: 余额 | Q3: 年增 | R3: 余额 | S3: 年增 | T3: 余额 | U3: 年增 | V3: 余额 | W3: 年增
A4: 一、盈利结果
A5: （一）并表口径
A6: 归母净利润 | B6: 489.8 | C6: 9.65 | D6: 556.41 | E6: =D6-B6 -> 66.61 | F6: 621.03 | G6: =F6-D6 -> 64.62 | H6: 670.16 | I6: =H6-F6 -> 49.13 | J6: 685.76 | K6: =J6-H6 -> 15.6 | L6: 706.18 | M6: =L6-J6 -> 20.42 | N6: =N7*(1-N25-N26-N27)-10-子公司!N64 -> 757.81904 | O6: =N6-L6 -> 51.639042 | P6: =P7*(1-P25-P26-P27)-10-子公司!P64 -> 810.60057 | Q6: =P6-N6 -> 52.781523 | R6: =R7*(1-R25-R26-R27)-10-子公司!R64 -> 866.01284 | S6: =R6-P6 -> 55.412279 | T6: =T7*(1-T25-T26-T27)-10-子公司!T64 -> 927.36198 | U6: =T6-R6 -> 61.349135 | V6: =V7*(1-V25-V26-V27)-10-子公司!V64 -> 985.20062 | W6: =V6-T6 -> 57.838642 | X6: =V6-L6 -> 279.02062 | Y6: =(V6/L6)^(1/5)-1 -> 0.06886253
A7: 营业净收入 | B7: 1947.31 | C7: 71.47 | D7: 2045.57 | E7: =D7-B7 -> 98.26 | F7: 2113.92 | G7: =F7-D7 -> 68.35 | H7: 2058.96 | I7: =H7-F7 -> -54.96 | J7: 2136.46 | K7: =J7-H7 -> 77.5 | L7: 2124.75 | M7: =L7-J7 -> -11.71 | N7: =N8+N9 -> 2219.8843 | O7: =N7-L7 -> 95.134319 | P7: =P8+P9 -> 2344.467 | Q7: =P7-N7 -> 124.58265 | R7: =R8+R9 -> 2461.359 | S7: =R7-P7 -> 116.89202 | T7: =T8+T9 -> 2591.0856 | U7: =T7-R7 -> 129.72664 | V7: =V8+V9 -> 2707.3909 | W7: =V7-T7 -> 116.30528 | X7: =V7-L7 -> 582.64091 | Y7: =(V7/L7)^(1/5)-1 -> 0.049659947
A8: 其中：利息净收入 | B8: 1505.15 | C8: 35.9 | D8: 1478.96 | E8: =D8-B8 -> -26.19 | F8: 1506.47 | G8: =F8-D8 -> 27.51 | H8: 1435.39 | I8: =H8-F8 -> -71.08 | J8: 1466.79 | K8: =J8-H8 -> 31.4 | L8: 1444.69 | M8: =L8-J8 -> -22.1 | N8: =N13+子公司!N8 -> 1487.1203 | O8: =N8-L8 -> 42.430273 | P8: =P13+子公司!P8 -> 1594.5546 | Q8: =P8-N8 -> 107.43433 | R8: =R13+子公司!R8 -> 1671.7017 | S8: =R8-P8 -> 77.147054 | T8: =T13+子公司!T8 -> 1751.2832 | U8: =T8-R8 -> 79.581531 | V8: =V13+子公司!V8 -> 1811.7919 | W8: =V8-T8 -> 60.508699 | X8: =V8-L8 -> 367.10188 | Y8: =(V8/L8)^(1/5)-1 -> 0.046325305
A9: 非利息净收入 | B9: 442.16 | C9: 35.57 | D9: 566.61 | E9: =D9-B9 -> 124.45 | F9: 607.45 | G9: =F9-D9 -> 40.84 | H9: 623.57 | I9: =H9-F9 -> 16.12 | J9: 669.67 | K9: =J9-H9 -> 46.1 | L9: 680.06 | M9: =L9-J9 -> 10.39 | N9: =N14+子公司!N9-4 -> 732.76405 | O9: =N9-L9 -> 52.704046 | P9: =P14+子公司!P9-4 -> 749.91237 | Q9: =P9-N9 -> 17.148329 | R9: =R14+子公司!R9-4 -> 789.65734 | S9: =R9-P9 -> 39.744963 | T9: =T14+子公司!T9-4 -> 839.80245 | U9: =T9-R9 -> 50.145113 | V9: =V14+子公司!V9-4 -> 895.59903 | W9: =V9-T9 -> 55.796576 | X9: =V9-L9 -> 215.53903 | Y9: =(V9/L9)^(1/5)-1 -> 0.056606496 | AA9: 为什么要减4亿 | AB9: 合并抵消经验值
A10: （二）本行口径
A11: 净利润 | B11: 477.67 | C11: 21.75 | D11: 515.14 | E11: =D11-B11 -> 37.47 | F11: 578.95 | G11: =F11-D11 -> 63.81 | H11: 626.51 | I11: =H11-F11 -> 47.56 | J11: 663.72 | K11: =J11-H11 -> 37.21 | L11: 647.01 | M11: =L11-J11 -> -16.71 | N11: =N196*N12 -> 685.87278 | O11: =N11-L11 -> 38.862783 | P11: =P196*P12 -> 718.39854 | Q11: =P11-N11 -> 32.525753 | R11: =R196*R12 -> 762.80085 | S11: =R11-P11 -> 44.40232 | T11: =T196*T12 -> 811.01314 | U11: =T11-R11 -> 48.212286 | V11: =V196*V12 -> 855.33941 | W11: =V11-T11 -> 44.32627 | X11: =V11-L11 -> 208.32941 | Y11: =(V11/L11)^(1/5)-1 -> 0.057415076
A12: 营业净收入（本行） | B12: =B13+B14 -> 1853.01 | C12: =C13+C14 -> 73.073854 | D12: 1914 | E12: =D12-B12 -> 60.99 | F12: 1981 | G12: =F12-D12 -> 67 | H12: 1912 | I12: =H12-F12 -> -69 | J12: 2003 | K12: =J12-H12 -> 91 | L12: =L13+L14 -> 1941.64 | M12: =M13+M14 -> -12 | N12: =N13+N14 -> 2027.8379 | O12: =O13+O14 -> 86.197861 | P12: =P13+P14 -> 2090.0167 | Q12: =Q13+Q14 -> 62.178834 | R12: =R13+R14 -> 2184.245 | S12: =S13+S14 -> 94.228327 | ... W12: =W13+W14 -> 88.143095 | X12: =V12-L12 -> 432.79497 | Y12: =(V12/L12)^(1/5)-1 -> 0.041066122
A13: 其中：利息净收入 | B13: 1261.15 | C13: 62.947601 | D13: 1412 | E13: =D13-B13 -> 150.85 | F13: 1426 | G13: =F13-D13 -> 14 | H13: 1351 | I13: =H13-F13 -> -75 | J13: 1381 | K13: =J13-H13 -> 30 | L13: 1359.33 | M13: -22 | N13: =息差测算表!C6 -> 1398.7484 | O13: =N13-L13 -> 39.418442 | P13: =息差测算表!D6 -> 1456.7307 | Q13: =P13-N13 -> 57.982301 | R13: =息差测算表!E6 -> 1520.0171 | S13: =R13-P13 -> 63.286398 | T13: =息差测算表!F6 -> 1582.4091 | U13: =T13-R13 -> 62.391913 | V13: =息差测算表!G6 -> 1625.5724 | W13: =V13-T13 -> 43.163371 | X13: =V13-L13 -> 266.24242 | Y13: =(V13/L13)^(1/5)-1 -> 0.036421192 | AA13: 和息差表链接
A14: 非利息净收入 | B14: 591.86 | C14: 10.126253 | D14: 501.78 | E14: =D14-B14 -> -90.08 | F14: 554.82 | G14: =F14-D14 -> 53.04 | H14: 560.41 | I14: =H14-F14 -> 5.59 | J14: 622.12 | K14: =J14-H14 -> 61.71 | L14: 582.31 | M14: 10 | N14: =中收测算表!B9 -> 629.08942 | O14: =N14-L14 -> 46.779419 | P14: =中收测算表!B10 -> 633.28595 | Q14: =P14-N14 -> 4.1965335 | R14: =中收测算表!B11 -> 664.22788 | S14: =R14-P14 -> 30.941929 | T14: =中收测算表!B12 -> 703.88282 | U14: =T14-R14 -> 39.654941 | V14: =中收测算表!B13 -> 748.86255 | W14: =V14-T14 -> 44.979724 | X14: =V14-L14 -> 166.55255 | Y14: =(V14/L14)^(1/5)-1 -> 0.051597566 | Z14: 和后面链接
A15: 二、一级核心指标
A16: 总资产 | B16: 75112 | C16: 7608 | D16: 80429 | E16: =D16-B16 -> 5317 | F16: 85475 | G16: =F16-D16 -> 5046 | H16: 90525 | I16: =H16-F16 -> 5050 | J16: 95327 | K16: =J16-H16 -> 4802 | L16: 101316.58 | M16: 5989.36 | N16: =L16+O16 -> 107999.58 | O16: 6683 | P16: =N16+Q16 -> 114699.58 | Q16: =5200+1500 -> 6700 | R16: =P16+S16 -> 119599.58 | S16: =5400-500 -> 4900 | T16: =R16+U16 -> 124699.58 | U16: =5600-500 -> 5100 | V16: =T16+W16 -> 129999.58 | W16: =5800-500 -> 5300 | X16: =V16-L16 -> 28683 | Y16: =(V16/L16)^(1/5)-1 -> 0.051119966
A17: ROE | B17: 0.1011 | C17: -0.0096 | D17: 0.1073 | E17: =D17-B17 -> 0.0062 | F17: 0.108 | G17: =F17-D17 -> 0.0007 | H17: 0.108 | I17: =H17-F17 -> 0 | J17: 0.0979 | K17: =J17-H17 -> -0.0101 | L17: 0.0939 | M17: =L17-J17 -> -0.004 | N17: =资本!D76 -> 0.095294354 | O17: =N17-L17 -> 0.0013943536 | P17: =资本!E76 -> 0.095069286 | Q17: =P17-N17 -> -0.00022506801 | R17: =资本!F76 -> 0.0922937 | S17: =R17-P17 -> -0.0027755852 | T17: =资本!G76 -> 0.091916814 | U17: =T17-R17 -> -0.00037688674 | V17: =资本!H76 -> 0.091152488 | W17: =V17-T17 -> -0.00076432555 | X17: =V17-L17 -> -0.0027475118
A18: RAROC | B18: ='[1]2.年化RAROC（并表）-底稿'!$I$13 -> 0.085713918 | D18: ='[1]2.年化RAROC（并表）-底稿'!$M$13 -> 0.091498466 | E18: =D18-B18 -> 0.0057845486 | F18: ='[1]2.年化RAROC（并表）-底稿'!$Q$13 -> 0.094395276 | G18: =F18-D18 -> 0.0028968094 | H18: ='[1]2.年化RAROC（并表）-底稿'!$U$13 -> 0.094876189 | I18: =H18-F18 -> 0.00048091322 | J18: ='[1]2.年化RAROC（并表）-底稿'!$Y$13 -> 0.091549249 | K18: =J18-H18 -> -0.0033269398 | L18: 0.0881 | M18: =L18-J18 -> -0.003449249 | N18: =资本!D94 -> 0.087980207 | O18: =N18-L18 -> -0.00011979261 | P18: =资本!E94 -> 0.087539869 | Q18: =P18-N18 -> -0.0004403382 | R18: =资本!F94 -> 0.087814458 | S18: =R18-P18 -> 0.00027458925 | T18: =资本!G94 -> 0.089743652 | U18: =T18-R18 -> 0.0019291932 | V18: =资本!H94 -> 0.090961541 | W18: =V18-T18 -> 0.0012178897 | X18: =V18-L18 -> 0.0028615414
A19: 核心一级资本充足率 | B19: 0.0874 | C19: ='[1]1.1核心一级资本充足率（并表）-底稿'!$I$14-'[1]1.1核心一级资本充足率（并表）-底稿'!$E$14 -> 0.0005 | D19: 0.0885 | E19: =D19-B19 -> 0.0011 | F19: 0.0874 | G19: =F19-D19 -> -0.0011 | H19: 0.0899 | I19: =H19-F19 -> 0.0025 | J19: 0.0972 | K19: =J19-H19 -> 0.0073 | L19: 0.0948 | M19: =L19-J19 -> -0.0024 | N19: =资本!D84 -> 0.095730282 | O19: =N19-L19 -> 0.00093028246 | P19: =资本!E84 -> 0.099696284 | Q19: =P19-N19 -> 0.0039660017 | R19: =资本!F84 -> 0.10129985 | S19: =R19-P19 -> 0.0016035683 | T19: =资本!G84 -> 0.10303652 | U19: =T19-R19 -> 0.0017366681 | V19: =资本!H84 -> 0.10472588 | W19: =V19-T19 -> 0.0016893626 | X19: =V19-L19 -> 0.0099258831
A20: 三、二级核心指标（并表）
A21: 生息资产日均 | B21: 66678.02 | D21: 72251.78 | E21: =D21-B21 -> 5573.76 | F21: 76386.39 | G21: =F21-D21 -> 4134.61 | H21: 80467.13 | I21: =H21-F21 -> 4080.74 | J21: 83098.45 | K21: =J21-H21 -> 2631.32 | L21: 88562.26 | M21: =L21-J21 -> 5463.81 | N21: =L21+O21 -> 92357.244 | O21: =O53+子公司!O15 -> 3794.984 | P21: =N21+Q21 -> 100806.96 | Q21: =Q53+子公司!Q15 -> 8449.7175 | R21: =P21+S21 -> 106212.59 | S21: =S53+子公司!S15 -> 5405.6249 | T21: =R21+U21 -> 110798.4 | U21: =U53+子公司!U15 -> 4585.816 | V21: =T21+W21 -> 115610.38 | W21: =W53+子公司!W15 -> 4811.9801 | X21: =V21-L21 -> 27048.122 | Y21: =(V21/L21)^(1/5)-1 -> 0.054750232
A22: 生息资产占比（日均） | B22: =B21/(B16+B16-C16)*2 -> 0.93507068 | D22: =D21/(B16+D16)*2 -> 0.92903839 | E22: =D22-B22 -> -0.0060322907 | F22: =F21/(D16+F16)*2 -> 0.92085049 | G22: =F22-D22 -> -0.0081878967 | H22: =H21/(F16+H16)*2 -> 0.9143992 | I22: =H22-F22 -> -0.0064512873 | J22: =J21/(H16+J16)*2 -> 0.89424327 | K22: =J22-H22 -> -0.020155936 | L22: =L21/(J16+L16)*2 -> 0.90073889 | M22: =L22-J22 -> 0.0064956213 | N22: =(N53+子公司!N15)/(N51+子公司!N13) -> 0.91384354 | O22: =N22-L22 -> 0.013104646 | P22: =(P53+子公司!P15)/(P51+子公司!P13) -> 0.91260154 | Q22: =P22-N22 -> -0.0012419982 | R22: =(R53+子公司!R15)/(R51+子公司!R13) -> 0.91416923 | S22: =R22-P22 -> 0.0015676911 | T22: =(T53+子公司!T15)/(T51+子公司!T13) -> 0.91566453 | U22: =T22-R22 -> 0.0014953025 | V22: =(V53+子公司!V15)/(V51+子公司!V13) -> 0.91707937 | W22: =V22-T22 -> 0.0014148367 | X22: =V22-L22 -> 0.016340478 | AA22: 为什么减1000 | AB22: 合并抵消经验值
A23: 净息差 | B23: =B8/B21 -> 0.022573406 | C23: -0.0019 | D23: =D8/D21 -> 0.02046953 | E23: =D23-B23 -> -0.0021038754 | F23: =F8/F21 -> 0.019721707 | G23: =F23-D23 -> -0.00074782333 | H23: =H8/H21 -> 0.017838215 | I23: =H23-F23 -> -0.0018834915 | J23: =J8/J21 -> 0.017651232 | K23: =J23-H23 -> -0.00018698367 | L23: =L8/L21 -> 0.016312705 | M23: =L23-J23 -> -0.001338527 | N23: =N8/N21 -> 0.016101826 | O23: =N23-L23 -> -0.00021087876 | P23: =P8/P21 -> 0.015817902 | Q23: =P23-N23 -> -0.00028392439 | R23: =R8/R21 -> 0.015739205 | S23: =R23-P23 -> -7.8696776e-05 | T23: =T8/T21 -> 0.015806033 | U23: =T23-R23 -> 6.6827984e-05 | V23: =V8/V21 -> 0.015671533 | W23: =V23-T23 -> -0.00013450017 | X23: =V23-L23 -> -0.00064117211
A24: 非息收入占比 | B24: =B9/B7 -> 0.22706195 | C24: 0.0103 | D24: =D9/D7 -> 0.2769937 | E24: =D24-B24 -> 0.049931752 | F24: =F9/F7 -> 0.28735714 | G24: =F24-D24 -> 0.010363439 | H24: =H9/H7 -> 0.30285678 | I24: =H24-F24 -> 0.015499645 | J24: =J9/J7 -> 0.31344841 | K24: =J24-H24 -> 0.010591633 | L24: =L9/L7 -> 0.32006589 | M24: =L24-J24 -> 0.0066174754 | N24: =N9/N7 -> 0.3300911 | O24: =N24-L24 -> 0.010025205 | P24: =P9/P7 -> 0.31986476 | Q24: =P24-N24 -> -0.010226331 | R24: =R9/R7 -> 0.32082168 | S24: =R24-P24 -> 0.00095692065 | T24: =T9/T7 -> 0.32411219 | U24: =T24-R24 -> 0.0032905099 | V24: =V9/V7 -> 0.33079783 | W24: =V24-T24 -> 0.0066856316 | X24: =V24-L24 -> 0.010731936
A25: 成本收入比 | B25: 0.26653178 | C25: -0.0105 | D25: 0.29203107 | E25: =D25-B25 -> 0.025499292 | F25: 0.30534741 | G25: =F25-D25 -> 0.013316339 | H25: 0.32352256 | I25: =H25-F25 -> 0.018175144 | J25: 0.32488322 | K25: =J25-H25 -> 0.001360663 | L25: 0.31607954 | M25: =L25-J25 -> -0.0088036793 | N25: =L25+O25 -> 0.31607954 | O25: 0 | P25: =N25+Q25 -> 0.31557954 | Q25: -0.0005 | R25: =P25+S25 -> 0.31507954 | S25: -0.0005 | T25: =R25+U25 -> 0.31457954 | U25: -0.0005 | V25: =T25+W25 -> 0.31407954 | W25: -0.0005 | X25: =V25-L25 -> -0.002
A26: 风险成本率 | B26: 0.42617251 | C26: 0.0144 | D26: 0.37665785 | E26: =D26-B26 -> -0.049514664 | F26: 0.33778005 | G26: =F26-D26 -> -0.038877802 | H26: 0.30211369 | I26: =H26-F26 -> -0.03566636 | J26: 0.28604795 | K26: =J26-H26 -> -0.01606574 | L26: 0.2737828 | M26: =L26-J26 -> -0.01226515 | N26: =L26+O26 -> 0.2687828 | O26: -0.005 | P26: =N26+Q26 -> 0.2637828 | Q26: -0.005 | R26: =P26+S26 -> 0.2587828 | S26: -0.005 | T26: =R26+U26 -> 0.2537828 | U26: -0.005 | V26: =T26+W26 -> 0.2487828 | W26: -0.005 | X26: =V26-L26 -> -0.025
A27: 税务成本率 | B27: 0.053145108 | C27: 0.3%% | D27: 0.055451537 | E27: =D27-B27 -> 0.0023064289 | F27: 0.059548138 | G27: =F27-D27 -> 0.0040966013 | H27: 0.043759956 | I27: =H27-F27 -> -0.015788182 | J27: 0.063605216 | K27: =J27-H27 -> 0.01984526 | L27: 0.069255206 | M27: =L27-J27 -> 0.0056499904 | N27: =L27+O27 -> 0.069255206 | O27: 0 | P27: =N27+Q27 -> 0.069255206 | Q27: 0 | R27: =P27+S27 -> 0.069255206 | S27: 0 | T27: =R27+U27 -> 0.069255206 | U27: 0 | V27: =T27+W27 -> 0.069255206 | W27: 0 | X27: =V27-L27 -> 0
A28: 综合风险权重 | B28: 0.73672221 | D28: 0.72024808 | E28: =D28-B28 -> -0.01647413 | F28: 0.7308449 | G28: =F28-D28 -> 0.010596825 | H28: 0.74109085 | I28: =H28-F28 -> 0.010245949 | J28: 0.74233501 | K28: =J28-H28 -> 0.0012441539 | L28: =资本!C93 -> 0.75026761 | M28: =L28-J28 -> 0.0079326091 | N28: =资本!D93 -> 0.75809131 | O28: =N28-L28 -> 0.0078236989 | P28: =资本!E93 -> 0.7653228 | Q28: =P28-N28 -> 0.0072314833 | R28: =资本!F93 -> 0.77412488 | S28: =R28-P28 -> 0.0088020822 | T28: =资本!G93 -> 0.77735417 | U28: =T28-R28 -> 0.0032292919 | V28: =资本!H93 -> 0.78102084 | W28: =V28-T28 -> 0.003666673 | X28: =V28-L28 -> 0.030753229
A29: 四、其他指标（本行）
A30: 净息差 | B30: 0.0228 | C30: -0.0019 | D30: 0.0206 | E30: -0.0022 | F30: 0.0197 | G30: -0.0009 | H30: 0.0178 | I30: -0.0019 | J30: 0.017601992 | K30: -0.0002 | L30: =L13/L53 -> 0.016376089 | M30: -0.0012 | N30: =息差测算表!C7 -> 0.016226546 | O30: =N30-L30 -> -0.000149543 | P30: =息差测算表!D7 -> 0.015620824 | Q30: =P30-N30 -> -0.00060572192 | R30: =息差测算表!E7 -> 0.015656156 | S30: =R30-P30 -> 3.5331662e-05 | T30: =息差测算表!F7 -> 0.016 | U30: =T30-R30 -> 0.0003438445 | V30: =息差测算表!G7 -> 0.015529954 | W30: =V30-T30 -> -0.00047004641 | X30: =V30-L30 -> -0.00084613518 | Z30: 和后面链接
A31: 信贷资产占比（各项贷款/总资产，时点，人民币） | B31: =B57/B55 -> 0.61457084 | C31: -0.005 | D31: =D57/D55 -> 0.61682948 | E31: =D31-B31 -> 0.0022586486 | F31: =F57/F55 -> 0.62652337 | G31: =F31-D31 -> 0.0096938884 | H31: =H57/H55 -> 0.6335629 | I31: =H31-F31 -> 0.0070395265 | J31: =J57/J55 -> 0.64209499 | K31: =J31-H31 -> 0.0085320943 | L31: =L57/L55 -> 0.62312869 | M31: =L31-J31 -> -0.018966302 | N31: =N57/N55 -> 0.60872968 | O31: =N31-L31 -> -0.014399011 | P31: =P57/P55 -> 0.60660646 | Q31: =P31-N31 -> -0.0021232184 | R31: =R57/R55 -> 0.60564704 | S31: =R31-P31 -> -0.0009594238 | T31: =T57/T55 -> 0.60618142 | U31: =T31-R31 -> 0.00053438178 | V31: =V57/V55 -> 0.60655446 | W31: =V31-T31 -> 0.00037303719 | X31: =V31-L31 -> -0.016574234 | AA31: 改了公式需要核对
A32: 信贷资产占比（一般贷款/总资产，时点，人民币） | B32: =(B60+B63+B66)/B55 -> 0.54174354 | C32: -0.007 | D32: =(D60+D63+D66)/D55 -> 0.54068118 | E32: =D32-B32 -> -0.0010623591 | F32: =(F60+F63+F66)/F55 -> 0.54122397 | G32: =F32-D32 -> 0.00054279496 | H32: =(H60+H63+H66)/H55 -> 0.55391716 | I32: =H32-F32 -> 0.012693188 | J32: =(J60+J63+J66)/J55 -> 0.55988363 | K32: =J32-H32 -> 0.0059664652 | L32: =(L60+L63+L66)/L55 -> 0.56379388 | M32: =L32-J32 -> 0.0039102567 | N32: =(N60+N63+N66)/N55 -> 0.56215249 | O32: =N32-L32 -> -0.0016413942 | P32: =(P60+P63+P66)/P55 -> 0.56811999 | Q32: =P32-N32 -> 0.0059675034 | R32: =(R60+R63+R66)/R55 -> 0.57145845 | S32: =R32-P32 -> 0.0033384572 | T32: =(T60+T63+T66)/T55 -> 0.57188144 | U32: =T32-R32 -> 0.00042299314 | V32: =(V60+V63+V66)/V55 -> 0.56995208 | W32: =V32-T32 -> -0.0019293602 | X32: =V32-L32 -> 0.0061581994
A33: 自营存款占比（时点，人民币） | B33: =B125/B123 -> 0.65192009 | D33: =D125/D123 -> 0.64141497 | E33: =D33-B33 -> -0.010505122 | F33: =F125/F123 -> 0.65129927 | G33: =F33-D33 -> 0.0098842976 | H33: =H125/H123 -> 0.65983082 | I33: =H33-F33 -> 0.0085315468 | J33: =J125/J123 -> 0.67429979 | K33: =J33-H33 -> 0.014468979 | L33: =L125/L123 -> 0.66132456 | M33: =L33-J33 -> -0.012975238 | N33: =N125/N123 -> 0.65691877 | O33: =N33-L33 -> -0.0044057878 | P33: =P125/P123 -> 0.6767207 | Q33: =P33-N33 -> 0.019801928 | R33: =R125/R123 -> 0.69682107 | S33: =R33-P33 -> 0.020100369 | T33: =T125/T123 -> 0.7168917 | U33: =T33-R33 -> 0.020070633 | V33: =V125/V123 -> 0.73792925 | W33: =V33-T33 -> 0.021037551 | X33: =V33-L33 -> 0.076604693
A34: 零售存款占比（日均） | B34: =B134/B126 -> 0.18818642 | D34: =D134/D126 -> 0.18526335 | E34: =D34-B34 -> -0.0029230609 | F34: =F134/F126 -> 0.20445224 | G34: =F34-D34 -> 0.019188884 | H34: =H134/H126 -> 0.25222505 | I34: =H34-F34 -> 0.047772813 | J34: =J134/J126 -> 0.27145961 | K34: =J34-H34 -> 0.019234559 | L34: =L134/L126 -> 0.28711748 | M34: =L34-J34 -> 0.015657871 | N34: =N134/N126 -> 0.29448384 | O34: =N34-L34 -> 0.0073663559 | P34: =P134/P126 -> 0.30511638 | Q34: =P34-N34 -> 0.010632542 | R34: =R134/R126 -> 0.31361856 | S34: =R34-P34 -> 0.0085021806 | T34: =T134/T126 -> 0.32224574 | U34: =T34-R34 -> 0.0086271772 | V34: =V134/V126 -> 0.33095178 | W34: =V34-T34 -> 0.0087060446 | X34: =V34-L34 -> 0.0438343
A35: 对公活期占比（日均） | B35: =B131/B128 -> 0.50198314 | C35: -0.013 | D35: =D131/D128 -> 0.52313402 | E35: =D35-B35 -> 0.021150887 | F35: =F131/F128 -> 0.52047447 | G35: =F35-D35 -> -0.0026595479 | H35: =H131/H128 -> 0.54948243 | I35: =H35-F35 -> 0.029007957 | J35: =J131/J128 -> 0.52117308 | K35: =J35-H35 -> -0.028309352 | L35: =L131/L128 -> 0.45808969 | M35: =L35-J35 -> -0.063083393 | N35: =N131/N128 -> 0.43431898 | O35: =N35-L35 -> -0.023770702 | P35: =P131/P128 -> 0.43703864 | Q35: =P35-N35 -> 0.0027196534 | R35: =R131/R128 -> 0.43982351 | S35: =R35-P35 -> 0.002784872 | T35: =T131/T128 -> 0.44237246 | U35: =T35-R35 -> 0.0025489494 | V35: =V131/V128 -> 0.44494973 | W35: =V35-T35 -> 0.0025772677 | X35: =V35-L35 -> -0.01313996
A36: 零售活期占比（日均） | B36: =B137/B134 -> 0.33573981 | C36: -0.005 | D36: =D137/D134 -> 0.32881985 | E36: =D36-B36 -> -0.0069199527 | F36: =F137/F134 -> 0.28964125 | G36: =F36-D36 -> -0.0391786 | H36: =H137/H134 -> 0.24033569 | I36: =H36-F36 -> -0.049305561 | J36: =J137/J134 -> 0.268133 | K36: =J36-H36 -> 0.027797312 | L36: =L137/L134 -> 0.27089068 | M36: =L36-J36 -> 0.0027576712 | N36: =N137/N134 -> 0.274 | O36: =N36-L36 -> 0.0031093242 | P36: =P137/P134 -> 0.27630762 | Q36: =P36-N36 -> 0.0023076219 | R36: =R137/R134 -> 0.27823901 | S36: =R36-P36 -> 0.0019313898 | T36: =T137/T134 -> 0.27997359 | U36: =T36-R36 -> 0.0017345761 | V36: =V137/V134 -> 0.28161176 | W36: =V36-T36 -> 0.0016381723 | X36: =V36-L36 -> 0.010721084
A37: 人民币市场化负债占比（日均） | B37: =B140/B124 -> 0.34406719 | D37: =D140/D124 -> 0.3595394 | E37: =D37-B37 -> 0.015472212 | F37: =F140/F124 -> 0.346706 | G37: =F37-D37 -> -0.012833405 | H37: =H140/H124 -> 0.3190469 | I37: =H37-F37 -> -0.027659099 | J37: =J140/J124 -> 0.3302094 | K37: =J37-H37 -> 0.011162502 | L37: =L140/L124 -> 0.33330385 | M37: =L37-J37 -> 0.0030944467 | N37: =N140/N124 -> 0.32185827 | O37: =N37-L37 -> -0.011445579 | P37: =P140/P124 -> 0.33462483 | Q37: =P37-N37 -> 0.012766566 | R37: =R140/R124 -> 0.31515159 | S37: =R37-P37 -> -0.019473248 | T37: =T140/T124 -> 0.2950099 | U37: =T37-R37 -> -0.020141684 | V37: =V140/V124 -> 0.27277382 | W37: =V37-T37 -> -0.02223608 | X37: =V37-L37 -> -0.060530025
A38: 存贷比（一般性贷款/自营存款，人民币时点） | B38: =(B60+B63+B66+B69-1400)/(B127+B133) -> 0.98271752 | C38: -0.014295428 | D38: =(D60+D63+D66+D69-1600)/(D127+D133) -> 1.0080291 | E38: =D38-B38 -> 0.025311595 | F38: =(F60+F63+F66+F69-2400)/(F127+F133) -> 0.98310593 | G38: =F38-D38 -> -0.024923186 | H38: =(H60+H63+H66+H69-2400)/(H127+H133) -> 0.99161678 | I38: =H38-F38 -> 0.0085108523 | J38: =(J60+J63+J66+J69-2100)/(J127+J133) -> 0.98406336 | K38: =J38-H38 -> -0.007553418 | L38: =(L60+L63+L66+L69-2110)/(L127+L133) -> 0.95724308 | M38: =L38-J38 -> -0.026820283 | N38: =(N60+N63+N66+N69-2110)/(N127+N133) -> 0.94141015 | O38: =N38-L38 -> -0.015832933 | P38: =(P60+P63+P66+P69-2310)/(P127+P133) -> 0.92584271 | Q38: =P38-N38 -> -0.015567438 | R38: =(R60+R63+R66+R69-2310)/(R127+R133) -> 0.91450875 | S38: =R38-P38 -> -0.011333964 | T38: =(T60+T63+T66+T69-2310)/(T127+T133) -> 0.89807765 | U38: =T38-R38 -> -0.016431096 | V38: =(V60+V63+V66+V69-2310)/(V127+V133) -> 0.8774872 | W38: =V38-T38 -> -0.020590453 | X38: =V38-L38 -> -0.079755884
A39: 日均（一般性贷款/自营存款） | B39: =(B61+B64+B67+B70-1400)/(B128+B134) -> 0.95918332 | C39: -0.031245693 | D39: =(D61+D64+D67+D70-1500)/(D128+D134) -> 1.0041105 | E39: =D39-B39 -> 0.044927142 | F39: =(F61+F64+F67+F70-2200)/(F128+F134) -> 0.97230514 | G39: =F39-D39 -> -0.031805324 | H39: =(H61+H64+H67+H70-2400)/(H128+H134) -> 0.9407307 | I39: =H39-F39 -> -0.031574434 | J39: =(J61+J64+J67+J70-1930)/(J128+J134) -> 0.99709123 | K39: =J39-H39 -> 0.056360527 | L39: =(L61+L64+L67+L70-2200)/(L128+L134) -> 0.96637441 | M39: =L39-J39 -> -0.030716821 | N39: =(N61+N64+N67+N70-2110)/(N128+N134) -> 0.95797941 | O39: =N39-L39 -> -0.0083949928 | P39: =(P61+P64+P67+P70-2310)/(P128+P134) -> 0.94317034 | Q39: =P39-N39 -> -0.014809076 | R39: =(R61+R64+R67+R70-2310)/(R128+R134) -> 0.92941109 | S39: =R39-P39 -> -0.013759248 | T39: =(T61+T64+T67+T70-2310)/(T128+T134) -> 0.91345717 | U39: =T39-R39 -> -0.015953925 | V39: =(V61+V64+V67+V70-2310)/(V128+V134) -> 0.89089007 | W39: =V39-T39 -> -0.0225671 | X39: =V39-L39 -> -0.075484342
A40: 外币资负差（负债-资产，时点，亿美元） | B40: =B142-B98 -> -41.91 | D40: =D142-D98 -> -27.08 | E40: =D40-B40 -> 14.83 | F40: =F142-F98 -> -46 | G40: =F40-D40 -> -18.92 | H40: =H142-H98 -> -42.5 | I40: =H40-F40 -> 3.5 | J40: =J142-J98 -> -47.23 | K40: =J40-H40 -> -4.73 | L40: =L142-L98 -> 0.52633377 | M40: =L40-J40 -> 47.756334 | N40: =N142-N98 -> -134.47367 | O40: =N40-L40 -> -135 | P40: =P142-P98 -> -114.47367 | Q40: =P40-N40 -> 20 | R40: =R142-R98 -> -44.473666 | S40: =R40-P40 -> 70 | T40: =T142-T98 -> 25.526334 | U40: =T40-R40 -> 70 | V40: =V142-V98 -> 95.526334 | W40: =V40-T40 -> 70 | X40: =V40-L40 -> 95
A41: 风险加权资产 | B41: 49974.009 | C41: 2794.293 | D41: 53574.817 | E41: 3600.8071 | F41: 57752.949 | G41: 4178.1321 | H41: 61781 | I41: 4028.0513 | J41: 64598 | K41: 2817 | L41: =资本!C47-资本!C46 -> 70317.595 | M41: 6156 | N41: =资本!F47-资本!F46 -> 74206.805 | O41: =N41-L41 -> 3889.2106 | P41: =资本!J47-资本!J46 -> 78335.352 | Q41: =P41-N41 -> 4128.5467 | R41: =资本!N47-资本!N46 -> 81640.87 | S41: =R41-P41 -> 3305.5182 | T41: =资本!R47-资本!R46 -> 85067.514 | U41: =T41-R41 -> 3426.6439 | V41: =资本!V47-资本!V46 -> 88764.252 | W41: =V41-T41 -> 3696.738 | X41: =V41-L41 -> 18446.657 | Y41: =(V41/L41)^(1/5)-1 -> 0.047694872
A42: AC类投资收益率 | B42: =B192 -> 0.034943308 | D42: =D192 -> 0.033254316 | E42: =D42-B42 -> -0.0016889913 | F42: =F192 -> 0.032182615 | G42: =F42-D42 -> -0.0010717016 | H42: =H192 -> 0.02864003 | I42: =H42-F42 -> -0.0035425853 | J42: =J192 -> 0.026826842 | K42: =J42-H42 -> -0.0018131879 | L42: =L192 -> 0.023086202 | M42: =L42-J42 -> -0.0037406394 | N42: =N192 -> 0.020921025 | O42: =N42-L42 -> -0.002165177 | P42: =P192 -> 0.019838999 | Q42: =P42-N42 -> -0.0010820265 | R42: =R192 -> 0.020036364 | S42: =R42-P42 -> 0.00019736482 | T42: =T192 -> 0.019690909 | U42: =T42-R42 -> -0.00034545455 | V42: =V192 -> 0.019 | W42: =V42-T42 -> -0.00069090909 | X42: =V42-L42 -> -0.0040862023
A43: FVOCI及FVTPL类综合收益率（含公允价值变动） | B43: =B195 -> 0.026237056 | D43: =D195 -> 0.036858823 | E43: =D43-B43 -> 0.010621766 | F43: =F195 -> 0.021264769 | G43: =F43-D43 -> -0.015594054 | H43: =H195 -> 0.026689133 | I43: =H43-F43 -> 0.0054243643 | J43: =J195 -> 0.038869075 | K43: =J43-H43 -> 0.012179941 | L43: =L195 -> 0.02610136 | M43: =L43-J43 -> -0.012767715 | N43: =N195 -> 0.028273079 | O43: =N43-L43 -> 0.0021717194 | P43: =P195 -> 0.022780585 | Q43: =P43-N43 -> -0.0054924944 | R43: =R195 -> 0.023453633 | S43: =R43-P43 -> 0.00067304768 | T43: =T195 -> 0.024428886 | U43: =T43-R43 -> 0.00097525321 | V43: =V195 -> 0.025429763 | W43: =V43-T43 -> 0.0010008769 | X43: =V43-L43 -> -0.00067159723
A44: 核心一级资本充足率 | B44: 0.0847 | D44: 0.0851 | E44: =D44-B44 -> 0.0004 | F44: 0.0833 | G44: =F44-D44 -> -0.0018 | H44: 0.0859 | I44: =H44-F44 -> 0.0026 | J44: 0.0942 | K44: =J44-H44 -> 0.0083 | L44: 0.089842865 | M44: =L44-J44 -> -0.0043571352 | N44: =资本!M84 -> 0.091420724 | O44: =N44-L44 -> 0.0015778593 | P44: =资本!N84 -> 0.095382528 | Q44: =P44-N44 -> 0.0039618037 | R44: =资本!O84 -> 0.09688138 | S44: =R44-P44 -> 0.0014988525 | T44: =资本!P84 -> 0.09855918 | U44: =T44-R44 -> 0.0016777992 | V44: =资本!Q84 -> 0.10017424 | W44: =V44-T44 -> 0.0016150559 | X44: =V44-L44 -> 0.010331371
A45: LCR | B45: 1.3106821 | D45: 1.446998 | E45: =D45-B45 -> 0.13631595 | F45: 1.7083384 | G45: =F45-D45 -> 0.26134041 | H45: 1.6987697 | I45: =H45-F45 -> -0.0095687224 | J45: 2.186875 | K45: =J45-H45 -> 0.48810531 | L45: 1.4678879 | M45: =L45-J45 -> -0.7189871 | N45: =O229 -> 1.5490348 | O45: =N45-L45 -> 0.081146848 | P45: =Q229 -> 1.5859068 | Q45: =P45-N45 -> 0.036872085 | R45: =S229 -> 1.6092104 | S45: =R45-P45 -> 0.02330353 | T45: =U229 -> 1.6146604 | U45: =T45-R45 -> 0.0054500196 | V45: =W229 -> 1.6262955 | W45: =V45-T45 -> 0.011635157 | X45: =V45-L45 -> 0.15840764
A46: NSFR | B46: 1.0615501 | D46: 1.0620828 | E46: =D46-B46 -> 0.000532779 | F46: 1.0765073 | G46: =F46-D46 -> 0.014424503 | H46: 1.0794268 | I46: =H46-F46 -> 0.00291942 | J46: 1.0707998 | K46: =J46-H46 -> -0.008626977 | L46: 1.0472498 | M46: =L46-J46 -> -0.023549993 | N46: =O233 -> 1.0740923 | O46: =N46-L46 -> 0.026842489 | P46: =Q233 -> 1.0970978 | Q46: =P46-N46 -> 0.023005494 | R46: =S233 -> 1.1205338 | S46: =R46-P46 -> 0.023436005 | T46: =U233 -> 1.1458257 | U46: =T46-R46 -> 0.025291948 | V46: =W233 -> 1.1741752 | W46: =V46-T46 -> 0.028349464 | X46: =V46-L46 -> 0.1269254
A47: △EVE | B47: 0.0976 | D47: 0.0944 | E47: =D47-B47 -> -0.0032 | F47: 0.0657 | G47: =F47-D47 -> -0.0287 | H47: 0.0746 | I47: =H47-F47 -> 0.0089 | J47: 0.0856 | K47: =J47-H47 -> 0.011 | L47: 0.1049 | M47: =L47-J47 -> 0.0193 | N47: =中收测算表!AE48 -> 0.11154854 | O47: =N47-L47 -> 0.0066485432 | P47: =中收测算表!AF48 -> 0.10817813 | Q47: =P47-N47 -> -0.0033704101 | R47: =中收测算表!AG48 -> 0.11248077 | S47: =R47-P47 -> 0.0043026362 | T47: =中收测算表!AH48 -> 0.11366561 | U47: =T47-R47 -> 0.0011848444 | V47: =中收测算表!AI48 -> 0.1154522 | W47: =V47-T47 -> 0.0017865858 | X47: =V47-L47 -> 0.010552199
A48: 10期国债收益率 | B48: 0.0314 | C48: 0 | D48: 0.0278 | E48: =D48-B48 -> -0.0036 | F48: 0.0284 | G48: =F48-D48 -> 0.0006 | H48: 0.0256 | I48: =H48-F48 -> -0.0028 | J48: 0.0168 | K48: =J48-H48 -> -0.0088 | L48: 0.0185 | M48: -0.0008 | N48: 0.0175 | O48: =N48-L48 -> -0.001 | P48: 0.0175 | Q48: =P48-N48 -> 0 | R48: 0.0175 | S48: =R48-P48 -> 0 | T48: 0.0175 | U48: =T48-R48 -> 0 | V48: 0.0175 | W48: =V48-T48 -> 0 | X48: =V48-L48 -> -0.001
A49: 二、资产端
A50: 总资产（本行，时点） | B50: 71410 | C50: =B50-63931 -> 7479 | D50: 76661 | E50: =D50-B50 -> 5251 | F50: 81031 | G50: =F50-D50 -> 4370 | H50: 85652 | I50: =H50-F50 -> 4621 | J50: 89833 | K50: =J50-H50 -> 4181 | L50: =L119+L154 -> 95174.954 | M50: =L50-J50 -> 5341.9539 | N50: =L50+O50 -> 101384.54 | O50: =O16-子公司!O12 -> 6209.5864 | P50: =N50+Q50 -> 105443.36 | Q50: =Q16-子公司!Q12 -> 4058.8149 | R50: =P50+S50 -> 109471.4 | S50: =S16-子公司!S12 -> 4028.0434 | T50: =R50+U50 -> 113572.8 | U50: =U16-子公司!U12 -> 4101.3986 | V50: =T50+W50 -> 117697.23 | W50: =W16-子公司!W12 -> 4124.4353 | X50: =V50-L50 -> 22522.279 | Y50: =(V50/L50)^(1/5)-1 -> 0.043394913
A51: 总资产（本行，日均） | B51: 67980 | C51: 6979 | D51: 74352 | E51: =D51-B51 -> 6372 | F51: 78731 | G51: =F51-D51 -> 4379 | H51: 83421 | I51: =H51-F51 -> 4690 | J51: 85913 | K51: =J51-H51 -> 2492 | L51: 91367 | M51: =L51-J51 -> 5454 | N51: =N56+N99*7 -> 94189.775 | O51: =O56+O99*7 -> 2822.7747 | P51: =P56+P99*7 -> 102029.22 | Q51: =Q56+Q99*7 -> 7839.4477 | R51: =R56+R99*7 -> 105996.04 | S51: =S56+S99*7 -> 3966.8168 | T51: =T56+T99*7 -> 109878.89 | U51: =U56+U99*7 -> 3882.8482 | ... W51: =W56+W99*7 -> 3973.0028 | X51: =V51-L51 -> 22484.89 | Y51: =(V51/L51)^(1/5)-1 -> 0.044985287
A52: 生息资产（本行，时点） | B52: 66332.548 | C52: 6646.0687 | D52: 70674.819 | E52: 4342.2709 | F52: 74563.582 | G52: 3888.7628 | H52: 78391.719 | I52: 3828.1366 | J52: 81607.901 | K52: 3216.1822 | L52: 86688.214 | M52: 5080.3126 | N52: =N57+N73+N100*7+N103*7 -> 91944.825 | O52: =N52-L52 -> 5256.6113 | P52: =P57+P73+P100*7+P103*7 -> 95868.64 | Q52: =P52-N52 -> 3923.8149 | R52: =R57+R73+R100*7+R103*7 -> 99761.683 | S52: =R52-P52 -> 3893.0434 | T52: =T57+T73+T100*7+T103*7 -> 103728.08 | U52: =T52-R52 -> 3966.3986 | V52: =V57+V73+V100*7+V103*7 -> 107717.52 | W52: =V52-T52 -> 3989.4353 | X52: =V52-L52 -> 21029.303 | Y52: =(V52/L52)^(1/5)-1 -> 0.044396136
A53: 生息资产（本行，日均） | B53: 63265.647 | C53: 6744.2001 | D53: 68396.813 | E53: 5131.1664 | F53: 72357.645 | G53: 3960.8317 | H53: 76067.079 | I53: 3709.4339 | J53: 78458.985 | K53: 2391.9061 | L53: 83007 | M53: 4548.0149 | N53: =O53+L53 -> 86201.245 | O53: =O58+O74+O101*7+O104*7 -> 3194.2447 | P53: =Q53+N53 -> 93255.692 | Q53: =Q58+Q74+Q101*7+Q104*7 -> 7054.4477 | R53: =S53+P53 -> 97087.509 | S53: =S58+S74+S101*7+S104*7 -> 3831.8168 | T53: =U53+R53 -> 100835.36 | U53: =U58+U74+U101*7+U104*7 -> 3747.8482 | V53: =W53+T53 -> 104673.36 | W53: =W58+W74+W101*7+W104*7 -> 3838.0028 | X53: =V53-L53 -> 21666.36 | Y53: =(V53/L53)^(1/5)-1 -> 0.047476503
A54: 收益率 | B54: 0.0455 | C54: -0.003 | D54: 0.0433 | E54: -0.0022 | F54: 0.0415 | G54: -0.0018 | H54: 0.0389 | I54: -0.0026 | J54: 0.0366 | K54: 0.0023 | L54: 0.0316 | M54: =L54-J54 -> -0.005 | N54: =息差测算表!C11 -> 0.028819772 | O54: =N54-L54 -> -0.0027802278 | P54: =息差测算表!D11 -> 0.027816479 | Q54: =P54-N54 -> -0.0010032931 | R54: =息差测算表!E11 -> 0.02749354 | S54: =R54-P54 -> -0.000322939 | T54: =息差测算表!F11 -> 0.027070987 | U54: =T54-R54 -> -0.00042255295 | V54: =息差测算表!G11 -> 0.026619727 | W54: =V54-T54 -> -0.00045126015 | X54: =V54-L54 -> -0.004980273 | Z54: 和后面链接 | AA54: 和息差表链接
A55: （一）人民币小计（时点） | B55: =B57+B73+B93 -> 68883.63 | C55: =C57+C73+C93 -> 6744.28 | D55: =D57+D73+D93 -> 74350.44 | E55: =D55-B55 -> 5466.81 | F55: =F57+F73+F93 -> 78840 | G55: =F55-D55 -> 4489.56 | H55: =H57+H73+H93 -> 83499.5 | I55: =H55-F55 -> 4659.5 | J55: =J57+J73+J93 -> 87402.39 | K55: =J55-H55 -> 3902.89 | L55: =L57+L73+L93 -> 92663.704 | M55: =L55-J55 -> 5261.3139 | N55: =L55+O55 -> 97648.29 | O55: =O57+O73+O93 -> 4984.5864 | P55: =N55+Q55 -> 101287.11 | Q55: =Q57+Q73+Q93 -> 3638.8149 | R55: =P55+S55 -> 105245.15 | S55: =S57+S73+S93 -> 3958.0434 | T55: =R55+U55 -> 109276.55 | U55: =U57+U73+U93 -> 4031.3986 | V55: =T55+W55 -> 113330.98 | W55: =W57+W73+W93 -> 4054.4353 | X55: =V55-L55 -> 20667.279 | Y55: =(V55/L55)^(1/5)-1 -> 0.041088861
A56: 日均 | B56: =B58+B74+B94 -> 65350.52 | C56: =C58+C74+C94 -> 6484.52 | D56: =D58+D74+D94 -> 71451.55 | E56: =D56-B56 -> 6101.03 | F56: =F58+F74+F94 -> 75704.235 | G56: =F56-D56 -> 4252.685 | H56: =H58+H74+H94 -> 81221.74 | I56: =H56-F56 -> 5517.505 | J56: =J58+J74+J94 -> 83688.855 | K56: =J56-H56 -> 2467.115 | L56: =L58+L74+L94 -> 88963.48 | M56: =L56-J56 -> 5274.625 | N56: =L56+O56 -> 90936.525 | O56: =O58+O74+O94 -> 1973.0447 | P56: =N56+Q56 -> 98082.972 | Q56: =Q58+Q74+Q94 -> 7146.4477 | R56: =P56+S56 -> 101804.79 | S56: =S58+S74+S94 -> 3721.8168 | T56: =R56+U56 -> 105617.64 | U56: =U58+U74+U94 -> 3812.8482 | V56: =T56+W56 -> 109520.64 | W56: =W58+W74+W94 -> 3903.0028 | X56: =V56-L56 -> 20557.16 | Y56: =(V56/L56)^(1/5)-1 -> 0.042453861
A57: 1.境内人民币各项贷款（时点） | B57: =B60+B63+B66+B69+B71 -> 42333.87 | C57: =C60+C63+C66+C69+C71 -> 4125.2086 | D57: =D60+D63+D66+D69+D71 -> 45861.544 | E57: =D57-B57 -> 3527.6735 | F57: =F60+F63+F66+F69+F71 -> 49395.103 | G57: =F57-D57 -> 3533.5591 | H57: =H60+H63+H66+H69+H71 -> 52902.185 | I57: =H57-F57 -> 3507.0826 | J57: =J60+J63+J66+J69+J71 -> 56120.637 | K57: =J57-H57 -> 3218.4517 | L57: 57741.413 | M57: 1620.7755 | N57: =L57+O57 -> 59441.413 | O57: 1700 | P57: =N57+Q57 -> 61441.413 | Q57: 2000 | R57: =P57+S57 -> 63741.413 | S57: 2300 | T57: =R57+U57 -> 66241.413 | U57: 2500 | V57: =T57+W57 -> 68741.413 | W57: 2500 | X57: =V57-L57 -> 11000 | Y57: =(V57/L57)^(1/5)-1 -> 0.035490716 | AC57: =S57-'2026-2030年盈利测算表'!S57 -> 0 | AD57: =T57-'2026-2030年盈利测算表'!T57 -> 0 | AE57: =U57-'2026-2030年盈利测算表'!U57 -> 0 | AF57: =V57-'2026-2030年盈利测算表'!V57 -> 0 | AG57: =W57-'2026-2030年盈利测算表'!W57 -> 0
A58: 日均 | B58: =B61+B64+B67+B70+B72 -> 40599.77 | C58: =C61+C64+C67+C70+C72 -> 4025.1603 | D58: =D61+D64+D67+D70+D72 -> 44527.929 | E58: =E61+E64+E67+E70+E72 -> 3928.1594 | F58: =F61+F64+F67+F70+F72 -> 47504.025 | G58: =G61+G64+G67+G70+G72 -> 2976.0962 | H58: =H61+H64+H67+H70+H72 -> 51350.179 | I58: =I61+I64+I67+I70+I72 -> 3846.1539 | ... M58: =M61+M64+M67+M70+M72 -> 2766.7369 | N58: =O58+L58 -> 58730.355 | O58: =O61+O64+O67+O70+O72 -> 1529 | P58: =Q58+N58 -> 60845.194 | Q58: =Q61+Q64+Q67+Q70+Q72 -> 2114.8387 | R58: =S58+P58 -> 62910.194 | S58: =S61+S64+S67+S70+S72 -> 2065 | T58: =U58+R58 -> 65125.194 | U58: =U61+U64+U67+U70+U72 -> 2215 | V58: =W58+T58 -> 67470.194 | W58: =W61+W64+W67+W70+W72 -> 2345 | X58: =V58-L58 -> 10268.839 | Y58: =(V58/L58)^(1/5)-1 -> 0.033572934 | AC58: =S58-'2026-2030年盈利测算表'!S58 -> 0 | AD58: =T58-'2026-2030年盈利测算表'!T58 -> 0 | AE58: =U58-'2026-2030年盈利测算表'!U58 -> 0 | AF58: =V58-'2026-2030年盈利测算表'!V58 -> 0 | AG58: =W58-'2026-2030年盈利测算表'!W58 -> 0
A59: 收益率 | B59: 0.0539 | C59: =B59-5.64% -> -0.0025 | D59: 0.0508 | E59: =D59-B59 -> -0.0031 | F59: 0.0486 | G59: =F59-D59 -> -0.0022 | H59: 0.0479 | I59: =H59-F59 -> -0.0007 | J59: 0.044 | K59: =J59-H59 -> -0.0039 | L59: 0.0377 | M59: =L59-J59 -> -0.0063 | N59: =息差测算表!C13 -> 0.033818474 | O59: =N59-L59 -> -0.0038815257 | P59: =息差测算表!D13 -> 0.033158939 | Q59: =P59-N59 -> -0.00065953499 | R59: =息差测算表!E13 -> 0.032566156 | S59: =R59-P59 -> -0.00059278329 | T59: =息差测算表!F13 -> 0.03204545 | U59: =T59-R59 -> -0.00052070636 | V59: =息差测算表!G13 -> 0.031692184 | W59: =V59-T59 -> -0.00035326593 | X59: =V59-L59 -> -0.0060078163 | Z59: 和后面链接 | AC59: =S59-'2026-2030年盈利测算表'!S59 -> 0 | AD59: =T59-'2026-2030年盈利测算表'!T59 -> 0 | AE59: =U59-'2026-2030年盈利测算表'!U59 -> 0 | AF59: =V59-'2026-2030年盈利测算表'!V59 -> 0 | AG59: =W59-'2026-2030年盈利测算表'!W59 -> 0
A60: 1.1.对公一般贷款（时点） | B60: 18811.588 | C60: =B60-[2]贷款!$C$5 -> 1821.6683 | D60: =[3]Sheet1!$B$5 -> 20148.314 | E60: =D60-B60 -> 1336.726 | F60: =[3]Sheet1!$C$5 -> 22032.663 | G60: =F60-D60 -> 1884.349 | H60: =[3]Sheet1!$D$5 -> 23939.636 | I60: =H60-F60 -> 1906.9729 | J60: =[3]Sheet1!$E$5 -> 25906.176 | K60: =J60-H60 -> 1966.5408 | L60: 29293.131 | M60: =L60-J60 -> 3386.9547 | N60: =L60+O60 -> 32293.131 | O60: 3000 | P60: =N60+Q60 -> 35043.131 | Q60: 2750 | R60: =P60+S60 -> 37543.131 | S60: 2500 | T60: =R60+U60 -> 39793.131 | U60: 2250 | V60: =T60+W60 -> 41793.131 | W60: 2000 | X60: =V60-L60 -> 12500 | Y60: =(V60/L60)^(1/5)-1 -> 0.073662594 | AC60: =S60-'2026-2030年盈利测算表'!S60 -> 0 | AD60: =T60-'2026-2030年盈利测算表'!T60 -> 0 | AE60: =U60-'2026-2030年盈利测算表'!U60 -> 0 | AF60: =V60-'2026-2030年盈利测算表'!V60 -> 0 | AG60: =W60-'2026-2030年盈利测算表'!W60 -> 0
A61: 日均 | B61: 18185.416 | C61: =B61-[2]贷款!$C$4 -> 1643.0529 | D61: =[3]Sheet1!$B$4 -> 19859.874 | E61: =D61-B61 -> 1674.4577 | F61: =[3]Sheet1!$C$4 -> 21011.103 | G61: =F61-D61 -> 1151.2291 | H61: =[3]Sheet1!$D$4 -> 23707.664 | I61: =H61-F61 -> 2696.5609 | J61: =[3]Sheet1!$E$4 -> 25679.844 | K61: =J61-H61 -> 1972.1809 | L61: =[3]Sheet1!$F$4 -> 28337.351 | M61: =L61-J61 -> 2657.507 | N61: =L61+O61 -> 31337.351 | O61: 3000 | P61: =N61+Q61 -> 34017.351 | Q61: 2680 | R61: =P61+S61 -> 36457.351 | S61: 2440 | T61: =R61+U61 -> 38647.351 | U61: 2190 | V61: =T61+W61 -> 40617.351 | W61: 1970 | X61: =V61-L61 -> 12280 | Y61: =(V61/L61)^(1/5)-1 -> 0.074658477 | AC61: =S61-'2026-2030年盈利测算表'!S61 -> 0 | AD61: =T61-'2026-2030年盈利测算表'!T61 -> 0 | AE61: =U61-'2026-2030年盈利测算表'!U61 -> 0 | AF61: =V61-'2026-2030年盈利测算表'!V61 -> 0 | AG61: =W61-'2026-2030年盈利测算表'!W61 -> 0
A62: 收益率 | B62: 0.05 | C62: -0.0024 | D62: 0.0475 | E62: =D62-B62 -> -0.0025 | F62: 0.0458 | G62: =F62-D62 -> -0.0017 | H62: 0.0422 | I62: =H62-F62 -> -0.0036 | J62: 0.0392 | K62: =J62-H62 -> -0.003 | L62: 0.0339 | M62: -0.0052 | N62: =息差测算表!C17 -> 0.030316633 | O62: =N62-L62 -> -0.003583367 | P62: =息差测算表!D17 -> 0.02988497 | Q62: =P62-N62 -> -0.00043166256 | R62: =息差测算表!E17 -> 0.029389474 | S62: =R62-P62 -> -0.00049549687 | T62: =息差测算表!F17 -> 0.028923772 | U62: =T62-R62 -> -0.00046570133 | V62: =息差测算表!G17 -> 0.028482507 | W62: =V62-T62 -> -0.00044126479 | X62: =V62-L62 -> -0.0054174925 | Z62: 和后面链接 | AC62: =S62-'2026-2030年盈利测算表'!S62 -> 0 | AD62: =T62-'2026-2030年盈利测算表'!T62 -> 0 | AE62: =U62-'2026-2030年盈利测算表'!U62 -> 0 | AF62: =V62-'2026-2030年盈利测算表'!V62 -> 0 | AG62: =W62-'2026-2030年盈利测算表'!W62 -> 0
A63: 1.2.个人贷款（时点） | B63: 13655.147 | C63: =B63-[2]贷款!$G$5 -> 1877.721 | D63: =[3]Sheet1!$J$5 -> 14776.262 | E63: =D63-B63 -> 1121.1157 | F63: =[3]Sheet1!$K$5 -> 15535.429 | G63: =F63-D63 -> 759.16638 | H63: =[3]Sheet1!$L$5 -> 17109.008 | I63: =H63-F63 -> 1573.5796 | J63: =[3]Sheet1!$M$5 -> 18154.12 | K63: =J63-H63 -> 1045.1116 | L63: =[3]Sheet1!$N$5 -> 18334.921 | M63: =L63-J63 -> 180.80086 | N63: =L63+O63 -> 18184.921 | O63: -150 | P63: =N63+Q63 -> 18184.921 | Q63: 0 | R63: =P63+S63 -> 18284.921 | S63: 100 | T63: =R63+U63 -> 18384.921 | U63: 100 | V63: =T63+W63 -> 18484.921 | W63: 100 | X63: =V63-L63 -> 150 | Y63: =(V63/L63)^(1/5)-1 -> 0.0016308937 | AC63: =S63-'2026-2030年盈利测算表'!S63 -> 0 | AD63: =T63-'2026-2030年盈利测算表'!T63 -> 0 | AE63: =U63-'2026-2030年盈利测算表'!U63 -> 0 | AF63: =V63-'2026-2030年盈利测算表'!V63 -> 0 | AG63: =W63-'2026-2030年盈利测算表'!W63 -> 0
A64: 日均 | B64: 12452.026 | C64: =B64-[2]贷款!$G$4 -> 1381.1017 | D64: =[3]Sheet1!$J$4 -> 14206.957 | E64: =D64-B64 -> 1754.9312 | F64: =[3]Sheet1!$K$4 -> 15179.355 | G64: =F64-D64 -> 972.39778 | H64: =[3]Sheet1!$L$4 -> 16284.214 | I64: =H64-F64 -> 1104.8593 | J64: ='[4]2025年1-12月同比'!$H$10 -> 17635.702 | K64: =J64-H64 -> 1351.4875 | L64: ='[4]2025年1-12月同比'!$C$10 -> 18261.238 | M64: =L64-J64 -> 625.53659 | N64: =L64+O64 -> 18161.238 | O64: -100 | P64: =AVERAGE(N63,P63) -> 18184.921 | Q64: =P64-N64 -> 23.682546 | R64: =AVERAGE(P63,R63) -> 18234.921 | S64: =R64-P64 -> 50 | T64: =AVERAGE(R63,T63) -> 18334.921 | U64: =T64-R64 -> 100 | V64: =AVERAGE(T63,V63) -> 18434.921 | W64: =V64-T64 -> 100 | X64: =V64-L64 -> 173.68255 | Y64: =(V64/L64)^(1/5)-1 -> 0.0018950033 | AC64: =S64-'2026-2030年盈利测算表'!S64 -> 0 | AD64: =T64-'2026-2030年盈利测算表'!T64 -> 0 | AE64: =U64-'2026-2030年盈利测算表'!U64 -> 0 | AF64: =V64-'2026-2030年盈利测算表'!V64 -> 0 | AG64: =W64-'2026-2030年盈利测算表'!W64 -> 0
A65: 收益率 | B65: 0.0533 | C65: =B65-5.28% -> 0.0005 | D65: 0.0511 | E65: =D65-B65 -> -0.0022 | F65: 0.0497 | G65: =F65-D65 -> -0.0014 | H65: 0.0444 | I65: =H65-F65 -> -0.0053 | J65: 0.0394 | K65: =J65-H65 -> -0.005 | L65: 0.0332 | M65: -0.0062 | N65: =息差测算表!C21 -> 0.029991477 | O65: =N65-L65 -> -0.0032085232 | P65: =息差测算表!D21 -> 0.029885171 | Q65: =P65-N65 -> -0.00010630589 | R65: =息差测算表!E21 -> 0.029778017 | S65: =R65-P65 -> -0.00010715386 | T65: =息差测算表!F21 -> 0.029669618 | U65: =T65-R65 -> -0.0001083989 | V65: =息差测算表!G21 -> 0.029562395 | W65: =V65-T65 -> -0.00010722288 | X65: =V65-L65 -> -0.0036376047 | Z65: 和后面链接 | AC65: =S65-'2026-2030年盈利测算表'!S65 -> 0 | AD65: =T65-'2026-2030年盈利测算表'!T65 -> 0 | AE65: =U65-'2026-2030年盈利测算表'!U65 -> 0 | AF65: =V65-'2026-2030年盈利测算表'!V65 -> 0 | AG65: =W65-'2026-2030年盈利测算表'!W65 -> 0
A66: 1.3.信用卡贷款（时点） | B66: 4850.527 | C66: =B66-[2]贷款!$K$5 -> -287.79275 | D66: =[3]Sheet1!$R$5 -> 5275.3074 | E66: =D66-B66 -> 424.78038 | F66: =[3]Sheet1!$S$5 -> 5102.0066 | G66: =F66-D66 -> -173.30084 | H66: =[3]Sheet1!$T$5 -> 5203.162 | I66: =H66-F66 -> 101.15546 | J66: =[3]Sheet1!$U$5 -> 4874.8707 | K66: =J66-H66 -> -328.29126 | L66: =[3]Sheet1!$V$5 -> 4615.1776 | M66: =L66-J66 -> -259.69316 | N66: =L66+O66 -> 4415.1776 | O66: -200 | P66: =N66+Q66 -> 4315.1776 | Q66: -100 | R66: =P66+S66 -> 4315.1776 | S66: 0 | T66: =R66+U66 -> 4315.1776 | U66: 0 | V66: =T66+W66 -> 4315.1776 | W66: 0 | X66: =V66-L66 -> -300 | Y66: =(V66/L66)^(1/5)-1 -> -0.013352428 | AC66: =S66-'2026-2030年盈利测算表'!S66 -> 0 | AD66: =T66-'2026-2030年盈利测算表'!T66 -> 0 | AE66: =U66-'2026-2030年盈利测算表'!U66 -> 0 | AF66: =V66-'2026-2030年盈利测算表'!V66 -> 0 | AG66: =W66-'2026-2030年盈利测算表'!W66 -> 0
A67: 日均 | B67: 4944.845 | C67: =B67-[2]贷款!$K$4 -> -63.494991 | D67: =[3]Sheet1!$R$4 -> 5127.8054 | E67: =D67-B67 -> 182.96043 | F67: =[3]Sheet1!$S$4 -> 5253.4456 | G67: =F67-D67 -> 125.64022 | H67: =[3]Sheet1!$T$4 -> 5154.2296 | I67: =H67-F67 -> -99.216079 | J67: ='[4]2025年1-12月同比'!$H$14 -> 4976.6324 | K67: =J67-H67 -> -177.59713 | L67: ='[4]2025年1-12月同比'!$C$14 -> 4568.4939 | M67: =L67-J67 -> -408.13849 | N67: =L67+O67 -> 4482.4939 | O67: -86 | P67: =AVERAGE(N66,P66) -> 4365.1776 | Q67: =P67-N67 -> -117.31635 | R67: =AVERAGE(P66,R66) -> 4315.1776 | S67: =R67-P67 -> -50 | T67: =AVERAGE(R66,T66) -> 4315.1776 | U67: =T67-R67 -> 0 | V67: =AVERAGE(T66,V66) -> 4315.1776 | W67: =V67-T67 -> 0 | X67: =V67-L67 -> -253.31635 | Y67: =(V67/L67)^(1/5)-1 -> -0.011344187 | AC67: =S67-'2026-2030年盈利测算表'!S67 -> 0 | AD67: =T67-'2026-2030年盈利测算表'!T67 -> 0 | AE67: =U67-'2026-2030年盈利测算表'!U67 -> 0 | AF67: =V67-'2026-2030年盈利测算表'!V67 -> 0 | AG67: =W67-'2026-2030年盈利测算表'!W67 -> 0
A68: 收益率 | B68: 0.093 | C68: =B68-8.99% -> 0.0031 | D68: 0.0848 | E68: =D68-B68 -> -0.0082 | F68: 0.0839 | G68: =F68-D68 -> -0.0009 | H68: 0.084 | I68: =H68-F68 -> 0.0001 | J68: 0.0834 | K68: =J68-H68 -> -0.0006 | L68: =[5]收益成本率测算!$B$73 -> 0.076565211 | M68: ='[6]2025年1-12月同比'!$P$14 -> -0.0068749866 | N68: =息差测算表!C31 -> 0.072 | O68: =N68-L68 -> -0.004565211 | P68: =息差测算表!D31 -> 0.07 | Q68: =P68-N68 -> -0.002 | R68: =息差测算表!E31 -> 0.068 | S68: =R68-P68 -> -0.002 | T68: =息差测算表!F31 -> 0.066 | U68: =T68-R68 -> -0.002 | V68: =息差测算表!G31 -> 0.066 | W68: =V68-T68 -> 0 | X68: =V68-L68 -> -0.010565211 | Z68: 和后面链接 | AC68: =S68-'2026-2030年盈利测算表'!S68 -> 0 | AD68: =T68-'2026-2030年盈利测算表'!T68 -> 0 | AE68: =U68-'2026-2030年盈利测算表'!U68 -> 0 | AF68: =V68-'2026-2030年盈利测算表'!V68 -> 0 | AG68: =W68-'2026-2030年盈利测算表'!W68 -> 0
A69: 1.4.票据贴现（时点） | B69: 4138.0138 | C69: =B69-[7]展示!$B$6 -> 1021.267 | D69: =[7]展示!$D$6 -> 4663.4602 | E69: =D69-B69 -> 525.4464 | F69: =[7]展示!$E$6 -> 5118.2348 | G69: =F69-D69 -> 454.77461 | H69: =[7]展示!$F$6 -> 5168.8794 | I69: =H69-F69 -> 50.644616 | J69: =[7]展示!$G$6 -> 4484.7701 | K69: =J69-H69 -> -684.10933 | L69: 2013.4008 | M69: -2471.3693 | N69: =L69+O69 -> 1513.4008 | O69: -500 | P69: =N69+Q69 -> 1313.4008 | Q69: -200 | R69: =P69+S69 -> 1313.4008 | S69: 0 | T69: =R69+U69 -> 1313.4008 | U69: 0 | V69: =T69+W69 -> 1313.4008 | W69: 0 | X69: =V69-L69 -> -700 | Y69: =(V69/L69)^(1/5)-1 -> -0.081892771 | AC69: =S69-'2026-2030年盈利测算表'!S69 -> 0 | AD69: =T69-'2026-2030年盈利测算表'!T69 -> 0 | AE69: =U69-'2026-2030年盈利测算表'!U69 -> 0 | AF69: =V69-'2026-2030年盈利测算表'!V69 -> 0 | AG69: =W69-'2026-2030年盈利测算表'!W69 -> 0
A70: 日均 | B70: 3553.739 | C70: =B70-[7]展示!$B$5 -> 898.81421 | D70: =[7]展示!$D$5 -> 4086.2957 | E70: =D70-B70 -> 532.55669 | F70: =[7]展示!$E$5 -> 4618.4592 | G70: =F70-D70 -> 532.16344 | H70: =[7]展示!$F$5 -> 4632.1221 | I70: =H70-F70 -> 13.662961 | J70: =[7]展示!$G$5 -> 3975.1957 | K70: =J70-H70 -> -656.92637 | L70: ='[4]2025年1-12月同比'!$C$19 -> 2620.9618 | M70: =L70-3975.2 -> -1354.2382 | N70: =L70+O70 -> 1567.9618 | O70: -1053 | P70: =N70+Q70 -> 1467.9618 | Q70: -100 | R70: =P70+S70 -> 1467.9618 | S70: 0 | T70: =R70+U70 -> 1467.9618 | U70: 0 | V70: =T70+W70 -> 1467.9618 | W70: 0 | X70: =V70-L70 -> -1153 | Y70: =(V70/L70)^(1/5)-1 -> -0.10946537 | AC70: =S70-'2026-2030年盈利测算表'!S70 -> 0 | AD70: =T70-'2026-2030年盈利测算表'!T70 -> 0 | AE70: =U70-'2026-2030年盈利测算表'!U70 -> 0 | AF70: =V70-'2026-2030年盈利测算表'!V70 -> 0 | AG70: =W70-'2026-2030年盈利测算表'!W70 -> 0
A71: 1.5.非银贷款（时点） | B71: 878.595 | C71: =B71-[7]展示!$L$6 -> -307.655 | D71: =[7]展示!$N$6 -> 998.2 | E71: =D71-B71 -> 119.605 | F71: =[7]展示!$O$6 -> 1606.77 | G71: =F71-D71 -> 608.57 | H71: =[7]展示!$P$6 -> 1481.5 | I71: =H71-F71 -> -125.27 | J71: =[7]展示!$Q$6 -> 2700.7 | K71: =J71-H71 -> 1219.2 | L71: 3484.7825 | M71: 784.0825 | N71: =L71+O71 -> 3034.7825 | O71: =O57-O60-O63-O66-O69 -> -450 | P71: =N71+Q71 -> 2584.7825 | Q71: =Q57-Q60-Q63-Q66-Q69 -> -450 | R71: =P71+S71 -> 2284.7825 | S71: =S57-S60-S63-S66-S69 -> -300 | T71: =R71+U71 -> 2434.7825 | U71: =U57-U60-U63-U66-U69 -> 150 | V71: =T71+W71 -> 2834.7825 | W71: =W57-W60-W63-W66-W69 -> 400 | X71: =V71-L71 -> -650 | Y71: =(V71/L71)^(1/5)-1 -> -0.040447341 | AC71: =S71-'2026-2030年盈利测算表'!S71 -> 0 | AD71: =T71-'2026-2030年盈利测算表'!T71 -> 0 | AE71: =U71-'2026-2030年盈利测算表'!U71 -> 0 | AF71: =V71-'2026-2030年盈利测算表'!V71 -> 0 | AG71: =W71-'2026-2030年盈利测算表'!W71 -> 0
A72: 日均 | B72: 1463.7442 | C72: =B72-[7]展示!$L$5 -> 165.68649 | D72: =[7]展示!$N$5 -> 1246.9975 | E72: =D72-B72 -> -216.74668 | F72: =[7]展示!$O$5 -> 1441.6631 | G72: =F72-D72 -> 194.6656 | H72: =[7]展示!$P$5 -> 1571.9499 | I72: =H72-F72 -> 130.28685 | J72: =[7]展示!$Q$5 -> 2167.2447 | K72: =J72-H72 -> 595.29473 | L72: 3413.31 | M72: 1246.07 | N72: =L72+O72 -> 3181.31 | O72: -232 | P72: =(N71+P71)/2 -> 2809.7825 | Q72: =P72-N72 -> -371.5275 | R72: =(P71+R71)/2 -> 2434.7825 | S72: =R72-P72 -> -375 | T72: =(R71+T71)/2 -> 2359.7825 | U72: =T72-R72 -> -75 | V72: =(T71+V71)/2 -> 2634.7825 | W72: =V72-T72 -> 275 | X72: =V72-L72 -> -778.5275 | Y72: =(V72/L72)^(1/5)-1 -> -0.050458813 | AC72: =S72-'2026-2030年盈利测算表'!S72 -> 0 | AD72: =T72-'2026-2030年盈利测算表'!T72 -> 0 | AE72: =U72-'2026-2030年盈利测算表'!U72 -> 0 | AF72: =V72-'2026-2030年盈利测算表'!V72 -> 0 | AG72: =W72-'2026-2030年盈利测算表'!W72 -> 0
A73: 2.人民币非信贷类业务（时点） | B73: =B75+B84+B87+B90 -> 20874 | C73: =C75+C84+C87+C90 -> 4243 | D73: =D75+D84+D87+D90 -> 22171 | E73: =D73-B73 -> 1297 | F73: =F75+F84+F87+F90 -> 23123 | G73: =F73-D73 -> 952 | H73: =H75+H84+H87+H90 -> 23588 | I73: =H73-F73 -> 465 | J73: =J75+J84+J87+J90 -> 23347 | K73: =J73-H73 -> -241 | L73: =L75+L84+L87+L90 -> 26016.126 | M73: =L73-J73 -> 2669.1258 | N73: =L73+O73 -> 29100.712 | O73: =O50-O57-O93-O98*7 -> 3084.5864 | P73: =N73+Q73 -> 30639.527 | Q73: =Q50-Q57-Q93-Q98*7 -> 1538.8149 | R73: =P73+S73 -> 32197.571 | S73: =S50-S57-S93-S98*7 -> 1558.0434 | T73: =R73+U73 -> 33628.969 | U73: =U50-U57-U93-U98*7 -> 1431.3986 | V73: =T73+W73 -> 35083.404 | W73: =W50-W57-W93-W98*7 -> 1454.4353 | X73: =V73-L73 -> 9067.2786 | Y73: =(V73/L73)^(1/5)-1 -> 0.061626672
A74: 日均 | B74: =B76+B85+B88+B91 -> 20396.5 | C74: =C76+C85+C88+C91 -> 3525.5 | D74: =D76+D85+D88+D91 -> 21697.845 | E74: =D74-B74 -> 1301.345 | F74: =F76+F85+F88+F91 -> 21715.209 | G74: =F74-D74 -> 17.363917 | H74: =H76+H85+H88+H91 -> 22246.056 | I74: =H74-F74 -> 530.84736 | J74: =J76+J85+J88+J91 -> 22326.4 | K74: =J74-H74 -> 80.343577 | L74: =L76+L85+L88+L91 -> 24453 | M74: =L74-J74 -> 2126.6001 | N74: =L74+O74 -> 25309.045 | O74: =O76+O85+O88+O91 -> 856.04472 | P74: =N74+Q74 -> 29590.654 | Q74: =Q76+Q85+Q88+Q91 -> 4281.609 | R74: =P74+S74 -> 31147.47 | S74: =S76+S85+S88+S91 -> 1556.8168 | T74: =R74+U74 -> 32645.319 | U74: =U76+U85+U88+U91 -> 1497.8482 | V74: =T74+W74 -> 34103.321 | W74: =W76+W85+W88+W91 -> 1458.0028 | X74: =V74-L74 -> 9650.3215 | Y74: =(V74/L74)^(1/5)-1 -> 0.068791291
A75: 2.1.债券投资（时点） | B75: =16765-B95 -> 12831 | C75: =B75-8998 -> 3833 | D75: =19241-D95 -> 14364 | E75: =D75-B75 -> 1533 | F75: =20797-F95 -> 15396 | G75: =F75-D75 -> 1032 | H75: =21863-H95 -> 15853 | I75: =H75-F75 -> 457 | J75: =22065-J95 -> 15735 | K75: =J75-H75 -> -118 | L75: 17897.126 | M75: =L75-14980 -> 2917.1258 | N75: =L75+O75 -> 19397.126 | O75: =O78+O81 -> 1500 | P75: =N75+Q75 -> 20397.126 | Q75: =Q78+Q81 -> 1000 | R75: =P75+S75 -> 21397.126 | S75: =S78+S81 -> 1000 | T75: =R75+U75 -> 22397.126 | U75: =U78+U81 -> 1000 | V75: =T75+W75 -> 23397.126 | W75: =W78+W81 -> 1000 | X75: =V75-L75 -> 5500 | Y75: =(V75/L75)^(1/5)-1 -> 0.055056807
A76: 日均 | B76: 11734 | C76: =B76-8998 -> 2736 | D76: 13425 | E76: =D76-B76 -> 1691 | F76: 14297 | G76: =F76-D76 -> 872 | H76: 14916 | I76: =H76-F76 -> 619 | J76: 14980 | K76: =J76-H76 -> 64 | L76: =17383-L106*7 -> 16872 | M76: =L76-J76 -> 1892 | N76: =L76+O76 -> 17599 | O76: =O79+O82 -> 727 | P76: =N76+Q76 -> 20104 | Q76: =Q79+Q82 -> 2505 | R76: =P76+S76 -> 21104 | S76: =S79+S82 -> 1000 | T76: =R76+U76 -> 22104 | U76: =U79+U82 -> 1000 | V76: =T76+W76 -> 23104 | W76: =W79+W82 -> 1000 | X76: =V76-L76 -> 6232 | Y76: =(V76/L76)^(1/5)-1 -> 0.064888463
A77: 收益率 | B77: 0.0345 | C77: =B77-3.77% -> -0.0032 | D77: 0.0326 | E77: =D77-B77 -> -0.0019 | F77: 0.03 | G77: =F77-D77 -> -0.0026 | H77: 0.0276 | I77: =H77-F77 -> -0.0024 | J77: 0.0261 | K77: =J77-H77 -> -0.0015 | L77: 0.0221 | M77: =L77-J77 -> -0.004 | N77: =息差测算表!C35 -> 0.0203656 | O77: =N77-L77 -> -0.0017344001 | P77: =息差测算表!D35 -> 0.0193123 | Q77: =P77-N77 -> -0.0010533001 | R77: =息差测算表!E35 -> 0.019333333 | S77: =R77-P77 -> 2.1033602e-05 | T77: =息差测算表!F35 -> 0.019 | U77: =T77-R77 -> -0.00033333333 | V77: =息差测算表!G35 -> 0.018333333 | W77: =V77-T77 -> -0.00066666667 | X77: =V77-L77 -> -0.0037666667 | Z77: 和后面链接
A78: 2.1.1金市自营债券（人民币，时点） | H78: 13753 | J78: 14147 | L78: 12358 | M78: -1789 | N78: =L78+O78 -> 13858 | O78: 1500 | P78: =N78+Q78 -> 14858 | Q78: 1000 | R78: =P78+S78 -> 15858 | S78: 1000 | T78: =R78+U78 -> 16858 | U78: 1000 | V78: =T78+W78 -> 17858 | W78: 1000 | X78: =V78-L78 -> 5500 | Y78: =(V78/L78)^(1/5)-1 -> 0.076408022
A79: 日均 | L79: 13030 | M79: -514 | N79: =(L78+N78)/2-1255 -> 11853 | O79: =N79-L79 -> -1177 | P79: =(N78+P78)/2 -> 14358 | Q79: =P79-N79 -> 2505 | R79: =(P78+R78)/2 -> 15358 | S79: =R79-P79 -> 1000 | T79: =(R78+T78)/2 -> 16358 | U79: =T79-R79 -> 1000 | V79: =(T78+V78)/2 -> 17358 | W79: =V79-T79 -> 1000 | X79: =V79-L79 -> 4328 | Y79: =(V79/L79)^(1/5)-1 -> 0.059036805
A80: 收益率
A81: 2.1.2司库债券（时点） | H81: 1494 | J81: 798 | L81: 5027 | M81: 2688 | N81: =O81+L81 -> 5027 | O81: 0 | P81: =Q81+N81 -> 5027 | Q81: 0 | R81: =S81+P81 -> 5027 | S81: 0 | T81: =U81+R81 -> 5027 | U81: 0 | V81: =W81+T81 -> 5027 | W81: 0 | X81: =V81-L81 -> 0 | Y81: =(V81/L81)^(1/5)-1 -> 0
A82: 日均 | L82: 3123 | M82: 2244 | N82: =(N81+L81)/2 -> 5027 | O82: =N82-L82 -> 1904 | P82: =(P81+N81)/2 -> 5027 | Q82: =P82-N82 -> 0 | R82: =(R81+P81)/2 -> 5027 | S82: =R82-P82 -> 0 | T82: =(T81+R81)/2 -> 5027 | U82: =T82-R82 -> 0 | V82: =(V81+T81)/2 -> 5027 | W82: =V82-T82 -> 0 | X82: =V82-L82 -> 1904 | Y82: =(V82/L82)^(1/5)-1 -> 0.099885256
A83: 收益率
A84: 2.2.结构化融资（时点） | B84: 2109 | C84: -119 | D84: 2252 | E84: =D84-B84 -> 143 | F84: 2503 | G84: =F84-D84 -> 251 | H84: 2242 | I84: =H84-F84 -> -261 | J84: 2086 | K84: =J84-H84 -> -156 | L84: 2043 | M84: -43 | N84: =O84+L84 -> 2043 | O84: 0 | P84: =Q84+N84 -> 2043 | Q84: 0 | R84: =S84+P84 -> 2043 | S84: 0 | T84: =U84+R84 -> 2043 | U84: 0 | V84: =W84+T84 -> 2043 | W84: 0 | X84: =V84-L84 -> 0 | Y84: =(V84/L84)^(1/5)-1 -> 0
A85: 日均 | B85: 3646 | C85: =B85-3481 -> 165 | D85: 2852 | E85: =D85-B85 -> -794 | F85: 2632 | G85: =F85-D85 -> -220 | H85: =1816+729 -> 2545 | I85: =H85-F85 -> -87 | J85: =1511+646 -> 2157 | K85: =J85-H85 -> -388 | L85: 2102 | M85: 0 | N85: =AVERAGE(L84,N84) -> 2043 | O85: =N85-L85 -> -59 | P85: =AVERAGE(N84,P84) -> 2043 | Q85: =P85-N85 -> 0 | R85: =AVERAGE(P84,R84) -> 2043 | S85: =R85-P85 -> 0 | T85: =AVERAGE(R84,T84) -> 2043 | U85: =T85-R85 -> 0 | V85: =AVERAGE(T84,V84) -> 2043 | W85: =V85-T85 -> 0 | X85: =V85-L85 -> -59 | Y85: =(V85/L85)^(1/5)-1 -> -0.0056778113
A86: 收益率 | B86: 0.0582 | C86: =B86-6.01% -> -0.0019 | D86: 0.0531 | E86: =D86-B86 -> -0.0051 | F86: 0.0531 | G86: =F86-D86 -> 0 | H86: 0.0489 | I86: =H86-F86 -> -0.0042 | J86: 0.0454 | K86: =J86-H86 -> -0.0035 | L86: 0.0395 | M86: =L86-J86 -> -0.0059 | N86: =息差测算表!C47 -> 0.035974089 | O86: =N86-L86 -> -0.0035259114 | P86: =息差测算表!D47 -> 0.035996684 | Q86: =P86-N86 -> 2.2595757e-05 | R86: =息差测算表!E47 -> 0.034996684 | S86: =R86-P86 -> -0.001 | T86: =息差测算表!F47 -> 0.033996684 | U86: =T86-R86 -> -0.001 | V86: =息差测算表!G47 -> 0.033178259 | W86: =V86-T86 -> -0.00081842516 | X86: =V86-L86 -> -0.0063217408
A87: 2.3.同业资产（时点，不含拆放非银） | B87: =D87-E87 -> 1797 | C87: =B87-1034 -> 763 | D87: 1513 | E87: -284 | F87: 683 | G87: =F87-D87 -> -830 | H87: 1500 | I87: =H87-F87 -> 817 | J87: 2362 | K87: =J87-H87 -> 862 | L87: 2468 | M87: 106 | N87: =L87+O87 -> 3876.5864 | O87: =O73-O75-O84-O90 -> 1408.5864 | P87: =N87+Q87 -> 4228.4013 | Q87: =Q73-Q75-Q84-Q90 -> 351.81491 | R87: =P87+S87 -> 4588.4447 | S87: =S73-S75-S84-S90 -> 360.04339 | T87: =R87+U87 -> 4810.8433 | U87: =U73-U75-U84-U90 -> 222.39857 | V87: =T87+W87 -> 5045.2786 | W87: =W73-W75-W84-W90 -> 234.43526 | X87: =V87-L87 -> 2577.2786 | Y87: =(V87/L87)^(1/5)-1 -> 0.15374013
A88: 日均 | B88: =(B87+1034)/2 -> 1415.5 | C88: =B88-868 -> 547.5 | D88: =(D87+B87)/2 -> 1655 | E88: =D88-B88 -> 239.5 | F88: =(F87+D87)/2 -> 1098 | G88: =F88-D88 -> -557 | H88: =(H87+F87)/2 -> 1091.5 | I88: =H88-F88 -> -6.5 | J88: =(2362+1500)/2 -> 1931 | K88: =J88-H88 -> 839.5 | L88: =(2362+2468)/2 -> 2415 | M88: =L88-J88 -> 484 | N88: =AVERAGE(L87,N87)-555 -> 2617.2932 | O88: =N88-L88 -> 202.29321 | P88: =AVERAGE(N87,P87) -> 4052.4939 | Q88: =P88-N88 -> 1435.2007 | R88: =AVERAGE(P87,R87) -> 4408.423 | S88: =R88-P88 -> 355.92915 | T88: =AVERAGE(R87,T87) -> 4699.644 | U88: =T88-R88 -> 291.22098 | V88: =AVERAGE(T87,V87) -> 4928.0609 | W88: =V88-T88 -> 228.41692 | X88: =V88-L88 -> 2513.0609 | Y88: =(V88/L88)^(1/5)-1 -> 0.15332521
A89: 收益率
A90: 2.4.存款准备金（时点） | B90: 4137 | C90: -234 | D90: 4042 | E90: =D90-B90 -> -95 | F90: 4541 | G90: =F90-D90 -> 499 | H90: 3993 | I90: =H90-F90 -> -548 | J90: 3164 | K90: =J90-H90 -> -829 | L90: 3608 | M90: 445 | N90: =L90+O90 -> 3784 | O90: =O125*5.5% -> 176 | P90: =N90+Q90 -> 3971 | Q90: =Q125*5.5% -> 187 | R90: =P90+S90 -> 4169 | S90: =S125*5.5% -> 198 | T90: =R90+U90 -> 4378 | U90: =U125*5.5% -> 209 | V90: =T90+W90 -> 4598 | W90: =W125*5.5% -> 220 | X90: =V90-L90 -> 990 | Y90: =(V90/L90)^(1/5)-1 -> 0.049688617
A91: 日均 | B91: 3601 | C91: =B91-3524 -> 77 | D91: 3765.845 | E91: =D91-B91 -> 164.84503 | F91: 3688.2089 | G91: =F91-D91 -> -77.636083 | H91: 3693.5563 | I91: =H91-F91 -> 5.3473642 | J91: 3258.3999 | K91: =J91-H91 -> -435.15642 | L91: 3064 | M91: =L91-J91 -> -194.39989 | N91: =$L$91*N126/$L$126-152 -> 3049.7515 | O91: =N91-L91 -> -14.248496 | P91: =$L$91*P126/$L$126 -> 3391.1598 | Q91: =P91-N91 -> 341.40832 | R91: =$L$91*R126/$L$126 -> 3592.0474 | S91: =R91-P91 -> 200.88761 | T91: =$L$91*T126/$L$126 -> 3798.6747 | U91: =T91-R91 -> 206.62726 | V91: =$L$91*V126/$L$126 -> 4028.2605 | W91: =V91-T91 -> 229.58584 | X91: =V91-L91 -> 964.26053 | Y91: =(V91/L91)^(1/5)-1 -> 0.056247656
A92: 收益率 | B92: 0.0162 | C92: =B92-1.6% -> 0.0002 | D92: 0.0159 | E92: =D92-B92 -> -0.0003 | F92: 0.0156 | G92: =F92-D92 -> -0.0003 | H92: 0.016 | I92: =H92-F92 -> 0.0004 | J92: 0.0161 | K92: =J92-H92 -> 0.0001 | L92: 0.016 | M92: =L92-J92 -> -0.0001 | N92: =息差测算表!C49 -> 0.015965592 | O92: =N92-L92 -> -3.4407975e-05 | P92: =息差测算表!D49 -> 0.015965592 | Q92: =P92-N92 -> 0 | R92: =息差测算表!E49 -> 0.015965592 | S92: =R92-P92 -> 0 | T92: =息差测算表!F49 -> 0.015965592 | U92: =T92-R92 -> 0 | V92: =息差测算表!G49 -> 0.015965592 | W92: =V92-T92 -> 0 | X92: =V92-L92 -> -3.4407975e-05
A93: 3.人民币非生息资产（时点） | B93: =B50-B57-B73-B98*7 -> 5675.7599 | C93: =C50-C57-C73-C98*7 -> -1623.9286 | D93: =D50-D57-D73-D98*7 -> 6317.8964 | E93: =D93-B93 -> 642.13649 | F93: =F50-F57-F73-F98*7 -> 6321.8973 | G93: =F93-D93 -> 4.0008535 | H93: =H50-H57-H73-H98*7 -> 7009.3147 | I93: =H93-F93 -> 687.4174 | J93: =J50-J57-J73-J98*7 -> 7934.7529 | K93: =J93-H93 -> 925.43826 | L93: =L50-L57-L73-L98*7 -> 8906.1655 | M93: =L93-J93 -> 971.41253 | N93: =L93+O93 -> 9106.1655 | O93: =O95+O97 -> 200 | P93: =N93+Q93 -> 9206.1655 | Q93: =Q95+Q97 -> 100 | R93: =P93+S93 -> 9306.1655 | S93: =S95+S97 -> 100 | T93: =R93+U93 -> 9406.1655 | U93: =U95+U97 -> 100 | V93: =T93+W93 -> 9506.1655 | W93: =W95+W97 -> 100
A94: 日均 | B94: =B51-B58-B74-B99*7 -> 4354.2503 | C94: =C51-C58-C74-C99*7 -> -1066.1403 | D94: =D51-D58-D74-D99*7 -> 5225.7759 | E94: =D94-B94 -> 871.52559 | F94: =F51-F58-F74-F99*7 -> 6485.0008 | G94: =F94-D94 -> 1259.2249 | H94: =H51-H58-H74-H99*7 -> 7625.5046 | I94: =H94-F94 -> 1140.5038 | J94: =J51-J58-J74-J99*7 -> 6927.8363 | K94: =J94-H94 -> -697.66824 | L94: =L51-L58-L74-L99*7 -> 7309.1248 | M94: =L94-J94 -> 381.28841 | N94: =L94+O94 -> 6897.1248 | O94: =O96 -> -412 | P94: =N94+Q94 -> 7647.1248 | Q94: =Q96 -> 750 | R94: =P94+S94 -> 7747.1248 | S94: =S96 -> 100 | T94: =R94+U94 -> 7847.1248 | U94: =U96 -> 100 | V94: =T94+W94 -> 7947.1248 | W94: =W96 -> 100 | X94: =V94-L94 -> 638 | Y94: =(V94/L94)^(1/5)-1 -> 0.016878187
A95: 1.TPL（时点） | B95: 3934 | C95: =B95-2975 -> 959 | D95: 4877 | E95: =D95-B95 -> 943 | F95: 5401 | G95: =F95-D95 -> 524 | H95: 6010 | I95: =H95-F95 -> 609 | J95: 6330 | K95: =J95-H95 -> 320 | L95: 6631 | M95: =L95-J95 -> 301 | N95: =O95+L95 -> 6831 | O95: 200 | P95: =Q95+N95 -> 6931 | Q95: 100 | R95: =S95+P95 -> 7031 | S95: 100 | T95: =U95+R95 -> 7131 | U95: 100 | V95: =W95+T95 -> 7231 | W95: 100 | X95: =V95-L95 -> 600 | Y95: =(V95/L95)^(1/5)-1 -> 0.01747528
A96: 日均 | B96: 3357 | D96: 4536 | E96: =D96-B96 -> 1179 | F96: 5321 | G96: =F96-D96 -> 785 | H96: 5843 | I96: =H96-F96 -> 522 | J96: 6042 | K96: =J96-H96 -> 199 | L96: 6543 | M96: =L96-J96 -> 501 | N96: =(N95+L95)/2-600 -> 6131 | O96: =N96-L96 -> -412 | P96: =(P95+N95)/2 -> 6881 | Q96: =P96-N96 -> 750 | R96: =(R95+P95)/2 -> 6981 | S96: =R96-P96 -> 100 | T96: =(T95+R95)/2 -> 7081 | U96: =T96-R96 -> 100 | V96: =(V95+T95)/2 -> 7181 | W96: =V96-T96 -> 100 | X96: =V96-L96 -> 638 | Y96: =(V96/L96)^(1/5)-1 -> 0.018782793
A97: 2.其他（时点） | B97: =B93-B95 -> 1741.7599 | C97: =C93-C95 -> -2582.9286 | D97: =D93-D95 -> 1440.8964 | E97: =E93-E95 -> -300.86351 | F97: =F93-F95 -> 920.89725 | G97: =G93-G95 -> -519.99915 | H97: =H93-H95 -> 999.31466 | I97: =I93-I95 -> 78.417402 | ... M97: =M93-M95 -> 670.41253 | N97: =O97+L97 -> 2275.1655 | O97: 0 | P97: =Q97+N97 -> 2275.1655 | Q97: 0 | R97: =S97+P97 -> 2275.1655 | S97: 0 | T97: =U97+R97 -> 2275.1655 | U97: 0 | V97: =W97+T97 -> 2275.1655 | W97: 0 | X97: =V97-L97 -> 0 | Y97: =(V97/L97)^(1/5)-1 -> 0
A98: （二）外币小计（时点，亿美元） | B98: =B100+B103+B109 -> 360.91 | C98: =C100+C103+C109 -> 104.96 | D98: =D100+D103+D109 -> 330.08 | E98: =D98-B98 -> -30.83 | F98: =F100+F103+F109 -> 313 | G98: =F98-D98 -> -17.08 | H98: =H100+H103+H109 -> 307.5 | I98: =H98-F98 -> -5.5 | J98: =J100+J103+J109 -> 347.23 | K98: =J98-I98 -> 352.73 | L98: =L100+L103+L109 -> 358.75 | M98: =L98-J98 -> 11.52 | N98: =O98+L98 -> 533.75 | O98: =O100+O103+O109 -> 175 | P98: =Q98+N98 -> 593.75 | Q98: =Q100+Q103+Q109 -> 60 | R98: =S98+P98 -> 603.75 | S98: =S100+S103+S109 -> 10 | T98: =U98+R98 -> 613.75 | U98: =U100+U103+U109 -> 10 | V98: =W98+T98 -> 623.75 | W98: =W100+W103+W109 -> 10
A99: 日均 | B99: =B101+B104+B110 -> 375.64 | C99: =C101+C104+C110 -> 70.64 | D99: =D101+D104+D110 -> 414.35 | E99: =D99-B99 -> 38.71 | F99: =F101+F104+F110 -> 432.395 | G99: =F99-D99 -> 18.045 | H99: =H101+H104+H110 -> 314.18 | I99: =H99-F99 -> -118.215 | J99: =J101+J104+J110 -> 317.735 | K99: =J99-I99 -> 435.95 | L99: =L101+L104+L110 -> 343.36 | M99: =L99-J99 -> 25.625 | N99: =O99+L99 -> 464.75 | O99: =O101+O104+O110 -> 121.39 | P99: =Q99+N99 -> 563.75 | Q99: =Q101+Q104+Q110 -> 99 | R99: =S99+P99 -> 598.75 | S99: =S101+S104+S110 -> 35 | T99: =U99+R99 -> 608.75 | U99: =U101+U104+U110 -> 10 | V99: =W99+T99 -> 618.75 | W99: =W101+W104+W110 -> 10 | X99: =V99-L99 -> 275.39 | Y99: =(V99/L99)^(1/5)-1 -> 0.1250015
A100: 1.外币贷款（时点） | B100: 128.19 | C100: =B100-103.24 -> 24.95 | D100: 171.89 | E100: =D100-B100 -> 43.7 | F100: 135.69 | G100: =F100-D100 -> -36.2 | H100: 122.71 | I100: =H100-F100 -> -12.98 | J100: 123.75 | K100: =J100-H100 -> 1.04 | L100: 143.59 | M100: =L100-J100 -> 19.84 | N100: =L100+O100 -> 163.59 | O100: 20 | P100: =N100+Q100 -> 213.59 | Q100: =30+20 -> 50 | R100: =P100+S100 -> 263.59 | S100: =30+20 -> 50 | T100: =R100+U100 -> 313.59 | U100: =30+20 -> 50 | V100: =T100+W100 -> 363.59 | W100: =30+20 -> 50 | X100: =V100-L100 -> 220 | Y100: =(V100/L100)^(1/5)-1 -> 0.20419702
...

Sheet 板块（积极-原版本）
A1: 板块条线收入预测（积极情景）
A2: 板块 | B2: 指标 | C2: 2023年 | D2: 2024年 | F2: 2025年 | H2: 2026年 | J2: 2027年 | L2: 2028年 | N2: 2029年 | P2: 2030年
D3: 当年 | E3: 比上年 | F3: 当年 | G3: 比上年 | H3: 当年 | I3: 比上年 | J3: 当年 | K3: 比上年 | L3: 当年 | M3: 比上年 | N3: 当年 | O3: 比上年 | P3: 当年 | Q3: 比上年 | S3: 2026 | U3: 2027 | W3: 2028 | Y3: 2029 | AA3: 2030
A4: 三大板块合计占比 | B4: 一、营业净收入 | C4: =(C10+C27+C44)/'2026-2030年盈利测算表'!H12 -> 0.95686173 | D4: =(D10+D27+D44)/'2026-2030年盈利测算表'!J12 -> 0.91533694 | E4: =D4-C4 -> -0.04152479 | F4: =(F10+F27+F44)/'2026-2030年盈利测算表'!L12 -> 0.92221266 | G4: =F4-D4 -> 0.0068757152 | H4: =(H10+H27+H44)/S4 -> 0.92019874 | I4: =H4-F4 -> -0.0020139139 | J4: =(J10+J27+J44)/U4 -> 0.91155639 | K4: =J4-H4 -> -0.0086423544 | L4: =(L10+L27+L44)/W4 -> 0.91676492 | M4: =L4-J4 -> 0.0052085325 | N4: =(N10+N27+N44)/Y4 -> 0.93461815 | O4: =N4-L4 -> 0.017853234 | P4: =(P10+P27+P44)/AA4 -> 0.92879635 | Q4: =P4-N4 -> -0.0058218052 | S4: ='2026-2030年盈利测算表'!N12 -> 2027.8379 | U4: ='2026-2030年盈利测算表'!P12 -> 2090.0167 | W4: ='2026-2030年盈利测算表'!R12 -> 2184.245 | Y4: ='2026-2030年盈利测算表'!T12 -> 2286.2919 | AA4: ='2026-2030年盈利测算表'!V12 -> 2374.435
B5: （一）利息净收入 | C5: =(C11+C28+C45)/'2026-2030年盈利测算表'!H13 -> 0.90976725 | D5: =(D11+D28+D45)/'2026-2030年盈利测算表'!J13 -> 0.86587508 | E5: =D5-C5 -> -0.043892171 | F5: =(F11+F28+F45)/'2026-2030年盈利测算表'!L13 -> 0.85895075 | G5: =F5-D5 -> -0.0069243253 | H5: =(H11+H28+H45)/S5 -> 0.85520408 | I5: =H5-F5 -> -0.0037466774 | J5: =(J11+J28+J45)/U5 -> 0.84516172 | K5: =J5-H5 -> -0.010042359 | L5: =(L11+L28+L45)/W5 -> 0.85361029 | M5: =L5-J5 -> 0.0084485723 | N5: =(N11+N28+N45)/Y5 -> 0.87980918 | O5: =N5-L5 -> 0.02619889 | P5: =(P11+P28+P45)/AA5 -> 0.87095161 | Q5: =P5-N5 -> -0.0088575659 | S5: ='2026-2030年盈利测算表'!N13 -> 1398.7484 | U5: ='2026-2030年盈利测算表'!P13 -> 1456.7307 | W5: ='2026-2030年盈利测算表'!R13 -> 1520.0171 | Y5: ='2026-2030年盈利测算表'!T13 -> 1582.4091 | AA5: ='2026-2030年盈利测算表'!V13 -> 1625.5724
B6: （二）非息净收入 | C6: =(C12+C29+C46)/'2026-2030年盈利测算表'!H14 -> 1.0714014 | D6: =(D12+D29+D46)/'2026-2030年盈利测算表'!J14 -> 1.0249573 | E6: =D6-C6 -> -0.046444176 | F6: =(F12+F29+F46)/'2026-2030年盈利测算表'!L14 -> 1.0698897 | G6: =F6-D6 -> 0.044932413 | H6: =(H12+H29+H46)/S6 -> 1.0647111 | I6: =H6-F6 -> -0.0051785817 | J6: =(J12+J29+J46)/U6 -> 1.0642823 | K6: =J6-H6 -> -0.00042881459 | L6: =(L12+L29+L46)/W6 -> 1.0612878 | M6: =L6-J6 -> -0.0029944808 | N6: =(N12+N29+N46)/Y6 -> 1.057835 | O6: =N6-L6 -> -0.0034527962 | P6: =(P12+P29+P46)/AA6 -> 1.0543612 | Q6: =P6-N6 -> -0.0034738048 | S6: ='2026-2030年盈利测算表'!N14 -> 629.08942 | U6: ='2026-2030年盈利测算表'!P14 -> 633.28595 | W6: ='2026-2030年盈利测算表'!R14 -> 664.22788 | Y6: ='2026-2030年盈利测算表'!T14 -> 703.88282 | AA6: ='2026-2030年盈利测算表'!V14 -> 748.86255
B7: 二、净利润 | C7: =(C18+C35+C52)/'2026-2030年盈利测算表'!H11 -> 0.94393636 | D7: =(D18+D35+D52)/'2026-2030年盈利测算表'!J11 -> 0.90055308 | E7: =D7-C7 -> -0.043383282 | F7: =(F18+F35+F52)/'2026-2030年盈利测算表'!L11 -> 0.93963105 | G7: =F7-D7 -> 0.039077971 | H7: =(H18+H35+H52)/S7 -> 0.94100599 | I7: =H7-F7 -> 0.0013749408 | J7: =(J18+J35+J52)/U7 -> 0.91865229 | K7: =J7-H7 -> -0.022353701 | L7: =(L18+L35+L52)/W7 -> 0.94023692 | M7: =L7-J7 -> 0.021584634 | N7: =(N18+N35+N52)/Y7 -> 0.99145835 | O7: =N7-L7 -> 0.051221429 | P7: =(P18+P35+P52)/AA7 -> 0.97303126 | Q7: =P7-N7 -> -0.018427087 | S7: ='2026-2030年盈利测算表'!N11 -> 685.87278 | U7: ='2026-2030年盈利测算表'!P11 -> 718.39854 | W7: ='2026-2030年盈利测算表'!R11 -> 762.80085 | Y7: ='2026-2030年盈利测算表'!T11 -> 811.01314 | AA7: ='2026-2030年盈利测算表'!V11 -> 855.33941
A8: 公司业务板块 | B8: 对公板块占全行营收比 | C8: =C10/'2026-2030年盈利测算表'!$H$12 -> 0.39484836 | D8: =D10/'2026-2030年盈利测算表'!$J$12 -> 0.37888875 | E8: =D8-C8 -> -0.015959606 | F8: =F10/'2026-2030年盈利测算表'!$L$12 -> 0.40487602 | G8: =F8-D8 -> 0.025987265 | H8: =H10/S$4 -> 0.40420503 | I8: =H8-F8 -> -0.00067098598 | J8: =J10/U$4 -> 0.40738358 | K8: =J8-H8 -> 0.0031785531 | L8: =L10/W$4 -> 0.41589065 | M8: =L8-J8 -> 0.0085070713 | N8: =N10/Y$4 -> 0.42747467 | O8: =N8-L8 -> 0.011584012 | P8: =P10/AA$4 -> 0.42520141 | Q8: =P8-N8 -> -0.0022732528
B9: 对公板块占全行净利润比 | C9: =C18/'2026-2030年盈利测算表'!$H$11 -> 0.56009657 | D9: =D18/'2026-2030年盈利测算表'!$J$11 -> 0.52600875 | E9: =D9-C9 -> -0.034087815 | F9: =F18/'2026-2030年盈利测算表'!$L$11 -> 0.46529463 | G9: =F9-D9 -> -0.060714125 | H9: =H18/S$7 -> 0.46161203 | I9: =H9-F9 -> -0.0036826005 | J9: =J18/U$7 -> 0.4621097 | K9: =J9-H9 -> 0.00049767392 | L9: =L18/W$7 -> 0.4909752 | M9: =L9-J9 -> 0.028865501 | N9: =N18/Y$7 -> 0.45829759 | O9: =N9-L9 -> -0.032677617 | P9: =P18/AA$7 -> 0.38469681 | Q9: =P9-N9 -> -0.073600777
B10: 一、营业净收入 | C10: 754.95006 | D10: 758.91417 | E10: =D10-C10 -> 3.964109 | F10: 786.12347 | G10: =F10-D10 -> 27.209299 | H10: =H11+H12 -> 819.66226 | I10: =I11+I12 -> 33.538796 | J10: =J11+J12 -> 851.43849 | K10: =K11+K12 -> 31.776227 | L10: =L11+L12 -> 908.40709 | M10: =M11+M12 -> 56.968602 | N10: =N11+N12 -> 977.33186 | O10: =O11+O12 -> 68.924766 | ... Q10: =Q11+Q12 -> 32.281249
B11: （一）利息净收入 | C11: 662.43869 | D11: 655.02325 | E11: =D11-C11 -> -7.41544 | F11: 675.2832 | G11: =F11-D11 -> 20.259947 | H11: =F11+I11 -> 705.22095 | I11: =H63-F63 -> 29.937757 | J11: =H11+K11 -> 734.10386 | K11: =J63-H63 -> 28.882906 | L11: =J11+M11 -> 787.93872 | M11: =L63-J63 -> 53.834857 | N11: =L11+O11 -> 853.474 | O11: =N63-L63 -> 65.535284 | P11: =N11+Q11 -> 882.09361 | Q11: =P63-N63 -> 28.619609
B12: （二）非息净收入 | C12: 92.51137 | D12: 103.89092 | E12: =D12-C12 -> 11.379549 | F12: 110.84027 | G12: =F12-D12 -> 6.949351 | H12: =F12+I12 -> 114.44131 | I12: =中收测算表!$L9-中收测算表!$L8 -> 3.6010382 | J12: =H12+K12 -> 117.33463 | K12: =中收测算表!$L10-中收测算表!$L9 -> 2.8933207 | L12: =J12+M12 -> 120.46837 | M12: =中收测算表!$L11-中收测算表!$L10 -> 3.1337446 | N12: =L12+O12 -> 123.85785 | O12: =中收测算表!$L12-中收测算表!$L11 -> 3.3894812 | P12: =N12+Q12 -> 127.5195 | Q12: =中收测算表!$L13-中收测算表!$L12 -> 3.6616407
B13: 二、营业支出 | C13: 286.66983 | D13: 292.99939 | E13: =D13-C13 -> 6.329559 | F13: 384.30306 | G13: =F13-D13 -> 91.303671 | H13: =H15+H16+H14 -> 399.30229 | I13: =H13-F13 -> 14.999232 | J13: =J15+J16+J14 -> 411.58885 | K13: =J13-H13 -> 12.286557 | L13: =L15+L16+L14 -> 419.7797 | M13: =L13-J13 -> 8.1908535 | N13: =N15+N16+N14 -> 484.77724 | O13: =N13-L13 -> 64.997539 | P13: =P15+P16+P14 -> 553.86014 | Q13: =P13-N13 -> 69.082897
B14: （一）税金及附加 | C14: 8.683676 | D14: 9.098435 | E14: =D14-C14 -> 0.414759 | F14: 8.687011 | G14: =F14-D14 -> -0.411424 | H14: =F14 -> 8.687011 | I14: 0 | J14: =H14 -> 8.687011 | K14: 0 | L14: =J14 -> 8.687011 | M14: 0 | N14: =L14 -> 8.687011 | O14: 0 | P14: =N14 -> 8.687011 | Q14: 0
B15: （二）营业费用 | C15: 177.66118 | D15: 180.12733 | E15: =D15-C15 -> 2.466141 | F15: 175.07805 | G15: =F15-D15 -> -5.049275 | H15: =F15+I15 -> 182.85053 | I15: =I93 -> 7.7724776 | J15: =H15+K15 -> 188.15812 | K15: =K93 -> 5.3075895 | L15: =J15+M15 -> 196.32865 | M15: =M93 -> 8.1705297 | N15: =L15+O15 -> 205.17385 | O15: =O93 -> 8.8452024 | P15: =N15+Q15 -> 212.7441 | Q15: =Q93 -> 7.5702501
B16: （三）资产减值损失 | C16: 100.32497 | D16: 103.77363 | E16: =D16-C16 -> 3.448659 | F16: 200.538 | G16: =F16-D16 -> 96.76437 | H16: =F16+I16 -> 207.76475 | I16: =I99 -> 7.2267546 | J16: =H16+K16 -> 214.74372 | K16: =K99 -> 6.9789675 | L16: =J16+M16 -> 214.76404 | M16: =M99 -> 0.020323858 | N16: =L16+O16 -> 270.91638 | O16: =O99 -> 56.152336 | P16: =N16+Q16 -> 332.42903 | Q16: =Q99 -> 61.512647
B17: 三、所得税费用 | C17: 117.33914 | D17: 116.76586 | E17: =D17-C17 -> -0.573283 | F17: 100.75284 | G17: =F17-D17 -> -16.013012 | H17: =F17+I17 -> 103.75284 | I17: =I106 -> 3 | J17: =H17+K17 -> 107.87071 | K17: =K106 -> 4.1178628 | L17: =J17+M17 -> 114.11108 | M17: =M106 -> 6.2403762 | N17: =L17+O17 -> 120.86925 | O17: =O106 -> 6.7581669 | P17: =N17+Q17 -> 126.70663 | Q17: =Q106 -> 5.8373749
B18: 四、净利润 | C18: =350.8461+0.06 -> 350.9061 | D18: 349.12253 | E18: =D18-C18 -> -1.783571 | F18: 301.05028 | G18: =F18-D18 -> -48.072252 | H18: =H10-H13-H17 -> 316.60713 | I18: =H18-F18 -> 15.556849 | J18: =J10-J13-J17 -> 331.97893 | K18: =J18-H18 -> 15.371807 | L18: =L10-L13-L17 -> 374.5163 | M18: =L18-J18 -> 42.537372 | N18: =N10-N13-N17 -> 371.68536 | O18: =N18-L18 -> -2.8309401 | P18: =P10-P13-P17 -> 329.04634 | Q18: =P18-N18 -> -42.639023
B19: 五、资本占用 | C19: 3209 | D19: 3546 | E19: =D19-C19 -> 337 | F19: 3954 | G19: =F19-D19 -> 408 | H19: =F19+I19 -> 4287.8531 | I19: =SUMIF(资本!$AG:$AG,"对公",资本!G:G)*0.11 -> 333.8531 | J19: =H19+K19 -> 4582.3015 | K19: =SUMIF(资本!$AG:$AG,"对公",资本!K:K)*0.11 -> 294.44836 | L19: =J19+M19 -> 4861.8967 | M19: =SUMIF(资本!$AG:$AG,"对公",资本!O:O)*0.11 -> 279.59527 | N19: =L19+O19 -> 5104.5699 | O19: =SUMIF(资本!$AG:$AG,"对公",资本!S:S)*0.11 -> 242.6732 | P19: =N19+Q19 -> 5342.8198 | Q19: =SUMIF(资本!$AG:$AG,"对公",资本!W:W)*0.11 -> 238.24988
B20: 六、成本收入比 | C20: 0.2353 | D20: 0.2373 | E20: =D20-C20 -> 0.002 | F20: 0.2227 | G20: =F20-D20 -> -0.0146 | H20: =H15/H10 -> 0.22308033 | I20: =H20-F20 -> 0.00038032944 | J20: =J15/J10 -> 0.2209885 | K20: =J20-H20 -> -0.0020918265 | L20: =L15/L10 -> 0.21612408 | M20: =L20-J20 -> -0.004864423 | N20: =N15/N10 -> 0.20993263 | O20: =N20-L20 -> -0.0061914478 | P20: =P15/P10 -> 0.21071844 | Q20: =P20-N20 -> 0.00078580841
B21: 七、风险成本率 | C21: =C16/C10 -> 0.13288955 | D21: =D16/D10 -> 0.13673961 | E21: =D21-C21 -> 0.003850067 | F21: =F16/F10 -> 0.25509733 | G21: =F21-D21 -> 0.11835772 | H21: =H16/H10 -> 0.25347605 | I21: =H21-F21 -> -0.0016212809 | J21: =J16/J10 -> 0.25221284 | K21: =J21-H21 -> -0.0012632092 | L21: =L16/L10 -> 0.23641828 | M21: =L21-J21 -> -0.015794559 | N21: =N16/N10 -> 0.27719999 | O21: =N21-L21 -> 0.040781707 | P21: =P16/P10 -> 0.32926378 | Q21: =P21-N21 -> 0.05206379
B22: 八、税务成本率 | C22: =(C17+C14)/C10 -> 0.16692868 | D22: =(D17+D14)/D10 -> 0.16584786 | E22: =D22-C22 -> -0.0010808172 | F22: =(F17+F14)/F10 -> 0.13921459 | G22: =F22-D22 -> -0.026633272 | H22: =(H17+H14)/H10 -> 0.13717828 | I22: =H22-F22 -> -0.0020363139 | J22: =(J17+J14)/J10 -> 0.13689505 | K22: =J22-H22 -> -0.00028322095 | L22: =(L17+L14)/L10 -> 0.13517959 | M22: =L22-J22 -> -0.0017154684 | N22: =(N17+N14)/N10 -> 0.13256118 | O22: =N22-L22 -> -0.0026184089 | P22: =(P17+P14)/P10 -> 0.13410448 | Q22: =P22-N22 -> 0.0015432986
B23: 九、营收/风险资产 | C23: =C10/C19*0.11 -> 0.025878625 | D23: =D10/D19*0.11 -> 0.023542177 | E23: =D23-C23 -> -0.002336448 | F23: =F10/F19*0.11 -> 0.021869899 | G23: =F23-D23 -> -0.0016722775 | H23: =H10/H19*0.11 -> 0.021027504 | I23: =H23-F23 -> -0.00084239502 | J23: =J10/J19*0.11 -> 0.020439125 | K23: =J23-H23 -> -0.00058837881 | L23: =L10/L19*0.11 -> 0.020552633 | M23: =L23-J23 -> 0.00011350784 | N23: =N10/N19*0.11 -> 0.021060835 | O23: =N23-L23 -> 0.00050820166 | P23: =P10/P19*0.11 -> 0.020786297 | Q23: =P23-N23 -> -0.00027453743
B24: 十、风险资本回报率 | C24: =C18/C19 -> 0.10935061 | D24: =D18/D19 -> 0.09845531 | E24: =D24-C24 -> -0.010895298 | F24: =F18/F19 -> 0.076138158 | G24: =F24-D24 -> -0.022317152 | H24: =H18/H19 -> 0.073838147 | I24: =H24-F24 -> -0.0023000115 | J24: =J18/J19 -> 0.072448078 | K24: =J24-H24 -> -0.0013900687 | L24: =L18/L19 -> 0.077030905 | M24: =L24-J24 -> 0.0045828271 | N24: =N18/N19 -> 0.072814237 | O24: =N24-L24 -> -0.0042166679 | P24: =P18/P19 -> 0.061586644 | Q24: =P24-N24 -> -0.011227593
A25: 零售板块 | B25: 零售板块占全行营收比 | C25: =C27/'2026-2030年盈利测算表'!$H$12 -> 0.40165903 | D25: =D27/'2026-2030年盈利测算表'!$J$12 -> 0.36305681 | E25: =D25-C25 -> -0.038602219 | F25: =F27/'2026-2030年盈利测算表'!$L$12 -> 0.34547735 | G25: =F25-D25 -> -0.017579463 | H25: =H27/S$4 -> 0.33564503 | I25: =H25-F25 -> -0.0098323239 | J25: =J27/U$4 -> 0.32719425 | K25: =J25-H25 -> -0.0084507792 | L25: =L27/W$4 -> 0.3231747 | M25: =L25-J25 -> -0.0040195476 | N25: =N27/Y$4 -> 0.3252341 | O25: =N25-L25 -> 0.0020594047 | P25: =P27/AA$4 -> 0.32218231 | Q25: =P25-N25 -> -0.0030517991
B26: 零售板块占全行净利润比 | C26: =C35/'2026-2030年盈利测算表'!$H$11 -> 0.043708258 | D26: =D35/'2026-2030年盈利测算表'!$J$11 -> 0.0024893781 | E26: =D26-C26 -> -0.04121888 | F26: =F35/'2026-2030年盈利测算表'!$L$11 -> -0.023901804 | G26: =F26-D26 -> -0.026391182 | H26: =H35/S$7 -> -0.035034426 | I26: =H26-F26 -> -0.011132622 | J26: =J35/U$7 -> -0.039557975 | K26: =J26-H26 -> -0.004523549 | L26: =L35/W$7 -> -0.040667202 | M26: =L26-J26 -> -0.0011092274 | N26: =N35/Y$7 -> 0.039372332 | O26: =N26-L26 -> 0.080039534 | P26: =P35/AA$7 -> 0.10377724 | Q26: =P26-N26 -> 0.064404908
B27: 一、营业净收入 | C27: 767.97207 | D27: 727.2028 | E27: =D27-C27 -> -40.769272 | F27: 670.79264 | G27: =F27-D27 -> -56.410154 | H27: =H28+H29 -> 680.63369 | I27: =I28+I29 -> 9.8410499 | J27: =J28+J29 -> 683.84144 | K27: =K28+K29 -> 3.207747 | L27: =L28+L29 -> 705.89273 | M27: =M28+M29 -> 22.05129 | N27: =N28+N29 -> 743.58009 | O27: =O28+O29 -> 37.687362 | ... Q27: =Q28+Q29 -> 21.420842
B28: （一）利息净收入 | C28: 538.44495 | D28: 520.03316 | E28: =D28-C28 -> -18.411786 | F28: 478.69 | G28: =F28-D28 -> -41.34316 | H28: =F28+I28 -> 480.94973 | I28: =H64-F64 -> 2.2597287 | J28: =H28+K28 -> 477.26932 | K28: =J64-H64 -> -3.6804068 | L28: =J28+M28 -> 489.66674 | M28: =L64-J64 -> 12.397415 | N28: =L28+O28 -> 512.61919 | O28: =N64-L64 -> 22.952455 | P28: =N28+Q28 -> 519.45248 | Q28: =P64-N64 -> 6.8332843
B29: （二）非息净收入 | C29: 229.52712 | D29: 207.16964 | E29: =D29-C29 -> -22.357487 | F29: 192.10264 | G29: =F29-D29 -> -15.066993 | H29: =F29+I29 -> 199.68396 | I29: =中收测算表!$J9-中收测算表!$J8+中收测算表!$N9-中收测算表!$N8 -> 7.5813212 | J29: =H29+K29 -> 206.57212 | K29: =中收测算表!$J10-中收测算表!$J9+中收测算表!$N10-中收测算表!$N9 -> 6.8881538 | L29: =J29+M29 -> 216.22599 | M29: =中收测算表!$J11-中收测算表!$J10+中收测算表!$N11-中收测算表!$N10 -> 9.6538752 | N29: =L29+O29 -> 230.9609 | O29: =中收测算表!$J12-中收测算表!$J11+中收测算表!$N12-中收测算表!$N11 -> 14.734907 | P29: =N29+Q29 -> 245.54846 | Q29: =中收测算表!$J13-中收测算表!$J12+中收测算表!$N13-中收测算表!$N12 -> 14.587558
B30: 二、营业支出 | C30: 731.22019 | D30: 724.6131 | E30: =D30-C30 -> -6.60709 | F30: 685.65282 | G30: =F30-D30 -> -38.960276 | H30: =H32+H33+H31 -> 704.00466 | I30: =H30-F30 -> 18.351833 | J30: =J32+J33+J31 -> 711.60164 | K30: =J30-H30 -> 7.596979 | L30: =L32+L33+L31 -> 736.25551 | M30: =L30-J30 -> 24.653875 | N30: =N32+N33+N31 -> 710.99042 | O30: =N30-L30 -> -25.265093 | P30: =P32+P33+P31 -> 675.57798 | Q30: =P30-N30 -> -35.412442
B31: （一）税金及附加 | C31: 9.39503 | D31: 8.992212 | E31: =D31-C31 -> -0.402818 | F31: 7.984384 | G31: =F31-D31 -> -1.007828 | H31: =F31+I31 -> 7.984384 | I31: =I107 -> 0 | J31: =H31+K31 -> 7.984384 | K31: =K107 -> 0 | L31: =J31+M31 -> 7.984384 | M31: =M107 -> 0 | N31: =L31+O31 -> 7.984384 | O31: =O107 -> 0 | P31: =N31+Q31 -> 7.984384 | Q31: =Q107 -> 0
B32: （二）营业费用 | C32: 268.45312 | D32: 267.89367 | E32: =D32-C32 -> -0.55945 | F32: 250.59667 | G32: =F32-D32 -> -17.297 | H32: =F32+I32 -> 261.72175 | I32: =I94 -> 11.125078 | J32: =H32+K32 -> 269.31873 | K32: =K94 -> 7.596979 | L32: =J32+M32 -> 278.9726 | M32: =M88 -> 9.6538752 | N32: =L32+O32 -> 293.70751 | O32: =O88 -> 14.734907 | P32: =N32+Q32 -> 308.29507 | Q32: =Q88 -> 14.587558
B33: （三）资产减值损失 | C33: 453.37204 | D33: 447.72722 | E33: =D33-C33 -> -5.644823 | F33: 427.07177 | G33: =F33-D33 -> -20.655448 | H33: =F33+I33 -> 434.29852 | I33: =I100 -> 7.2267546 | J33: =H33+K33 -> 434.29852 | K33: =K100 -> 0 | L33: =J33+M33 -> 449.29852 | M33: =M100 -> 15 | N33: =L33+O33 -> 409.29852 | O33: =O100 -> -40 | P33: =N33+Q33 -> 359.29852 | Q33: =Q100 -> -50
B34: 三、所得税费用 | C34: 9.375067 | D34: 0.91358 | E34: =D34-C34 -> -8.461487 | F34: 0.658195 | G34: =F34-D34 -> -0.255385 | H34: =F34+I31 -> 0.658195 | I34: 0 | J34: =H34+K34 -> 0.658195 | K34: 0 | L34: =J34+M34 -> 0.658195 | M34: 0 | N34: =L34+O34 -> 0.658195 | O34: 0 | P34: =N34+Q34 -> 0.658195 | Q34: 0
B35: 四、净利润 | C35: 27.383661 | D35: =1.60225+0.05 -> 1.65225 | E35: =D35-C35 -> -25.731411 | F35: =-15.414706-0.05 -> -15.464706 | G35: =F35-D35 -> -17.116956 | H35: =H27-H30-H34 -> -24.029159 | I35: =H35-F35 -> -8.564453 | J35: =J27-J30-J34 -> -28.418391 | K35: =J35-H35 -> -4.3892321 | L35: =L27-L30-L34 -> -31.020976 | M35: =L35-J35 -> -2.6025854 | N35: =N27-N30-N34 -> 31.931478 | O35: =N35-L35 -> 62.952455 | P35: =P27-P30-P34 -> 88.764763 | Q35: =P35-N35 -> 56.833284
B36: 五、资本占用 | C36: 1668 | D36: 1433.45 | E36: =D36-C36 -> -234.55 | F36: 1435 | G36: =F36-D36 -> 1.55 | H36: =F36+I36 -> 1412.3045 | I36: =SUMIF(资本!$AG:$AG,"零售",资本!G:G)*0.11 -> -22.6955 | J36: =H36+K36 -> 1403.6448 | K36: =SUMIF(资本!$AG:$AG,"零售",资本!K:K)*0.11 -> -8.659651 | L36: =J36+M36 -> 1406.8732 | M36: =SUMIF(资本!$AG:$AG,"零售",资本!O:O)*0.11 -> 3.2283343 | N36: =L36+O36 -> 1410.1205 | O36: =SUMIF(资本!$AG:$AG,"零售",资本!S:S)*0.11 -> 3.2473219 | P36: =N36+Q36 -> 1413.3866 | Q36: =SUMIF(资本!$AG:$AG,"零售",资本!W:W)*0.11 -> 3.2660576
B37: 六、成本收入比 | C37: 0.3496 | D37: 0.3684 | E37: =D37-C37 -> 0.0188 | F37: 0.3736 | G37: =F37-D37 -> 0.0052 | H37: =H32/H27 -> 0.38452659 | I37: =H37-F37 -> 0.010926586 | J37: =J32/J27 -> 0.39383213 | K37: =J37-H37 -> 0.0093055417 | L37: =L32/L27 -> 0.39520538 | M37: =L37-J37 -> 0.0013732524 | N37: =N32/N27 -> 0.39499109 | O37: =N37-L37 -> -0.00021428916 | P37: =P32/P27 -> 0.4029996 | Q37: =P37-N37 -> 0.008008508
B38: 七、风险成本率 | C38: =C33/C27 -> 0.59034965 | D38: =D33/D27 -> 0.61568412 | E38: =D38-C38 -> 0.025334477 | F38: =F33/F27 -> 0.63666734 | G38: =F38-D38 -> 0.020983218 | H38: =H33/H27 -> 0.63807967 | I38: =H38-F38 -> 0.0014123302 | J38: =J33/J27 -> 0.63508658 | K38: =J38-H38 -> -0.0029930887 | L38: =L33/L27 -> 0.63649688 | M38: =L38-J38 -> 0.0014103017 | N38: =N33/N27 -> 0.55044309 | O38: =N38-L38 -> -0.086053794 | P38: =P33/P27 -> 0.4696707 | Q38: =P38-N38 -> -0.080772391
B39: 八、税务成本率 | C39: =(C34+C31)/C27 -> 0.024441119 | D39: =(D34+D31)/D27 -> 0.013621774 | E39: =D39-C39 -> -0.010819346 | F39: =(F34+F31)/F27 -> 0.012884129 | G39: =F39-D39 -> -0.00073764471 | H39: =(H34+H31)/H27 -> 0.012697842 | I39: =H39-F39 -> -0.00018628722 | J39: =(J34+J31)/J27 -> 0.012638279 | K39: =J39-H39 -> -5.9562731e-05 | L39: =(L34+L31)/L27 -> 0.012243474 | M39: =L39-J39 -> -0.00039480553 | N39: =(N34+N31)/N27 -> 0.01162293 | O39: =N39-L39 -> -0.00062054407 | P39: =(P34+P31)/P27 -> 0.011297475 | Q39: =P39-N39 -> -0.00032545442
B40: 九、营收/风险资产 | C40: =C27/C36*0.11 -> 0.05064564 | D40: =D27/D36*0.11 -> 0.055804045 | E40: =D40-C40 -> 0.0051584045 | F40: =F27/F36*0.11 -> 0.051419645 | G40: =F40-D40 -> -0.0043843994 | H40: =H27/H36*0.11 -> 0.053012439 | I40: =H40-F40 -> 0.0015927939 | J40: =J27/J36*0.11 -> 0.053590877 | K40: =J40-H40 -> 0.00057843791 | L40: =L27/L36*0.11 -> 0.055192039 | M40: =L40-J40 -> 0.0016011625 | N40: =N27/N36*0.11 -> 0.058004837 | O40: =N40-L40 -> 0.0028127975 | P40: =P27/P36*0.11 -> 0.059537925 | Q40: =P40-N40 -> 0.0015330877
B41: 十、风险资本回报率 | C41: =C35/C36 -> 0.016417063 | D41: =D35/D36 -> 0.0011526387 | E41: =D41-C41 -> -0.015264424 | F41: =F35/F36 -> -0.010776799 | G41: =F41-D41 -> -0.011929437 | H41: =H35/H36 -> -0.017014149 | I41: =H41-F41 -> -0.0062373502 | J41: =J35/J36 -> -0.020246141 | K41: =J41-H41 -> -0.0032319918 | L41: =L35/L36 -> -0.02204959 | M41: =L41-J41 -> -0.0018034491 | N41: =N35/N36 -> 0.022644503 | O41: =N41-L41 -> 0.044694093 | P41: =P35/P36 -> 0.062802891 | Q41: =P41-N41 -> 0.040158388
A42: 金融市场板块 | B42: 金市板块占全行营收比 | C42: =C44/'2026-2030年盈利测算表'!$H$12 -> 0.16035434 | D42: =D44/'2026-2030年盈利测算表'!$J$12 -> 0.17339138 | E42: =D42-C42 -> 0.013037035 | F42: =F44/'2026-2030年盈利测算表'!$L$12 -> 0.17185929 | G42: =F42-D42 -> -0.0015320868 | H42: =H44/S$4 -> 0.18034869 | I42: =H42-F42 -> 0.008489396 | J42: =J44/U$4 -> 0.17697856 | K42: =J42-H42 -> -0.0033701283 | L42: =L44/W$4 -> 0.17769957 | M42: =L42-J42 -> 0.00072100874 | N42: =N44/Y$4 -> 0.18190938 | O42: =N42-L42 -> 0.0042098173 | P42: =P44/AA$4 -> 0.18141263 | Q42: =P42-N42 -> -0.00049675328 | U42: =333+1-20-9 -> 305
B43: 金市板块占全行净利润比 | C43: =C52/'2026-2030年盈利测算表'!$H$11 -> 0.34013153 | D43: =D52/'2026-2030年盈利测算表'!$J$11 -> 0.37205495 | E43: =D43-C43 -> 0.031923413 | F43: =F52/'2026-2030年盈利测算表'!$L$11 -> 0.49823822 | G43: =F43-D43 -> 0.12618328 | H43: =H52/S$7 -> 0.51442839 | I43: =H43-F43 -> 0.016190163 | J43: =J52/U$7 -> 0.49610056 | K43: =J43-H43 -> -0.018327826 | L43: =L52/W$7 -> 0.48992892 | M43: =L43-J43 -> -0.0061716398 | N43: =N52/Y$7 -> 0.49378843 | O43: =N43-L43 -> 0.0038595132 | P43: =P52/AA$7 -> 0.48455722 | Q43: =P43-N43 -> -0.0092312174
B44: 一、营业净收入 | C44: 306.5975 | D44: 347.30293 | E44: =D44-C44 -> 40.705426 | F44: 333.68887 | G44: =F44-D44 -> -13.614056 | H44: =H45+H46 -> 365.71789 | I44: =I45+I46 -> 32.029022 | J44: =J45+J46 -> 369.88814 | K44: =K45+K46 -> 4.1702467 | L44: =L45+L46 -> 388.13939 | M44: =M45+M46 -> 18.251253 | N44: =N45+N46 -> 415.89795 | O44: =O45+O46 -> 27.758553 | ... Q44: =Q45+Q46 -> 14.854548
B45: （一）利息净收入 | C45: 28.211917 | D45: 20.717073 | E45: =D45-C45 -> -7.494844 | F45: 13.62433 | G45: =F45-D45 -> -7.092743 | H45: =F45+I45 -> 10.044685 | I45: =H65-F65 -> -3.5796447 | J45: =H45+K45 -> 19.799873 | K45: =J65-H65 -> 9.7551877 | L45: =J45+M45 -> 19.896817 | M45: =L65-J65 -> 0.096943729 | N45: =L45+O45 -> 26.124817 | O45: =N65-L65 -> 6.2279998 | P45: =N45+Q45 -> 14.248839 | Q45: =P65-N65 -> -11.875978
B46: （二）非息净收入 | C46: 278.38558 | D46: 326.58585 | E46: =D46-C46 -> 48.20027 | F46: 320.06454 | G46: =F46-D46 -> -6.521313 | H46: =F46+I46 -> 355.67321 | I46: =中收测算表!$Q9-中收测算表!$Q8 -> 35.608666 | J46: =H46+K46 -> 350.08827 | K46: =中收测算表!$Q10-中收测算表!$Q9 -> -5.584941 | L46: =J46+M46 -> 368.24258 | M46: =中收测算表!$Q11-中收测算表!$Q10 -> 18.154309 | N46: =L46+O46 -> 389.77313 | O46: =中收测算表!$Q12-中收测算表!$Q11 -> 21.530553 | P46: =N46+Q46 -> 416.50366 | Q46: =中收测算表!$Q13-中收测算表!$Q12 -> 26.730525
B47: 二、营业支出 | C47: 22.416177 | D47: 18.02244 | E47: =D47-C47 -> -4.393737 | F47: 19.819708 | G47: =F47-D47 -> 1.797268 | H47: =H49+H50+H48 -> 21.885465 | I47: =H47-F47 -> 2.0657566 | J47: =J49+J50+J48 -> 22.490224 | K47: =J47-H47 -> 0.60475939 | L47: =L49+L50+L48 -> 23.421194 | M47: =L47-J47 -> 0.93096961 | N47: =N49+N50+N48 -> 24.429037 | O47: =N47-L47 -> 1.0078434 | P47: =P49+P50+P48 -> 25.291609 | Q47: =P47-N47 -> 0.86257233
B48: （一）税金及附加 | C48: 0.98707 | D48: 0.490602 | E48: =D48-C48 -> -0.496468 | F48: 1.05104 | G48: =F48-D48 -> 0.560438 | H48: =F48+I48 -> 1.05104 | I48: 0 | J48: =H48+K48 -> 1.05104 | K48: 0 | L48: =J48+M48 -> 1.05104 | M48: 0 | N48: =L48+O48 -> 1.05104 | O48: 0 | P48: =N48+Q48 -> 1.05104 | Q48: 0
B49: （二）营业费用 | C49: 19.788181 | D49: 18.235781 | E49: =D49-C49 -> -1.5524 | F49: 19.94881 | G49: =F49-D49 -> 1.713029 | H49: =F49+I49 -> 20.834425 | I49: =I95 -> 0.88561461 | J49: =H49+K49 -> 21.439184 | K49: =K95 -> 0.60475939 | L49: =J49+M49 -> 22.370154 | M49: =M95 -> 0.93096961 | N49: =L49+O49 -> 23.377997 | O49: =O95 -> 1.0078434 | P49: =N49+Q49 -> 24.240569 | Q49: =Q95 -> 0.86257233 | S49: =F44-F47-F51 -> 322.86916
B50: （三）资产减值损失 | C50: 1.640925 | D50: -0.703943 | E50: =D50-C50 -> -2.344868 | F50: -1.180141 | G50: =F50-D50 -> -0.476198 | H50: =F50+I50 -> 0 | I50: =I101 -> 1.180141 | J50: =H50+K50 -> 0 | K50: =K101 -> 0 | L50: =J50+M50 -> 0 | M50: =M101 -> 0 | N50: =L50+O50 -> 0 | O50: =O101 -> 0 | P50: =N50+Q50 -> 0 | Q50: =Q101 -> 0 | S50: 333 | T50: 1 | U50: -20 | V50: 9 | W50: 322 | X50: =S50+T50+U50+V50 -> 323
B51: 三、所得税费用 | C51: 13 | D51: 18 | E51: =D51-C51 -> 5 | F51: -9 | G51: =F51-D51 -> -27 | H51: =F51+I51 -> -9 | I51: =I108 -> 0 | J51: =H51+K51 -> -9 | K51: =K108 -> 0 | L51: =J51+M51 -> -9 | M51: =M108 -> 0 | N51: =L51+O51 -> -9 | O51: =O108 -> 0 | P51: =N51+Q51 -> -9 | Q51: =Q108 -> 0 | S51: 282 | T51: 1 | U51: -18 | V51: -18 | W51: 247 | X51: =S51+T51+U51+V51 -> 247
B52: 四、净利润 | C52: =213.115807-0.02 -> 213.09581 | D52: 246.94031 | E52: =D52-C52 -> 33.844502 | F52: =322.465113-0.1 -> 322.36511 | G52: =F52-D52 -> 75.424804 | H52: =H44-H47-H51 -> 352.83243 | I52: =H52-F52 -> 30.467316 | J52: =J44-J47-J51 -> 356.39792 | K52: =J52-H52 -> 3.5654873 | L52: =L44-L47-L51 -> 373.7182 | M52: =L52-J52 -> 17.320284 | N52: =N44-N47-N51 -> 400.46891 | O52: =N52-L52 -> 26.750709 | P52: =P44-P47-P51 -> 414.46088 | Q52: =P52-N52 -> 13.991975 | S52: 248 | T52: -2 | U52: -20 | V52: -13 | W52: 213 | X52: =S52+T52+U52+V52 -> 213
B53: 五、资本占用 | C53: 788 | D53: 1141 | E53: =D53-C53 -> 353 | F53: 1264 | G53: =F53-D53 -> 123 | H53: =F53+I53 -> 1388.0929 | I53: =SUMIF(资本!$AG:$AG,"金市",资本!G:G)*0.11 -> 124.0929 | J53: =H53+K53 -> 1477.7587 | K53: =SUMIF(资本!$AG:$AG,"金市",资本!K:K)*0.11 -> 89.665797 | L53: =J53+M53 -> 1571.1294 | M53: =SUMIF(资本!$AG:$AG,"金市",资本!O:O)*0.11 -> 93.370701 | N53: =L53+O53 -> 1668.453 | O53: =SUMIF(资本!$AG:$AG,"金市",资本!S:S)*0.11 -> 97.323625 | P53: =N53+Q53 -> 1773.829 | Q53: =SUMIF(资本!$AG:$AG,"金市",资本!W:W)*0.11 -> 105.37598
B54: 六、成本收入比 | C54: 0.0645 | D54: 0.0525 | E54: =D54-C54 -> -0.012 | F54: 0.0598 | G54: =F54-D54 -> 0.0073 | H54: =H49/H44 -> 0.056968568 | I54: =H54-F54 -> -0.0028314322 | J54: =J49/J44 -> 0.057961264 | K54: =J54-H54 -> 0.00099269581 | L54: =L49/L44 -> 0.057634329 | M54: =L54-J54 -> -0.00032693431 | N54: =N49/N44 -> 0.056210898 | O54: =N54-L54 -> -0.0014234313 | P54: =P49/P44 -> 0.056274937 | Q54: =P54-N54 -> 6.4038764e-05
B55: 七、风险成本率 | C55: =C50/C44 -> 0.0053520495 | D55: =D50/D44 -> -0.0020268847 | E55: =D55-C55 -> -0.0073789342 | F55: =F50/F44 -> -0.0035366508 | G55: =F55-D55 -> -0.001509766 | H55: =H50/H44 -> 0 | I55: =H55-F55 -> 0.0035366508 | J55: =J50/J44 -> 0 | K55: =J55-H55 -> 0 | L55: =L50/L44 -> 0 | M55: =L55-J55 -> 0 | N55: =N50/N44 -> 0 | O55: =N55-L55 -> 0 | P55: =P50/P44 -> 0 | Q55: =P55-N55 -> 0
B56: 八、税务成本率 | C56: =(C51+C48)/C44 -> 0.0456203 | D56: =(D51+D48)/D44 -> 0.053240559 | E56: =D56-C56 -> 0.007620259 | F56: =(F51+F48)/F44 -> -0.023821472 | G56: =F56-D56 -> -0.077062031 | H56: =(H51+H48)/H44 -> -0.021735223 | I56: =H56-F56 -> 0.0020862486 | J56: =(J51+J48)/J44 -> -0.021490173 | K56: =J56-H56 -> 0.00024505042 | L56: =(L51+L48)/L44 -> -0.020479653 | M56: =L56-J56 -> 0.0010105199 | N56: =(N51+N48)/N44 -> -0.019112766 | O56: =N56-L56 -> 0.0013668871 | P56: =(P51+P48)/P44 -> -0.01845366 | Q56: =P56-N56 -> 0.00065910586
B57: 九、营收/风险资产 | C57: =C44/C53*0.11 -> 0.042799144 | D57: =D44/D53*0.11 -> 0.033482316 | E57: =D57-C57 -> -0.0093168281 | F57: =F44/F53*0.11 -> 0.02903938 | G57: =F57-D57 -> -0.0044429359 | H57: =H44/H53*0.11 -> 0.028981467 | I57: =H57-F57 -> -5.7912903e-05 | J57: =J44/J53*0.11 -> 0.027533382 | K57: =J57-H57 -> -0.0014480843 | L57: =L44/L53*0.11 -> 0.027174931 | M57: =L57-J57 -> -0.0003584513 | N57: =N44/N53*0.11 -> 0.027419875 | O57: =N57-L57 -> 0.00024494426 | P57: =P44/P53*0.11 -> 0.026712143 | Q57: =P57-N57 -> -0.00070773218
B58: 十、风险资本回报率 | C58: =C52/C53 -> 0.27042615 | D58: =D52/D53 -> 0.21642446 | E58: =D58-C58 -> -0.054001691 | F58: =F52/F53 -> 0.25503569 | G58: =F58-D58 -> 0.038611231 | H58: =H52/H53 -> 0.25418503 | I58: =H58-F58 -> -0.00085066546 | J58: =J52/J53 -> 0.24117464 | K58: =J58-H58 -> -0.013010389 | L58: =L52/L53 -> 0.23786596 | M58: =L58-J58 -> -0.0033086781 | N58: =N52/N53 -> 0.24002408 | O58: =N58-L58 -> 0.0021581261 | P58: =P52/P53 -> 0.23365324 | Q58: =P58-N58 -> -0.0063708489
C60: =C58 -> 0.27042615 | D60: =D58 -> 0.21642446 | F60: =F58 -> 0.25503569 | H60: =F60 -> 0.25503569 | J60: =H60 -> 0.25503569 | L60: =J60 -> 0.25503569 | N60: =L60 -> 0.25503569 | P60: =N60 -> 0.25503569
D61: =D46 -> 326.58585 | F61: =F46 -> 320.06454 | G61: =F61-D61 -> -6.521313 | H61: =H53*H60+H51+H47-H45 -> 356.85401 | I61: =H61-F61 -> 36.789469 | J61: =J53*J60+J51+J47-J45 -> 370.57156 | K61: =J61-H61 -> 13.71755 | L61: =L53*L60+L51+L47-L45 -> 395.21845 | M61: =L61-J61 -> 24.646887 | N61: =N53*N60+N51+N47-N45 -> 414.81929 | O61: =N61-L61 -> 19.600842 | P61: =P53*P60+P51+P47-P45 -> 454.43247 | Q61: =P61-N61 -> 39.613184
A63: 对公 | B63: 利息净收入（测算） | D63: ='板块-利息（积极-原版本）'!$D$5+'板块-利息（积极-原版本）'!$F$5 -> 724.72288 | F63: ='板块-利息（积极-原版本）'!$J$5+'板块-利息（积极-原版本）'!$L$5 -> 749.85239 | H63: ='板块-利息（积极-原版本）'!$V$5 -> 779.79014 | J63: ='板块-利息（积极-原版本）'!$Z$5 -> 808.67305 | L63: ='板块-利息（积极-原版本）'!$AD$5 -> 862.50791 | N63: ='板块-利息（积极-原版本）'!$AH$5 -> 928.04319 | P63: ='板块-利息（积极-原版本）'!$AL$5 -> 956.6628
A64: 零售 | B64: 利息净收入（测算） | D64: ='板块-利息（积极-原版本）'!$D$13+'板块-利息（积极-原版本）'!$F$13 -> 531.40375 | F64: ='板块-利息（积极-原版本）'!$L$13+'板块-利息（积极-原版本）'!$J$13 -> 491.36696 | H64: ='板块-利息（积极-原版本）'!$V$13 -> 493.62669 | J64: ='板块-利息（积极-原版本）'!$Z$13 -> 489.94628 | L64: ='板块-利息（积极-原版本）'!$AD$13 -> 502.3437 | N64: ='板块-利息（积极-原版本）'!$AH$13 -> 525.29615 | P64: ='板块-利息（积极-原版本）'!$AL$13 -> 532.12944
A65: 金市 | B65: 利息净收入（测算） | D65: ='板块-利息（积极-原版本）'!$D$19+'板块-利息（积极-原版本）'!$F$19 -> 111.66315 | F65: ='板块-利息（积极-原版本）'!$L$19+'板块-利息（积极-原版本）'!$J$19 -> 114.69477 | H65: ='板块-利息（积极-原版本）'!$V$19 -> 111.11513 | J65: ='板块-利息（积极-原版本）'!$Z$19 -> 120.87032 | L65: ='板块-利息（积极-原版本）'!$AD$19 -> 120.96726 | N65: ='板块-利息（积极-原版本）'!$AH$19 -> 127.19526 | P65: ='板块-利息（积极-原版本）'!$AL$19 -> 115.31928
F67: 2025 | H67: 2026 | J67: 2027 | L67: 2028 | N67: 2029 | P67: 2030
A68: 全行 | B68: 当年计提减值占比 | F68: ='2026-2030年盈利测算表'!L26 -> 0.2737828 | H68: ='2026-2030年盈利测算表'!N26 -> 0.2687828 | I68: =H68-F68 -> -0.005 | J68: ='2026-2030年盈利测算表'!P26 -> 0.2637828 | K68: =J68-H68 -> -0.005 | L68: ='2026-2030年盈利测算表'!R26 -> 0.2587828 | M68: =L68-J68 -> -0.005 | N68: ='2026-2030年盈利测算表'!T26 -> 0.2537828 | O68: =N68-L68 -> -0.005 | P68: ='2026-2030年盈利测算表'!V26 -> 0.2487828 | Q68: =P68-N68 -> -0.005
K70: =K10+K27+K44 -> 39.15422 | M70: =M10+M27+M44 -> 97.271145 | O70: =O10+O27+O44 -> 134.37068 | Q70: =Q10+Q27+Q44 -> 68.556639
I71: =I90/I113 -> 0.01326433
A73: 全行 | B73: 营收 | F73: ='2026-2030年盈利测算表'!L12 -> 1941.64 | H73: ='2026-2030年盈利测算表'!N12 -> 2027.8379 | I73: =H73-F73 -> 86.197861 | J73: ='2026-2030年盈利测算表'!P12 -> 2090.0167 | K73: =J73-H73 -> 62.178834 | L73: ='2026-2030年盈利测算表'!R12 -> 2184.245 | M73: =L73-J73 -> 94.228327 | N73: ='2026-2030年盈利测算表'!T12 -> 2286.2919 | O73: =N73-L73 -> 102.04685 | P73: ='2026-2030年盈利测算表'!V12 -> 2374.435 | Q73: =P73-N73 -> 88.143095
B74: 对公 | F74: =F10 -> 786.12347 | H74: =H10 -> 819.66226 | I74: =H74-F74 -> 33.538796 | J74: =J10 -> 851.43849 | K74: =J74-H74 -> 31.776227 | L74: =L10 -> 908.40709 | M74: =L74-J74 -> 56.968602 | N74: =N10 -> 977.33186 | O74: =N74-L74 -> 68.924766 | P74: =P10 -> 1009.6131 | Q74: =P74-N74 -> 32.281249
B75: 零售 | F75: =F27 -> 670.79264 | H75: =H27 -> 680.63369 | I75: =H75-F75 -> 9.8410499 | J75: =J27 -> 683.84144 | K75: =J75-H75 -> 3.207747 | L75: =L27 -> 705.89273 | M75: =L75-J75 -> 22.05129 | N75: =N27 -> 743.58009 | O75: =N75-L75 -> 37.687362 | P75: =P27 -> 765.00093 | Q75: =P75-N75 -> 21.420842
B76: 金市 | F76: =F44 -> 333.68887 | H76: =H44 -> 365.71789 | I76: =H76-F76 -> 32.029022 | J76: =J44 -> 369.88814 | K76: =J76-H76 -> 4.1702467 | L76: =L44 -> 388.13939 | M76: =L76-J76 -> 18.251253 | N76: =N44 -> 415.89795 | O76: =N76-L76 -> 27.758553 | P76: =P44 -> 430.75249 | Q76: =P76-N76 -> 14.854548
F77: =(F74+F75+F76)/F73 -> 0.92221266 | I77: =(I74+I75+I76)/I73 -> 0.87483456 | K77: =(K74+K75+K76)/K73 -> 0.62970335 | M77: =(M74+M75+M76)/M73 -> 1.032292 | O77: =(O74+O75+O76)/O73 -> 1.3167548 | Q77: =(Q74+Q75+Q76)/Q73 -> 0.77778797 | AA77: 公司 | AB77: 零售 | AC77: 金市 | AD77: 全行
Z78: 2025年 | AA78: -201 | AB78: -427 | AC78: 1 | AD78: 553.96 | AE78: =AB78+AA78+AC78 -> -627 | AF78: =AE78/AD78 -> -1.1318507
A79: 全行 | B79: 利息 | F79: ='2026-2030年盈利测算表'!L13 -> 1359.33 | H79: ='2026-2030年盈利测算表'!N13 -> 1398.7484 | I79: =H79-F79 -> 39.418442 | J79: ='2026-2030年盈利测算表'!P13 -> 1456.7307 | K79: =J79-H79 -> 57.982301 | L79: ='2026-2030年盈利测算表'!R13 -> 1520.0171 | M79: =L79-J79 -> 63.286398 | N79: ='2026-2030年盈利测算表'!T13 -> 1582.4091 | O79: =N79-L79 -> 62.391913 | P79: ='2026-2030年盈利测算表'!V13 -> 1625.5724 | Q79: =P79-N79 -> 43.163371 | T79: =1995-625 -> 1370 | V79: =I77 -> 0.87483456 | Z79: 2024年 | AA79: -104 | AB79: -448 | AC79: 1 | AD79: 576.5 | AE79: =AB79+AA79+AC79 -> -551 | AF79: =AE79/AD79 -> -0.95576756
B80: 对公 | F80: =F11 -> 675.2832 | H80: =H11 -> 705.22095 | I80: =H80-F80 -> 29.937757 | J80: =J11 -> 734.10386 | K80: =J80-H80 -> 28.882906 | L80: =L11 -> 787.93872 | M80: =L80-J80 -> 53.834857 | N80: =N11 -> 853.474 | O80: =N80-L80 -> 65.535284 | P80: =P11 -> 882.09361 | Q80: =P80-N80 -> 28.619609 | T80: =824-119 -> 705 | Z80: 2023年 | AA80: -100 | AB80: -453 | AC80: -2 | AD80: 592.1 | AE80: =AB80+AA80+AC80 -> -555 | AF80: =AE80/AD80 -> -0.93734167
B81: 零售 | F81: =F28 -> 478.69 | H81: =H28 -> 480.94973 | I81: =H81-F81 -> 2.2597287 | J81: =J28 -> 477.26932 | K81: =J81-H81 -> -3.6804068 | L81: =L28 -> 489.66674 | M81: =L81-J81 -> 12.397415 | N81: =N28 -> 512.61919 | O81: =N81-L81 -> 22.952455 | P81: =P28 -> 519.45248 | Q81: =P81-N81 -> 6.8332843 | T81: =683-203 -> 480 | Z81: 2022年 | AA81: -238 | AB81: -353 | AC81: 14 | AD81: 691.5 | AE81: =AB81+AA81+AC81 -> -577 | AF81: =AE81/AD81 -> -0.83441793
B82: 金市 | F82: =F45 -> 13.62433 | H82: =H45 -> 10.044685 | I82: =H82-F82 -> -3.5796447 | J82: =J45 -> 19.799873 | K82: =J82-H82 -> 9.7551877 | L82: =L45 -> 19.896817 | M82: =L82-J82 -> 0.096943729 | N82: =N45 -> 26.124817 | O82: =N82-L82 -> 6.2279998 | P82: =P45 -> 14.248839 | Q82: =P82-N82 -> -11.875978 | T82: =366-351 -> 15 | Z82: 2021年 | AA82: -279 | AB82: -300 | AC82: -9 | AD82: 741.71 | AE82: =AB82+AA82+AC82 -> -588 | AF82: =AE82/AD82 -> -0.79276267
F83: =(F80+F81+F82)/F79 -> 0.85895075 | I83: =(I80+I81+I82)/I79 -> 0.72600133 | K83: =(K80+K81+K82)/K79 -> 0.60290272 | M83: =(M80+M81+M82)/M79 -> 1.0480801 | O83: =(O80+O81+O82)/O79 -> 1.5180772 | Q83: =(Q80+Q81+Q82)/Q79 -> 0.54622507 | Z83: 2020年 | AA83: -378 | AB83: -328 | AC83: -9 | AD83: 795.36 | AE83: =AB83+AA83+AC83 -> -715 | AF83: =AE83/AD83 -> -0.89896399
F85: 2025 | H85: 2026 | J85: 2027 | L85: 2028 | N85: 2029 | P85: 2030
A86: 全行 | B86: 非息 | F86: ='2026-2030年盈利测算表'!L14 -> 582.31 | H86: ='2026-2030年盈利测算表'!N14 -> 629.08942 | I86: =H86-F86 -> 46.779419 | J86: ='2026-2030年盈利测算表'!P14 -> 633.28595 | K86: =J86-H86 -> 4.1965335 | L86: ='2026-2030年盈利测算表'!R14 -> 664.22788 | M86: =L86-J86 -> 30.941929 | N86: ='2026-2030年盈利测算表'!T14 -> 703.88282 | O86: =N86-L86 -> 39.654941 | P86: ='2026-2030年盈利测算表'!V14 -> 748.86255 | Q86: =P86-N86 -> 44.979724
B87: 对公 | F87: =F12 -> 110.84027 | H87: =H12 -> 114.44131 | I87: =H87-F87 -> 3.6010382 | J87: =J12 -> 117.33463 | K87: =J87-H87 -> 2.8933207 | L87: =L12 -> 120.46837 | M87: =L87-J87 -> 3.1337446 | N87: =N12 -> 123.85785 | O87: =N87-L87 -> 3.3894812 | P87: =P12 -> 127.5195 | Q87: =P87-N87 -> 3.6616407
B88: 零售 | F88: =F29 -> 192.10264 | H88: =H29 -> 199.68396 | I88: =H88-F88 -> 7.5813212 | J88: =J29 -> 206.57212 | K88: =J88-H88 -> 6.8881538 | L88: =L29 -> 216.22599 | M88: =L88-J88 -> 9.6538752 | N88: =N29 -> 230.9609 | O88: =N88-L88 -> 14.734907 | P88: =P29 -> 245.54846 | Q88: =P88-N88 -> 14.587558 | Z88: 2025年 | AA88: 318.88 | AB88: 310.66
B89: 金市 | F89: =F46 -> 320.06454 | H89: =H46 -> 355.67321 | I89: =H89-F89 -> 35.608666 | J89: =J46 -> 350.08827 | K89: =J89-H89 -> -5.584941 | L89: =L46 -> 368.24258 | M89: =L89-J89 -> 18.154309 | N89: =N46 -> 389.77313 | O89: =N89-L89 -> 21.530553 | P89: =P46 -> 416.50366 | Q89: =P89-N89 -> 26.730525 | Z89: 2024年 | AA89: 319.24 | AB89: 294.27
F90: =(F87+F88+F89)/F86 -> 1.0698897 | I90: =(I87+I88+I89)/I86 -> 1.0002481 | K90: =(K87+K88+K89)/K86 -> 1 | M90: =(M87+M88+M89)/M86 -> 1 | O90: =(O87+O88+O89)/O86 -> 1 | Q90: =(Q87+Q88+Q89)/Q86 -> 1 | Z90: 2023年 | AA90: 319.1 | AB90: 275.13
Z91: 2022年 | AA91: 392.47 | AB91: 216.24
B92: 费用 | F92: ='2026-2030年盈利测算表'!L202 -> 611.72 | H92: ='2026-2030年盈利测算表'!N202 -> 638.87692 | I92: =H92-F92 -> 27.156917 | J92: ='2026-2030年盈利测算表'!P202 -> 657.42155 | K92: =J92-H92 -> 18.544636 | L92: ='2026-2030年盈利测算表'!R202 -> 685.96926 | M92: =L92-J92 -> 28.547704 | N92: ='2026-2030年盈利测算表'!T202 -> 716.87426 | O92: =N92-L92 -> 30.905001 | P92: ='2026-2030年盈利测算表'!V202 -> 743.32459 | Q92: =P92-N92 -> 26.450337 | Z92: 2021年 | AA92: 453.32 | AB92: 194.19
B93: 对公 | F93: =F15 -> 175.07805 | H93: =H15 -> 182.85053 | I93: =I$92*$F$96*$F93/($F$93+$F$94+$F$95) -> 7.7724776 | J93: =J15 -> 188.15812 | K93: =K$92*$F$96*$F93/($F$93+$F$94+$F$95) -> 5.3075895 | L93: =L15 -> 196.32865 | M93: =M$92*$F$96*$F93/($F$93+$F$94+$F$95) -> 8.1705297 | N93: =N15 -> 205.17385 | O93: =O$92*$F$96*$F93/($F$93+$F$94+$F$95) -> 8.8452024 | P93: =P15 -> 212.7441 | Q93: =Q$92*$F$96*$F93/($F$93+$F$94+$F$95) -> 7.5702501 | Z93: 2020年 | AA93: 486.37 | AB93: 207.78
B94: 零售 | F94: =F32 -> 250.59667 | H94: =H32 -> 261.72175 | I94: =I$92*$F$96*$F94/($F$93+$F$94+$F$95) -> 11.125078 | J94: =J32 -> 269.31873 | K94: =K$92*$F$96*$F94/($F$93+$F$94+$F$95) -> 7.596979 | L94: =L32 -> 278.9726 | M94: =M$92*$F$96*$F94/($F$93+$F$94+$F$95) -> 11.694827 | N94: =N32 -> 293.70751 | O94: =O$92*$F$96*$F94/($F$93+$F$94+$F$95) -> 12.660515 | P94: =P32 -> 308.29507 | Q94: =Q$92*$F$96*$F94/($F$93+$F$94+$F$95) -> 10.835622
B95: 金市 | F95: =F49 -> 19.94881 | H95: =H49 -> 20.834425 | I95: =I$92*$F$96*$F95/($F$93+$F$94+$F$95) -> 0.88561461 | J95: =J49 -> 21.439184 | K95: =K$92*$F$96*$F95/($F$93+$F$94+$F$95) -> 0.60475939 | L95: =L49 -> 22.370154 | M95: =M$92*$F$96*$F95/($F$93+$F$94+$F$95) -> 0.93096961 | N95: =N49 -> 23.377997 | O95: =O$92*$F$96*$F95/($F$93+$F$94+$F$95) -> 1.0078434 | P95: =P49 -> 24.240569 | Q95: =Q$92*$F$96*$F95/($F$93+$F$94+$F$95) -> 0.86257233
F96: =SUM(F93:F95)/F92 -> 0.72847632 | I96: =I92-I93-I94-I95 -> 7.373746 | K96: =K92-K93-K94-K95 -> 5.0353078 | M96: =M92-M93-M94-M95 -> 7.7513779 | O96: =O92-O93-O94-O95 -> 8.3914396 | Q96: =Q92-Q93-Q94-Q95 -> 7.1818929
B98: 当年计提减值 | F98: ='2026-2030年盈利测算表'!L203 -> 553.96 | H98: ='2026-2030年盈利测算表'!N203 -> 568.41351 | I98: ='2026-2030年盈利测算表'!O203 -> 14.453509 | J98: ='2026-2030年盈利测算表'!P203 -> 575.39248 | K98: ='2026-2030年盈利测算表'!Q203 -> 6.9789675 | L98: ='2026-2030年盈利测算表'!R203 -> 590.4128 | M98: ='2026-2030年盈利测算表'!S203 -> 15.020324 | N98: ='2026-2030年盈利测算表'!T203 -> 606.56514 | O98: ='2026-2030年盈利测算表'!U203 -> 16.152336 | ... Q98: ='2026-2030年盈利测算表'!W203 -> 11.512647
B99: 对公 | F99: =F16 -> 200.538 | H99: =H16 -> 207.76475 | I99: =I98/2 -> 7.2267546 | J99: =J16 -> 214.74372 | K99: =K98-K100-K101 -> 6.9789675 | L99: =L16 -> 214.76404 | M99: =M98-M100-M101 -> 0.020323858 | N99: =N16 -> 270.91638 | O99: =O98-O100-O101 -> 56.152336 | P99: =P16 -> 332.42903 | Q99: =Q98-Q100-Q101 -> 61.512647 | S99: =L100+L99-L98 -> 73.649767
B100: 零售 | F100: =F33 -> 427.07177 | H100: =H33 -> 434.29852 | I100: =I98/2 -> 7.2267546 | J100: =J33 -> 434.29852 | K100: 0 | L100: =L33 -> 449.29852 | M100: 15 | N100: =N33 -> 409.29852 | O100: -40 | P100: =P33 -> 359.29852 | Q100: -50 | S100: =H100+H99-H98 -> 73.649767 | V100: =S100/4 -> 18.412442
B101: 金市 | F101: =F50 -> -1.180141 | H101: =H50 -> 0 | I101: =-F101 -> 1.180141 | J101: =J50 -> 0 | K101: 0 | L101: =L50 -> 0 | M101: 0 | N101: =N50 -> 0 | O101: 0 | P101: =P50 -> 0 | Q101: 0
F102: =(F99+F100+F101)/F98 -> 1.130821 | I102: =I98-I99-I100-I101 -> -1.180141 | K102: =K98-K99-K100-K101 -> 0 | M102: =M98-M99-M100-M101 -> 0 | O102: =O98-O99-O100-O101 -> 0 | Q102: =Q98-Q99-Q100-Q101 -> 0
F103: =F99+F100+F101-F98 -> 72.469626 | H103: =H99+H100+H101-H98 -> 73.649767 | I103: =I99+I100+I101-I98 -> 1.180141 | J103: =J99+J100+J101-J98 -> 73.649767 | K103: =K99+K100+K101-K98 -> 0 | L103: =L99+L100+L101-L98 -> 73.649767
B105: 所得税 | F105: ='2026-2030年盈利测算表'!L204 -> 128.58728 | H105: ='2026-2030年盈利测算表'!N204 -> 134.29583 | I105: ='2026-2030年盈利测算表'!O204 -> 5.7085496 | J105: ='2026-2030年盈利测算表'!P204 -> 138.41369 | K105: ='2026-2030年盈利测算表'!Q204 -> 4.1178628 | L105: ='2026-2030年盈利测算表'!R204 -> 144.65407 | M105: ='2026-2030年盈利测算表'!S204 -> 6.2403762 | N105: ='2026-2030年盈利测算表'!T204 -> 151.41223 | O105: ='2026-2030年盈利测算表'!U204 -> 6.7581669 | ... Q105: ='2026-2030年盈利测算表'!W204 -> 5.8373749
B106: 对公 | F106: =F17+F14 -> 109.43986 | H106: =H17+H14 -> 112.43986 | I106: 3 | J106: =J17+J14 -> 116.55772 | K106: =K105 -> 4.1178628 | L106: =L17+L14 -> 122.79809 | M106: =M105 -> 6.2403762 | N106: =N17+N14 -> 129.55626 | O106: =O105 -> 6.7581669 | P106: =P17+P14 -> 135.39364 | Q106: =Q105 -> 5.8373749
B107: 零售 | F107: =F34+F31 -> 8.642579 | H107: =H34+H31 -> 8.642579 | I107: 0 | J107: =J34+J31 -> 8.642579 | K107: 0 | L107: =L34+L31 -> 8.642579 | M107: 0 | N107: =N34+N31 -> 8.642579 | O107: 0 | P107: =P34+P31 -> 8.642579 | Q107: 0
B108: 金市 | F108: =F48+F51 -> -7.94896 | H108: =H48+H51 -> -7.94896 | I108: 0 | J108: =J48+J51 -> -7.94896 | K108: 0 | L108: =L48+L51 -> -7.94896 | M108: 0 | N108: =N48+N51 -> -7.94896 | O108: 0 | P108: =P48+P51 -> -7.94896 | Q108: 0
...

Sheet 板块-利息（纯账面）
Z2: ='2026-2030年盈利测算表'!O30/2 -> -7.47715e-05 | AG2: ='2026-2030年盈利测算表'!Q30/2 -> -0.00030286096 | AN2: ='2026-2030年盈利测算表'!S30/2 -> 1.7665831e-05 | AU2: ='2026-2030年盈利测算表'!U30/2 -> 0.00017192225 | BB2: ='2026-2030年盈利测算表'!W30/2 -> -0.00023502321
A3: 项目 | B3: 2024年 | J3: 2025年 | R3: 2025年 | W3: 2026年 | AD3: 2027年 | AK3: 2028年 | AR3: 2029年 | AY3: 2030年
B4: 时点 | C4: 平均余额 | D4: 利息净收入 | E4: FTP利差 | F4: 补贴 | G4: 补贴率 | H4: 内部利息收支 | I4: FTP率 | J4: 时点 | K4: 平均余额 | L4: 利息净收入 | M4: FTP利差 | N4: 补贴 | O4: 补贴率 | P4: 内部利息收支 | Q4: FTP率 | R4: 平均余额 | S4: 调整量 | T4: 调整后日均 | U4: FTP利差及补贴率 | V4: 利息净收入 | W4: 平均余额 | X4: 调整后日均 | Y4: 外部利率 | Z4: FTP利差及补贴率 | AA4: 方案1利息净收入 | AB4: 按FTP折算 | AC4: 方案2利息净收入 | AD4: 平均余额 | AE4: 调整后日均 | AF4: 外部利率 | AG4: FTP利差及补贴率 | AH4: 方案1利息净收入 | AI4: 按FTP折算 | AJ4: 方案2利息净收入 | AK4: 平均余额 | AL4: 调整后日均 | AM4: 外部利率 | AN4: FTP利差及补贴率 | AO4: 方案1利息净收入 | AP4: 按FTP折算 | AQ4: 方案2利息净收入 | AR4: 平均余额 | AS4: 调整后日均 | AT4: 外部利率 | AU4: FTP利差及补贴率 | AV4: 方案1利息净收入 | AW4: 按FTP折算 | AX4: 方案2利息净收入 | AY4: 平均余额 | AZ4: 调整后日均 | BA4: 外部利率 | BB4: FTP利差及补贴率 | BC4: 方案1利息净收入 | BD4: 按FTP折算 | BE4: 方案2利息净收入
A5: 对公条线 | D5: =D6+D7++D8+D9+D12 -> 678.33913 | F5: =SUM(F6:F12) -> 46.38375 | H5: =H6+H7++H8+H9+H12 -> 215.349 | L5: =L6+L7++L8+L9+L12 -> 697.86592 | N5: =SUM(N6:N12) -> 51.986471 | P5: =P6+P7++P8+P9+P12 -> 180.15447 | V5: =V6+V7++V8+V9+V12 -> 749.85239 | AA5: =AA6+AA7++AA8+AA9+AA12 -> 779.79014 | AC5: =AC6+AC7++AC8+AC9+AC12 -> 797.5912 | AH5: =AH6+AH7++AH8+AH9+AH12 -> 808.67305 | AJ5: =AJ6+AJ7++AJ8+AJ9+AJ12 -> 854.33272 | AO5: =AO6+AO7++AO8+AO9+AO12 -> 862.50791 | AQ5: =AQ6+AQ7++AQ8+AQ9+AQ12 -> 899.71824 | AV5: =AV6+AV7++AV8+AV9+AV12 -> 928.04319 | AX5: =AX6+AX7++AX8+AX9+AX12 -> 944.28072 | BC5: =BC6+BC7++BC8+BC9+BC12 -> 956.6628 | BE5: =BE6+BE7++BE8+BE9+BE12 -> 976.90443
A6: 1.1.对公一般贷款 | B6: =('2025对公人民币'!$C$50)/10000 -> 25889.737 | C6: =('2025对公人民币'!$E$50)/10000 -> 25660.363 | D6: =('2025对公人民币'!$G$48)/10000 -> 205.47597 | E6: =D6/C6 -> 0.0080075242 | F6: =('2025对公人民币'!$G$92+'2025对公人民币'!$G$97)/10000 -> 45.384394 | G6: =F6/C6 -> 0.0017686575 | H6: =('2025对公人民币'!$K$48)/10000 -> -794.13578 | I6: =H6/C6 -> -0.030947956 | J6: =('2025对公人民币'!$B$50)/10000 -> 29273.308 | K6: =('2025对公人民币'!$D$50)/10000 -> 28333.814 | L6: =('2025对公人民币'!$F$49)/10000 -> 232.01934 | M6: =L6/K6 -> 0.008188779 | N6: =('2025对公人民币'!$F$92+'2025对公人民币'!$F$97)/10000 -> 50.797726 | O6: =N6/K6 -> 0.0017928305 | P6: =('2025对公人民币'!$J$49)/10000 -> -725.98105 | Q6: =P6/K6 -> -0.025622426 | R6: ='2026-2030年盈利测算表'!$L$61 -> 28337.351 | S6: =K6-R6 -> -3.5375403 | T6: =R6+S6 -> 28333.814 | U6: =M6+O6 -> 0.0099816095 | V6: =U6*T6 -> 282.81707 | W6: ='2026-2030年盈利测算表'!N$61 -> 31337.351 | X6: =W6+$S6 -> 31333.814 | Y6: =息差测算表!C17 -> 0.030316633 | Z6: =U6+Z$2 -> 0.009906838 | AA6: =Z6*X6 -> 310.41902 | AB6: =Y6+$Q6+$O6 -> 0.0064870376 | AC6: =AB6*X6 -> 203.26363 | AD6: ='2026-2030年盈利测算表'!P$61 -> 34017.351 | AE6: =AD6+$S6 -> 34013.814 | AF6: =息差测算表!D17 -> 0.02988497 | AG6: =Z6+AG$2 -> 0.0096039771 | AH6: =AG6*AE6 -> 326.66789 | AI6: =AF6+$Q6+$O6 -> 0.0060553751 | AJ6: =AI6*AE6 -> 205.9664 | AK6: ='2026-2030年盈利测算表'!R$61 -> 36457.351 | AL6: =AK6+$S6 -> 36453.814 | AM6: =息差测算表!E17 -> 0.029389474 | AN6: =AG6+AN$2 -> 0.0096216429 | AO6: =AN6*AL6 -> 350.74558 | AP6: =AM6+$Q6+$O6 -> 0.0055598782 | AQ6: =AP6*AL6 -> 202.67877 | AR6: ='2026-2030年盈利测算表'!T$61 -> 38647.351 | AS6: =AR6+$S6 -> 38643.814 | AT6: =息差测算表!F17 -> 0.028923772 | AU6: =AN6+AU$2 -> 0.0097935651 | AV6: =AU6*AS6 -> 378.46071 | AW6: =AT6+$Q6+$O6 -> 0.0050941769 | AX6: =AW6*AS6 -> 196.85842 | AY6: ='2026-2030年盈利测算表'!V$61 -> 40617.351 | AZ6: =AY6+$S6 -> 40613.814 | BA6: =息差测算表!G17 -> 0.028482507 | BB6: =AU6+BB$2 -> 0.0095585419 | BC6: =BB6*AZ6 -> 388.20884 | BD6: =BA6+$Q6+$O6 -> 0.0046529121 | BE6: =BD6*AZ6 -> 188.97251
A7: 2.2.结构化融资 | B7: =('2025对公人民币'!$C$65)/10000 -> 1585.2996 | C7: =('2025对公人民币'!$E$65)/10000 -> 1623.7424 | D7: =('2025对公人民币'!$G$65)/10000 -> 21.234315 | E7: =D7/C7 -> 0.013077392 | H7: =('2025对公人民币'!$K$65)/10000 -> -52.378166 | I7: =H7/C7 -> -0.032257682 | J7: =('2025对公人民币'!$B$65)/10000 -> 1557.0979 | K7: =('2025对公人民币'!$D$65)/10000 -> 1562.0869 | L7: =('2025对公人民币'!$F$65)/10000 -> 20.08368 | M7: =L7/K7 -> 0.012856954 | P7: =('2025对公人民币'!$J$65)/10000 -> -41.868424 | Q7: =P7/K7 -> -0.026802877 | R7: ='2026-2030年盈利测算表'!$L$85 -> 2102 | S7: =K7-R7 -> -539.91306 | T7: =R7+S7 -> 1562.0869 | U7: =M7 -> 0.012856954 | V7: =U7*T7 -> 20.08368 | W7: ='2026-2030年盈利测算表'!N$85 -> 2043 | X7: =W7+$S7 -> 1503.0869 | Y7: =息差测算表!C47 -> 0.035974089 | Z7: =U7+Z$2 -> 0.012782183 | AA7: =Z7*X7 -> 19.212732 | AB7: =Y7+$Q7+$O7 -> 0.0091712116 | AC7: =AB7*X7 -> 13.785128 | AD7: ='2026-2030年盈利测算表'!P$85 -> 2043 | AE7: =AD7+$S7 -> 1503.0869 | AF7: =息差测算表!D47 -> 0.035996684 | AG7: =Z7+AG$2 -> 0.012479322 | AH7: =AG7*AE7 -> 18.757505 | AI7: =AF7+$Q7+$O7 -> 0.0091938074 | AJ7: =AI7*AE7 -> 13.819092 | AK7: ='2026-2030年盈利测算表'!R$85 -> 2043 | AL7: =AK7+$S7 -> 1503.0869 | AM7: =息差测算表!E47 -> 0.034996684 | AN7: =AG7+AN$2 -> 0.012496987 | AO7: =AN7*AL7 -> 18.784059 | AP7: =AM7+$Q7+$O7 -> 0.0081938074 | AQ7: =AP7*AL7 -> 12.316005 | AR7: ='2026-2030年盈利测算表'!T$85 -> 2043 | AS7: =AR7+$S7 -> 1503.0869 | AT7: =息差测算表!F47 -> 0.033996684 | AU7: =AN7+AU$2 -> 0.01266891 | AV7: =AU7*AS7 -> 19.042473 | AW7: =AT7+$Q7+$O7 -> 0.0071938074 | AX7: =AW7*AS7 -> 10.812918 | AY7: ='2026-2030年盈利测算表'!V$85 -> 2043 | AZ7: =AY7+$S7 -> 1503.0869 | BA7: =息差测算表!G47 -> 0.033178259 | BB7: =AU7+BB$2 -> 0.012433886 | BC7: =BB7*AZ7 -> 18.689212 | BD7: =BA7+$Q7+$O7 -> 0.0063753822 | BE7: =BD7*AZ7 -> 9.5827537
A8: 1.境内外币贷款 | B8: =('2025对公外币'!$C$49)/10000 -> 756.18197 | C8: =('2025对公外币'!$E$49)/10000 -> 717.6423 | D8: =('2025对公外币'!$G$49)/10000 -> 5.510139 | E8: =D8/C8 -> 0.0076781134 | F8: =('2025对公外币'!$G$92+'2025对公外币'!$G$97)/10000 -> 0.999356 | H8: =('2025对公外币'!$K$49)/10000 -> -33.342283 | I8: =H8/C8 -> -0.046460866 | J8: =('2025对公外币'!$B$49)/10000 -> 834.05625 | K8: =('2025对公外币'!$D$49)/10000 -> 851.44728 | L8: =('2025对公外币'!$F$49)/10000 -> 5.046905 | M8: =L8/K8 -> 0.0059274427 | N8: =('2025对公外币'!$F$92+'2025对公外币'!$F$97)/10000 -> 1.188745 | O8: =N8/K8 -> 0.0013961463 | P8: =('2025对公外币'!$J$49)/10000 -> -32.802688 | Q8: =P8/K8 -> -0.0385258 | R8: ='2026-2030年盈利测算表'!$L$101*7 -> 1008 | S8: =K8-R8 -> -156.55272 | T8: =R8+S8 -> 851.44728 | U8: =M8+O8 -> 0.007323589 | V8: =U8*T8 -> 6.23565 | W8: ='2026-2030年盈利测算表'!N$101*7 -> 1159.2 | X8: =W8+$S8 -> 1002.6473 | Y8: =息差测算表!C19 -> 0.0408 | Z8: =U8+Z$2 -> 0.0072488175 | AA8: =Z8*X8 -> 7.2680072 | AB8: =Y8+$Q8+$O8 -> 0.0036703461 | AC8: =AB8*X8 -> 3.6800625 | AD8: ='2026-2030年盈利测算表'!P$101*7 -> 1320.13 | AE8: =AD8+$S8 -> 1163.5773 | AF8: =息差测算表!D19 -> 0.0408 | AG8: =Z8+AG$2 -> 0.0069459566 | AH8: =AG8*AE8 -> 8.0821573 | AI8: =AF8+$Q8+$O8 -> 0.0036703461 | AJ8: =AI8*AE8 -> 4.2707313 | AK8: ='2026-2030年盈利测算表'!R$101*7 -> 1670.13 | AL8: =AK8+$S8 -> 1513.5773 | AM8: =息差测算表!E19 -> 0.0408 | AN8: =AG8+AN$2 -> 0.0069636224 | AO8: =AN8*AL8 -> 10.539981 | AP8: =AM8+$Q8+$O8 -> 0.0036703461 | AQ8: =AP8*AL8 -> 5.5553524 | AR8: ='2026-2030年盈利测算表'!T$101*7 -> 2020.13 | AS8: =AR8+$S8 -> 1863.5773 | AT8: =息差测算表!F19 -> 0.0408 | AU8: =AN8+AU$2 -> 0.0071355447 | AV8: =AU8*AS8 -> 13.297639 | AW8: =AT8+$Q8+$O8 -> 0.0036703461 | AX8: =AW8*AS8 -> 6.8399735 | AY8: ='2026-2030年盈利测算表'!V$101*7 -> 2370.13 | AZ8: =AY8+$S8 -> 2213.5773 | BA8: =息差测算表!G19 -> 0.0408 | BB8: =AU8+BB$2 -> 0.0069005215 | BC8: =BB8*AZ8 -> 15.274838 | BD8: =BA8+$Q8+$O8 -> 0.0036703461 | BE8: =BD8*AZ8 -> 8.1245947
A9: 1.1.对公存款 | B9: =('2025对公人民币'!$C$9)/10000 -> 37521.175 | C9: =('2025对公人民币'!$E$9)/10000 -> 36404.754 | D9: =('2025对公人民币'!$G$9)/10000 -> 424.65036 | E9: =D9/C9 -> 0.011664695 | H9: =('2025对公人民币'!$K$9)/10000 -> 1024.2581 | I9: =H9/C9 -> 0.028135285 | J9: =('2025对公人民币'!$B$9)/10000 -> 38895.76 | K9: =('2025对公人民币'!$D$9)/10000 -> 38001.257 | L9: =('2025对公人民币'!$F$9)/10000 -> 421.94727 | M9: =L9/K9 -> 0.011103508 | P9: =('2025对公人民币'!$J$9)/10000 -> 913.94741 | Q9: =P9/K9 -> 0.024050452 | R9: ='2026-2030年盈利测算表'!$L$128 -> 38055.867 | S9: =K9-R9 -> -54.609378 | T9: =R9+S9 -> 38001.257 | U9: =M9 -> 0.011103508 | V9: =U9*T9 -> 421.94727 | W9: ='2026-2030年盈利测算表'!N$128 -> 39355.867 | X9: =W9+$S9 -> 39301.257 | Y9: =息差测算表!C65 -> 0.010142374 | Z9: =AC9/X9 -> 0.013799236 | AA9: =AA10+AA11 -> 422.00382 | AB9: =$Q9-Y9+$O9 -> 0.013908078 | AC9: =AC10+AC11 -> 542.32732 | AD9: ='2026-2030年盈利测算表'!P$128 -> 41055.867 | AE9: =AD9+$S9 -> 41001.257 | AF9: =息差测算表!D65 -> 0.0098088855 | AG9: =AJ9/AE9 -> 0.014295242 | AH9: =AH10+AH11 -> 429.21722 | AI9: =$Q9-AF9+$O9 -> 0.014241567 | AJ9: =AJ10+AJ11 -> 586.12291 | AK9: ='2026-2030年盈利测算表'!R$128 -> 42955.867 | AL9: =AK9+$S9 -> 42901.257 | AM9: =息差测算表!E65 -> 0.0094970589 | AN9: =AQ9/AL9 -> 0.014599606 | AO9: =AO10+AO11 -> 451.34028 | AP9: =$Q9-AM9+$O9 -> 0.014553393 | AQ9: =AQ10+AQ11 -> 626.34147 | AR9: ='2026-2030年盈利测算表'!T$128 -> 44855.867 | AS9: =AR9+$S9 -> 44801.257 | AT9: =息差测算表!F65 -> 0.0091735269 | AU9: =AX9/AS9 -> 0.014916316 | AV9: =AV10+AV11 -> 480.44135 | AW9: =$Q9-AT9+$O9 -> 0.014876925 | AX9: =AX10+AX11 -> 668.2697 | AY9: ='2026-2030年盈利测算表'!V$128 -> 46955.867 | AZ9: =AY9+$S9 -> 46901.257 | BA9: =息差测算表!G65 -> 0.0091566068 | BB9: =BE9/AZ9 -> 0.014926078 | BC9: =BC10+BC11 -> 493.43074 | BD9: =$Q9-BA9+$O9 -> 0.014893845 | BE9: =BE10+BE11 -> 700.0518
A10: 其中：对公活期存款 | B10: =('2025对公人民币'!$C$10)/10000 -> 18987.111 | C10: =('2025对公人民币'!$E$10)/10000 -> 19160.377 | D10: =('2025对公人民币'!$G$10)/10000 -> 323.20839 | E10: =D10/C10 -> 0.016868582 | H10: =('2025对公人民币'!$K$10)/10000 -> 512.616 | I10: =H10/C10 -> 0.026753962 | J10: =('2025对公人民币'!$B$10)/10000 -> 18838.786 | K10: =('2025对公人民币'!$D$10)/10000 -> 17388.973 | L10: =('2025对公人民币'!$F$10)/10000 -> 308.49187 | M10: =L10/K10 -> 0.01774066 | P10: =('2025对公人民币'!$J$10)/10000 -> 391.29192 | Q10: =P10/K10 -> 0.022502301 | R10: ='2026-2030年盈利测算表'!$L$131 -> 17433 | S10: =K10-R10 -> -44.026546 | T10: =R10+S10 -> 17388.973 | U10: =M10 -> 0.01774066 | V10: =U10*T10 -> 308.49187 | W10: ='2026-2030年盈利测算表'!N$131 -> 17093 | X10: =W10+$S10 -> 17048.973 | Y10: =息差测算表!C67 -> 0.0025 | Z10: =U10+Z$2 -> 0.017665888 | AA10: =Z10*X10 -> 301.18526 | AB10: =$Q10-Y10+$O10 -> 0.020002301 | AC10: =AB10*X10 -> 341.01871 | AD10: ='2026-2030年盈利测算表'!P$131 -> 17943 | AE10: =AD10+$S10 -> 17898.973 | AF10: =息差测算表!D67 -> 0.0025 | AG10: =Z10+AG$2 -> 0.017363027 | AH10: =AG10*AE10 -> 310.78037 | AI10: =$Q10-AF10+$O10 -> 0.020002301 | AJ10: =AI10*AE10 -> 358.02066 | AK10: ='2026-2030年盈利测算表'!R$131 -> 18893 | AL10: =AK10+$S10 -> 18848.973 | AM10: =息差测算表!E67 -> 0.0025 | AN10: =AG10+AN$2 -> 0.017380693 | AO10: =AN10*AL10 -> 327.60823 | AP10: =$Q10-AM10+$O10 -> 0.020002301 | AQ10: =AP10*AL10 -> 377.02285 | AR10: ='2026-2030年盈利测算表'!T$131 -> 19843 | AS10: =AR10+$S10 -> 19798.973 | AT10: =息差测算表!F67 -> 0.0025 | AU10: =AN10+AU$2 -> 0.017552616 | AV10: =AU10*AS10 -> 347.52377 | AW10: =$Q10-AT10+$O10 -> 0.020002301 | AX10: =AW10*AS10 -> 396.02504 | AY10: ='2026-2030年盈利测算表'!V$131 -> 20893 | AZ10: =AY10+$S10 -> 20848.973 | BA10: =息差测算表!G67 -> 0.0025 | BB10: =AU10+BB$2 -> 0.017317592 | BC10: =BB10*AZ10 -> 361.05402 | BD10: =$Q10-BA10+$O10 -> 0.020002301 | BE10: =BD10*AZ10 -> 417.02745
A11: 其中：对公定期存款 | B11: =B9-B10 -> 18534.064 | C11: =C9-C10 -> 17244.377 | D11: =D9-D10 -> 101.44197 | E11: =D11/C11 -> 0.0058826117 | H11: =H9-H10 -> 511.64213 | I11: =H11/C11 -> 0.029670085 | J11: =J9-J10 -> 20056.974 | K11: =K9-K10 -> 20612.284 | L11: =L9-L10 -> 113.45541 | M11: =L11/K11 -> 0.0055042619 | P11: =P9-P10 -> 522.65549 | Q11: =P11/K11 -> 0.025356506 | R11: =R9-R10 -> 20622.867 | S11: =K11-R11 -> -10.582832 | T11: =R11+S11 -> 20612.284 | U11: =M11 -> 0.0055042619 | V11: =U11*T11 -> 113.45541 | W11: =W9-W10 -> 22262.867 | X11: =W11+$S11 -> 22252.284 | Y11: =(息差测算表!C64*息差测算表!C65-息差测算表!C66*息差测算表!C67)/(息差测算表!C64-息差测算表!C66) -> 0.016309856 | Z11: =U11+Z$2 -> 0.0054294904 | AA11: =Z11*X11 -> 120.81856 | AB11: =$Q11-Y11+$O11 -> 0.0090466496 | AC11: =AB11*X11 -> 201.30862 | AD11: =AD9-AD10 -> 23112.867 | AE11: =AD11+$S11 -> 23102.284 | AF11: =(息差测算表!D64*息差测算表!D65-息差测算表!D66*息差测算表!D67)/(息差测算表!D64-息差测算表!D66) -> 0.015482926 | AG11: =Z11+AG$2 -> 0.0051266294 | AH11: =AG11*AE11 -> 118.43685 | AI11: =$Q11-AF11+$O11 -> 0.0098735801 | AJ11: =AI11*AE11 -> 228.10225 | AK11: =AK9-AK10 -> 24062.867 | AL11: =AK11+$S11 -> 24052.284 | AM11: =(息差测算表!E64*息差测算表!E65-息差测算表!E66*息差测算表!E67)/(息差测算表!E64-息差测算表!E66) -> 0.014990811 | AN11: =AG11+AN$2 -> 0.0051442952 | AO11: =AN11*AL11 -> 123.73205 | AP11: =$Q11-AM11+$O11 -> 0.010365694 | AQ11: =AP11*AL11 -> 249.31862 | AR11: =AR9-AR10 -> 25012.867 | AS11: =AR11+$S11 -> 25002.284 | AT11: =(息差测算表!F64*息差测算表!F65-息差测算表!F66*息差测算表!F67)/(息差测算表!F64-息差测算表!F66) -> 0.014467714 | AU11: =AN11+AU$2 -> 0.0053162175 | AV11: =AU11*AS11 -> 132.91758 | AW11: =$Q11-AT11+$O11 -> 0.010888792 | AX11: =AW11*AS11 -> 272.24466 | AY11: =AY9-AY10 -> 26062.867 | AZ11: =AY11+$S11 -> 26052.284 | BA11: =(息差测算表!G64*息差测算表!G65-息差测算表!G66*息差测算表!G67)/(息差测算表!G64-息差测算表!G66) -> 0.0144928 | BB11: =AU11+BB$2 -> 0.0050811943 | BC11: =BB11*AZ11 -> 132.37672 | BD11: =$Q11-BA11+$O11 -> 0.010863706 | BE11: =BD11*AZ11 -> 283.02435
A12: 1.外币存款 | B12: =('2025对公外币'!$C$22)/10000 -> 1691.3803 | C12: =('2025对公外币'!$E$22)/10000 -> 1441.9937 | D12: =('2025对公外币'!$G$8)/10000 -> 21.468342 | E12: =D12/C12 -> 0.014887958 | H12: =('2025对公外币'!$K$8)/10000 -> 70.947106 | I12: =H12/C12 -> 0.049200703 | J12: =('2025对公外币'!$B$22)/10000 -> 1784.1836 | K12: =('2025对公外币'!$D$22)/10000 -> 1741.1196 | L12: =('2025对公外币'!$F$8)/10000 -> 18.768717 | M12: =L12/K12 -> 0.010779683 | P12: =('2025对公外币'!$J$8)/10000 -> 66.85921 | Q12: =P12/K12 -> 0.038400125 | R12: ='2026-2030年盈利测算表'!$L$145*7 -> 1743 | S12: =K12-R12 -> -1.880388 | T12: =R12+S12 -> 1741.1196 | U12: =M12 -> 0.010779683 | V12: =U12*T12 -> 18.768717 | W12: ='2026-2030年盈利测算表'!N$145*7 -> 1953 | X12: =W12+$S12 -> 1951.1196 | Y12: =息差测算表!C75 -> 0.0207 | Z12: =U12+Z$2 -> 0.010704911 | AA12: =Z12*X12 -> 20.886562 | AB12: =$Q12-Y12+$O12 -> 0.017700125 | AC12: =AB12*X12 -> 34.53506 | AD12: ='2026-2030年盈利测算表'!P$145*7 -> 2496.4158 | AE12: =AD12+$S12 -> 2494.5354 | AF12: =息差测算表!D75 -> 0.0207 | AG12: =Z12+AG$2 -> 0.01040205 | AH12: =AG12*AE12 -> 25.948283 | AI12: =$Q12-AF12+$O12 -> 0.017700125 | AJ12: =AI12*AE12 -> 44.153588 | AK12: ='2026-2030年盈利测算表'!R$145*7 -> 2986.4158 | AL12: =AK12+$S12 -> 2984.5354 | AM12: =息差测算表!E75 -> 0.0207 | AN12: =AG12+AN$2 -> 0.010419716 | AO12: =AN12*AL12 -> 31.098012 | AP12: =$Q12-AM12+$O12 -> 0.017700125 | AQ12: =AP12*AL12 -> 52.826649 | AR12: ='2026-2030年盈利测算表'!T$145*7 -> 3476.4158 | AS12: =AR12+$S12 -> 3474.5354 | AT12: =息差测算表!F75 -> 0.0207 | AU12: =AN12+AU$2 -> 0.010591638 | AV12: =AU12*AS12 -> 36.801023 | AW12: =$Q12-AT12+$O12 -> 0.017700125 | AX12: =AW12*AS12 -> 61.49971 | AY12: ='2026-2030年盈利测算表'!V$145*7 -> 3966.4158 | AZ12: =AY12+$S12 -> 3964.5354 | BA12: =息差测算表!G75 -> 0.0207 | BB12: =AU12+BB$2 -> 0.010356615 | BC12: =BB12*AZ12 -> 41.059168 | BD12: =$Q12-BA12+$O12 -> 0.017700125 | BE12: =BD12*AZ12 -> 70.172771
A13: 零售条线 | D13: =D14+D15+D16 -> 509.44867 | F13: =F14+F15+F16 -> 21.955088 | H13: =H14+H15+H16 -> -326.16074 | L13: =L14+L15+L16 -> 466.36133 | N13: =SUM(N14:N18) -> 25.005626 | P13: =P14+P15+P16 -> -224.88528 | V13: =V14+V15+V16 -> 491.36696 | AA13: =AA14+AA15+AA16 -> 493.62669 | AC13: =AC14+AC15+AC16 -> 488.15319 | AH13: =AH14+AH15+AH16 -> 489.94628 | AJ13: =AJ14+AJ15+AJ16 -> 501.67252 | AO13: =AO14+AO15+AO16 -> 502.3437 | AQ13: =AQ14+AQ15+AQ16 -> 518.45268 | AV13: =AV14+AV15+AV16 -> 525.29615 | AX13: =AX14+AX15+AX16 -> 540.40392 | BC13: =BC14+BC15+BC16 -> 532.12944 | BE13: =BE14+BE15+BE16 -> 565.89977
A14: 1.2.个人贷款 | B14: =('2025零售人民币'!$C$58)/10000 -> 18154.514 | C14: =('2025零售人民币'!$E$58)/10000 -> 17635.736 | D14: =('2025零售人民币'!$G$58)/10000 -> 120.22383 | E14: =D14/C14 -> 0.0068170573 | F14: =('2025零售人民币'!$G$94+'2025零售人民币'!$G$99)/10000 -> 21.955088 | G14: =F14/C14 -> 0.0012449204 | H14: =('2025零售人民币'!$K$58)/10000 -> -575.36515 | I14: =H14/C14 -> -0.032624957 | J14: =('2025零售人民币'!$B$58)/10000 -> 18409.542 | K14: =('2025零售人民币'!$D$58)/10000 -> 18261.902 | L14: =('2025零售人民币'!$F$58)/10000 -> 105.83204 | M14: =L14/K14 -> 0.0057952362 | N14: =('2025零售人民币'!$F$94+'2025零售人民币'!$F$99)/10000 -> 25.005626 | O14: =N14/K14 -> 0.0013692783 | P14: =('2025零售人民币'!$J$58)/10000 -> -494.09674 | Q14: =P14/K14 -> -0.027056149 | R14: ='2026-2030年盈利测算表'!$L$64 -> 18261.238 | S14: =K14-R14 -> 0.66401072 | T14: =R14+S14 -> 18261.902 | U14: =O14+M14 -> 0.0071645145 | V14: =U14*T14 -> 130.83766 | W14: ='2026-2030年盈利测算表'!N$64 -> 18161.238 | X14: =W14+$S14 -> 18161.902 | Y14: =息差测算表!C21 -> 0.029991477 | Z14: =U14+Z$2 -> 0.007089743 | AA14: =Z14*X14 -> 128.76322 | AB14: =Y14+$Q14+$O14 -> 0.0043046064 | AC14: =AB14*X14 -> 78.17984 | AD14: ='2026-2030年盈利测算表'!P$64 -> 18184.921 | AE14: =AD14+$S14 -> 18185.585 | AF14: =息差测算表!D21 -> 0.029885171 | AG14: =Z14+AG$2 -> 0.0067868821 | AH14: =AG14*AE14 -> 123.42342 | AI14: =AF14+$Q14+$O14 -> 0.0041983005 | AJ14: =AI14*AE14 -> 76.348549 | AK14: ='2026-2030年盈利测算表'!R$64 -> 18234.921 | AL14: =AK14+$S14 -> 18235.585 | AM14: =息差测算表!E21 -> 0.029778017 | AN14: =AG14+AN$2 -> 0.0068045479 | AO14: =AN14*AL14 -> 124.08491 | AP14: =AM14+$Q14+$O14 -> 0.0040911466 | AQ14: =AP14*AL14 -> 74.604451 | AR14: ='2026-2030年盈利测算表'!T$64 -> 18334.921 | AS14: =AR14+$S14 -> 18335.585 | AT14: =息差测算表!F21 -> 0.029669618 | AU14: =AN14+AU$2 -> 0.0069764702 | AV14: =AU14*AS14 -> 127.91766 | AW14: =AT14+$Q14+$O14 -> 0.0039827477 | AX14: =AW14*AS14 -> 73.026008 | AY14: ='2026-2030年盈利测算表'!V$64 -> 18434.921 | AZ14: =AY14+$S14 -> 18435.585 | BA14: =息差测算表!G21 -> 0.029562395 | BB14: =AU14+BB$2 -> 0.0067414469 | BC14: =BB14*AZ14 -> 124.28252 | BD14: =BA14+$Q14+$O14 -> 0.0038755249 | BE14: =BD14*AZ14 -> 71.447567
A15: 1.3.信用卡贷款 | B15: =('2025零售人民币'!$C$64)/10000 -> 4874.8621 | C15: =('2025零售人民币'!$E$64)/10000 -> 4972.7642 | D15: =('2025零售人民币'!$G$64)/10000 -> 264.80783 | E15: =D15/C15 -> 0.053251637 | H15: =('2025零售人民币'!$K$64)/10000 -> -150.29796 | I15: =H15/C15 -> -0.030224228 | J15: =('2025零售人民币'!$B$64)/10000 -> 4615.1746 | K15: =('2025零售人民币'!$D$64)/10000 -> 4564.3988 | L15: =('2025零售人民币'!$F$64)/10000 -> 235.69213 | M15: =L15/K15 -> 0.051637059 | P15: =('2025零售人民币'!$J$64)/10000 -> -113.95831 | Q15: =P15/K15 -> -0.024966774 | R15: ='2026-2030年盈利测算表'!$L$67 -> 4568.4939 | S15: =K15-R15 -> -4.0951731 | T15: =R15+S15 -> 4564.3988 | U15: =M15 -> 0.051637059 | V15: =U15*T15 -> 235.69213 | W15: ='2026-2030年盈利测算表'!N$67 -> 4482.4939 | X15: =W15+$S15 -> 4478.3988 | Y15: =息差测算表!C31 -> 0.072 | Z15: =U15+Z$2 -> 0.051562287 | AA15: =Z15*X15 -> 230.91648 | AB15: =Y15+$Q15+$O15 -> 0.047033226 | AC15: =AB15*X15 -> 210.63354 | AD15: ='2026-2030年盈利测算表'!P$67 -> 4365.1776 | AE15: =AD15+$S15 -> 4361.0824 | AF15: =息差测算表!D31 -> 0.07 | AG15: =Z15+AG$2 -> 0.051259426 | AH15: =AG15*AE15 -> 223.54658 | AI15: =AF15+$Q15+$O15 -> 0.045033226 | AJ15: =AI15*AE15 -> 196.39361 | AK15: ='2026-2030年盈利测算表'!R$67 -> 4315.1776 | AL15: =AK15+$S15 -> 4311.0824 | AM15: =息差测算表!E31 -> 0.068 | AN15: =AG15+AN$2 -> 0.051277092 | AO15: =AN15*AL15 -> 221.05977 | AP15: =AM15+$Q15+$O15 -> 0.043033226 | AQ15: =AP15*AL15 -> 185.51978 | AR15: ='2026-2030年盈利测算表'!T$67 -> 4315.1776 | AS15: =AR15+$S15 -> 4311.0824 | AT15: =息差测算表!F31 -> 0.066 | AU15: =AN15+AU$2 -> 0.051449015 | AV15: =AU15*AS15 -> 221.80094 | AW15: =AT15+$Q15+$O15 -> 0.041033226 | AX15: =AW15*AS15 -> 176.89762 | AY15: ='2026-2030年盈利测算表'!V$67 -> 4315.1776 | AZ15: =AY15+$S15 -> 4311.0824 | BA15: =息差测算表!G31 -> 0.066 | BB15: =AU15+BB$2 -> 0.051213991 | BC15: =BB15*AZ15 -> 220.78774 | BD15: =BA15+$Q15+$O15 -> 0.041033226 | BE15: =BD15*AZ15 -> 176.89762
A16: 1.2.零售存款 | B16: =('2025零售人民币'!$C$25)/10000 -> 14313.876 | C16: =('2025零售人民币'!$E$25)/10000 -> 13306.346 | D16: =('2025零售人民币'!$G$25)/10000 -> 124.41701 | E16: =D16/C16 -> 0.009350201 | H16: =('2025零售人民币'!$K$25)/10000 -> 399.50236 | I16: =H16/C16 -> 0.030023447 | J16: =('2025零售人民币'!$B$25)/10000 -> 15535.015 | K16: =('2025零售人民币'!$D$25)/10000 -> 14926.463 | L16: =('2025零售人民币'!$F$25)/10000 -> 124.83717 | M16: =L16/K16 -> 0.0083634796 | P16: =('2025零售人民币'!$J$25)/10000 -> 383.16977 | Q16: =P16/K16 -> 0.0256705 | R16: ='2026-2030年盈利测算表'!$L$134 -> 15327.216 | S16: =K16-R16 -> -400.75336 | T16: =R16+S16 -> 14926.463 | U16: =M16 -> 0.0083634796 | V16: =U16*T16 -> 124.83717 | W16: ='2026-2030年盈利测算表'!N$134 -> 16427.216 | X16: =W16+$S16 -> 16026.463 | Y16: =息差测算表!C77 -> 0.013076925 | Z16: =AC16/X16 -> 0.012438166 | AA16: =AA17+AA18 -> 133.94699 | AB16: =$Q16-Y16+$O16 -> 0.012593575 | AC16: =AC17+AC18 -> 199.33981 | AD16: ='2026-2030年盈利测算表'!P$134 -> 18027.216 | AE16: =AD16+$S16 -> 17626.463 | AF16: =息差测算表!D77 -> 0.012532755 | AG16: =AJ16/AE16 -> 0.012987879 | AH16: =AH17+AH18 -> 142.97628 | AI16: =$Q16-AF16+$O16 -> 0.013137745 | AJ16: =AJ17+AJ18 -> 228.93037 | AK16: ='2026-2030年盈利测算表'!R$134 -> 19627.216 | AL16: =AK16+$S16 -> 19226.463 | AM16: =息差测算表!E77 -> 0.012088146 | AN16: =AQ16/AL16 -> 0.013436088 | AO16: =AO17+AO18 -> 157.19902 | AP16: =$Q16-AM16+$O16 -> 0.013582354 | AQ16: =AQ17+AQ18 -> 258.32845 | AR16: ='2026-2030年盈利测算表'!T$134 -> 21327.216 | AS16: =AR16+$S16 -> 20926.463 | AT16: =息差测算表!F77 -> 0.011646119 | AU16: =AX16/AS16 -> 0.013881003 | AV16: =AV17+AV18 -> 175.57755 | AW16: =$Q16-AT16+$O16 -> 0.014024382 | AX16: =AX17+AX18 -> 290.4803 | AY16: ='2026-2030年盈利测算表'!V$134 -> 23227.216 | AZ16: =AY16+$S16 -> 22826.463 | BA16: =息差测算表!G77 -> 0.011614536 | BB16: =BE16/AZ16 -> 0.013911686 | BC16: =BC17+BC18 -> 187.05918 | BD16: =$Q16-BA16+$O16 -> 0.014055964 | BE16: =BE17+BE18 -> 317.55459
A17: 其中：零售活期存款 | B17: =('2025零售人民币'!$C$26)/10000 -> 3949.8559 | C17: =('2025零售人民币'!$E$26)/10000 -> 3447.6015 | D17: =('2025零售人民币'!$G$26)/10000 -> 85.506221 | E17: =D17/C17 -> 0.024801654 | H17: =('2025零售人民币'!$K$26)/10000 -> 91.69683 | I17: =H17/C17 -> 0.026597282 | J17: =('2025零售人民币'!$B$26)/10000 -> 4205.9755 | K17: =('2025零售人民币'!$D$26)/10000 -> 3913.2434 | L17: =('2025零售人民币'!$F$26)/10000 -> 85.47143 | M17: =L17/K17 -> 0.021841583 | P17: =('2025零售人民币'!$J$26)/10000 -> 88.235591 | Q17: =P17/K17 -> 0.022547944 | R17: ='2026-2030年盈利测算表'!$L$137 -> 4152 | S17: =K17-R17 -> -238.75662 | T17: =R17+S17 -> 3913.2434 | U17: =M17 -> 0.021841583 | V17: =U17*T17 -> 85.47143 | W17: ='2026-2030年盈利测算表'!N$137 -> 4501.0573 | X17: =W17+$S17 -> 4262.3007 | Y17: =息差测算表!C79 -> 0.0005 | Z17: =U17+Z$2 -> 0.021766811 | AA17: =Z17*X17 -> 92.776695 | AB17: =$Q17-Y17+$O17 -> 0.022047944 | AC17: =AB17*X17 -> 93.974965 | AD17: ='2026-2030年盈利测算表'!P$137 -> 4981.0573 | AE17: =AD17+$S17 -> 4742.3007 | AF17: =息差测算表!D79 -> 0.0005 | AG17: =Z17+AG$2 -> 0.021463951 | AH17: =AG17*AE17 -> 101.78851 | AI17: =$Q17-AF17+$O17 -> 0.022047944 | AJ17: =AI17*AE17 -> 104.55798 | AK17: ='2026-2030年盈利测算表'!R$137 -> 5461.0573 | AL17: =AK17+$S17 -> 5222.3007 | AM17: =息差测算表!E79 -> 0.0005 | AN17: =AG17+AN$2 -> 0.021481616 | AO17: =AN17*AL17 -> 112.18346 | AP17: =$Q17-AM17+$O17 -> 0.022047944 | AQ17: =AP17*AL17 -> 115.14099 | AR17: ='2026-2030年盈利测算表'!T$137 -> 5971.0573 | AS17: =AR17+$S17 -> 5732.3007 | AT17: =息差测算表!F79 -> 0.0005 | AU17: =AN17+AU$2 -> 0.021653539 | AV17: =AU17*AS17 -> 124.12459 | AW17: =$Q17-AT17+$O17 -> 0.022047944 | AX17: =AW17*AS17 -> 126.38544 | AY17: ='2026-2030年盈利测算表'!V$137 -> 6541.0573 | AZ17: =AY17+$S17 -> 6302.3007 | BA17: =息差测算表!G79 -> 0.0005 | BB17: =AU17+BB$2 -> 0.021418515 | BC17: =BB17*AZ17 -> 134.98592 | BD17: =$Q17-BA17+$O17 -> 0.022047944 | BE17: =BD17*AZ17 -> 138.95277
A18: 其中：零售定期存款 | B18: =B16-B17 -> 10364.02 | C18: =C16-C17 -> 9858.7442 | D18: =D16-D17 -> 38.910786 | E18: =D18/C18 -> 0.0039468299 | H18: =H16-H17 -> 307.80553 | I18: =H18/C18 -> 0.031221576 | J18: =J16-J17 -> 11329.039 | K18: =K16-K17 -> 11013.22 | L18: =L16-L17 -> 39.365739 | M18: =L18/K18 -> 0.0035744079 | P18: =P16-P17 -> 294.93418 | Q18: =P18/K18 -> 0.026780014 | R18: =R16-R17 -> 11175.216 | S18: =K18-R18 -> -161.99673 | T18: =R18+S18 -> 11013.22 | U18: =M18 -> 0.0035744079 | V18: =U18*T18 -> 39.365739 | W18: =W16-W17 -> 11926.159 | X18: =W18+$S18 -> 11764.162 | Y18: =(息差测算表!C76*息差测算表!C77-息差测算表!C78*息差测算表!$C$79)/(息差测算表!C76-息差测算表!C78) -> 0.017823588 | Z18: =U18+Z$2 -> 0.0034996364 | AA18: =Z18*X18 -> 41.17029 | AB18: =$Q18-Y18+$O18 -> 0.0089564259 | AC18: =AB18*X18 -> 105.36485 | AD18: =AD16-AD17 -> 13046.159 | AE18: =AD18+$S18 -> 12884.162 | AF18: =(息差测算表!D76*息差测算表!D77-息差测算表!D78*息差测算表!$C$79)/(息差测算表!D76-息差测算表!D78) -> 0.017126893 | AG18: =Z18+AG$2 -> 0.0031967754 | AH18: =AG18*AE18 -> 41.187773 | AI18: =$Q18-AF18+$O18 -> 0.0096531218 | AJ18: =AI18*AE18 -> 124.37239 | AK18: =AK16-AK17 -> 14166.159 | AL18: =AK18+$S18 -> 14004.162 | AM18: =(息差测算表!E76*息差测算表!E77-息差测算表!E78*息差测算表!$C$79)/(息差测算表!E76-息差测算表!E78) -> 0.016555379 | AN18: =AG18+AN$2 -> 0.0032144412 | AO18: =AN18*AL18 -> 45.015557 | AP18: =$Q18-AM18+$O18 -> 0.010224636 | AQ18: =AP18*AL18 -> 143.18746 | AR18: =AR16-AR17 -> 15356.159 | AS18: =AR18+$S18 -> 15194.162 | AT18: =(息差测算表!F76*息差测算表!F77-息差测算表!F78*息差测算表!$C$79)/(息差测算表!F76-息差测算表!F78) -> 0.015980152 | AU18: =AN18+AU$2 -> 0.0033863635 | AV18: =AU18*AS18 -> 51.452957 | AW18: =$Q18-AT18+$O18 -> 0.010799862 | AX18: =AW18*AS18 -> 164.09486 | AY18: =AY16-AY17 -> 16686.159 | AZ18: =AY18+$S18 -> 16524.162 | BA18: =(息差测算表!G76*息差测算表!G77-息差测算表!G78*息差测算表!$C$79)/(息差测算表!G76-息差测算表!G78) -> 0.01597149 | BB18: =AU18+BB$2 -> 0.0031513403 | BC18: =BB18*AZ18 -> 52.073259 | BD18: =$Q18-BA18+$O18 -> 0.010808525 | BE18: =BD18*AZ18 -> 178.60182
A19: 金市条线 | D19: =SUM(D20:D27) -> 79.244517 | F19: =SUM(F20:F27) -> 32.418629 | H19: =SUM(H20:H27) -> -11.334408 | L19: =SUM(L20:L27) -> 114.69477 | P19: =SUM(P20:P27) -> -55.322085 | V19: =SUM(V20:V27) -> 115.43247 | AA19: =SUM(AA20:AA27) -> 117.35294 | AC19: =SUM(AC20:AC27) -> 105.9657 | AH19: =SUM(AH20:AH27) -> 126.40791 | AJ19: =SUM(AJ20:AJ27) -> 115.30563 | AO19: =SUM(AO20:AO27) -> 126.5457 | AQ19: =SUM(AQ20:AQ27) -> 109.83103 | AV19: =SUM(AV20:AV27) -> 133.17118 | AX19: =SUM(AX20:AX27) -> 101.431 | BC19: =SUM(BC20:BC27) -> 120.75183 | BE19: =SUM(BE20:BE27) -> 88.757376
A20: 1.4.票据贴现 | B20: =('2025金市人民币'!$C$57)/10000 -> 4476.6428 | C20: =('2025金市人民币'!$E$57)/10000 -> 3959.448 | D20: =('2025金市人民币'!$G$57)/10000 -> 54.867785 | E20: =D20/C20 -> 0.013857433 | F20: =('2025金市人民币'!$G$93+'2025金市人民币'!$G$98)/10000 -> 32.418629 | G20: =F20/C20 -> 0.0081876638 | H20: =('2025金市人民币'!$K$57)/10000 -> 0.033082 | I20: =H20/C20 -> 8.3552051e-06 | J20: =('2025金市人民币'!$B$57)/10000 -> 2004.0633 | K20: =('2025金市人民币'!$D$57)/10000 -> 2618.7728 | L20: =('2025金市人民币'!$F$57)/10000 -> 4.810082 | M20: =L20/K20 -> 0.0018367695 | P20: =('2025金市人民币'!$J$57)/10000 -> -23.896851 | Q20: =P20/K20 -> -0.0091252099 | R20: ='2026-2030年盈利测算表'!$L$70 -> 2620.9618 | S20: =K20-R20 -> -2.1890577 | T20: =R20+S20 -> 2618.7728 | U20: =M20 -> 0.0018367695 | V20: =U20*T20 -> 4.810082 | W20: ='2026-2030年盈利测算表'!N$70 -> 1567.9618 | X20: =W20+$S20 -> 1565.7728 | Y20: =息差测算表!C41 -> 0.014897166 | Z20: =U20+Z$2 -> 0.001761998 | AA20: =Z20*X20 -> 2.7588885 | AB20: =$U20 -> 0.0018367695 | AC20: =AB20*X20 -> 2.8759637 | AD20: ='2026-2030年盈利测算表'!P$70 -> 1467.9618 | AE20: =AD20+$S20 -> 1465.7728 | AF20: =息差测算表!D41 -> 0.014506391 | AG20: =Z20+AG$2 -> 0.0014591371 | AH20: =AG20*AE20 -> 2.1387634 | AI20: =$U20 -> 0.0018367695 | AJ20: =AI20*AE20 -> 2.6922867 | AK20: ='2026-2030年盈利测算表'!R$70 -> 1467.9618 | AL20: =AK20+$S20 -> 1465.7728 | AM20: =息差测算表!E41 -> 0.014522166 | AN20: =AG20+AN$2 -> 0.0014768029 | AO20: =AN20*AL20 -> 2.1646575 | AP20: =$U20 -> 0.0018367695 | AQ20: =AP20*AL20 -> 2.6922867 | AR20: ='2026-2030年盈利测算表'!T$70 -> 1467.9618 | AS20: =AR20+$S20 -> 1465.7728 | AT20: =息差测算表!F41 -> 0.014147166 | AU20: =AN20+AU$2 -> 0.0016487251 | AV20: =AU20*AS20 -> 2.4166564 | AW20: =$U20 -> 0.0018367695 | AX20: =AW20*AS20 -> 2.6922867 | AY20: ='2026-2030年盈利测算表'!V$70 -> 1467.9618 | AZ20: =AY20+$S20 -> 1465.7728 | BA20: =息差测算表!G41 -> 0.013647166 | BB20: =AU20+BB$2 -> 0.0014137019 | BC20: =BB20*AZ20 -> 2.0721658 | BD20: =$U20 -> 0.0018367695 | BE20: =BD20*AZ20 -> 2.6922867
A21: 1.5.非银贷款 | B21: =('2025金市人民币'!$C$73)/10000 -> 2629.2 | C21: =('2025金市人民币'!$E$73)/10000 -> 2119.9462 | D21: =('2025金市人民币'!$G$73)/10000 -> 63.08885 | E21: =D21/C21 -> 0.029759647 | H21: =('2025金市人民币'!$K$73)/10000 -> 0 | I21: =H21/C21 -> 0 | J21: =('2025金市人民币'!$B$73)/10000 -> 3483 | K21: =('2025金市人民币'!$D$73)/10000 -> 3381.2532 | L21: =('2025金市人民币'!$F$73)/10000 -> 15.053249 | M21: =L21/K21 -> 0.0044519734 | P21: =('2025金市人民币'!$J$73)/10000 -> -58.95305 | Q21: =P21/K21 -> -0.017435267 | R21: ='2026-2030年盈利测算表'!$L$72 -> 3413.31 | S21: =K21-R21 -> -32.056849 | T21: =R21+S21 -> 3381.2532 | U21: =M21 -> 0.0044519734 | V21: =U21*T21 -> 15.053249 | W21: ='2026-2030年盈利测算表'!N$72 -> 3181.31 | X21: =W21+$S21 -> 3149.2532 | Y21: =息差测算表!C41 -> 0.014897166 | Z21: =U21+Z$2 -> 0.0043772019 | AA21: =Z21*X21 -> 13.784917 | AB21: =$U21 -> 0.0044519734 | AC21: =AB21*X21 -> 14.020391 | AD21: ='2026-2030年盈利测算表'!P$72 -> 2809.7825 | AE21: =AD21+$S21 -> 2777.7257 | AF21: =息差测算表!D41 -> 0.014506391 | AG21: =Z21+AG$2 -> 0.0040743409 | AH21: =AG21*AE21 -> 11.317401 | AI21: =$U21 -> 0.0044519734 | AJ21: =AI21*AE21 -> 12.366361 | AK21: ='2026-2030年盈利测算表'!R$72 -> 2434.7825 | AL21: =AK21+$S21 -> 2402.7257 | AM21: =息差测算表!E41 -> 0.014522166 | AN21: =AG21+AN$2 -> 0.0040920067 | AO21: =AN21*AL21 -> 9.8319696 | AP21: =$U21 -> 0.0044519734 | AQ21: =AP21*AL21 -> 10.696871 | AR21: ='2026-2030年盈利测算表'!T$72 -> 2359.7825 | AS21: =AR21+$S21 -> 2327.7257 | AT21: =息差测算表!F41 -> 0.014147166 | AU21: =AN21+AU$2 -> 0.004263929 | AV21: =AU21*AS21 -> 9.9252569 | AW21: =$U21 -> 0.0044519734 | AX21: =AW21*AS21 -> 10.362973 | AY21: ='2026-2030年盈利测算表'!V$72 -> 2634.7825 | AZ21: =AY21+$S21 -> 2602.7257 | BA21: =息差测算表!G41 -> 0.013647166 | BB21: =AU21+BB$2 -> 0.0040289058 | BC21: =BB21*AZ21 -> 10.486136 | BD21: =$U21 -> 0.0044519734 | BE21: =BD21*AZ21 -> 11.587265
A22: 2.1金市自营债券（人民币） | B22: =('2025金市人民币'!$C$75)/10000 -> 13034.192 | C22: =('2025金市人民币'!$E$75)/10000 -> 11952.215 | D22: =('2025金市人民币'!$G$75)/10000 -> 83.859653 | E22: =D22/C22 -> 0.0070162435 | H22: =('2025金市人民币'!$K$75)/10000 -> -208.77407 | I22: =H22/C22 -> -0.017467395 | J22: =('2025金市人民币'!$B$75)/10000 -> 17318.514 | K22: =('2025金市人民币'!$D$75)/10000 -> 16092.641 | L22: =('2025金市人民币'!$F$75)/10000 -> 44.925444 | M22: =L22/K22 -> 0.0027916762 | P22: =('2025金市人民币'!$J$75)/10000 -> -297.31805 | Q22: =P22/K22 -> -0.018475404 | R22: ='2026-2030年盈利测算表'!$L$79 -> 13030 | S22: =K22-R22+2000 -> 5062.6412 | T22: =R22+S22-2000 -> 16092.641 | U22: =M22 -> 0.0027916762 | V22: =U22*T22 -> 44.925444 | W22: ='2026-2030年盈利测算表'!N$79 -> 11853 | X22: =W22+$S22 -> 16915.641 | Y22: =息差测算表!C35 -> 0.0203656 | Z22: =U22+Z$2 -> 0.0027169047 | AA22: =Z22*X22 -> 45.958186 | AB22: =Y22+$Q22+$O22 -> 0.0018901955 | AC22: =AB22*X22 -> 31.973869 | AD22: ='2026-2030年盈利测算表'!P$79 -> 14358 | AE22: =AD22+$S22 -> 19420.641 | AF22: =息差测算表!D35 -> 0.0193123 | AG22: =Z22+AG$2 -> 0.0024140438 | AH22: =AG22*AE22 -> 46.882278 | AI22: =AF22+$Q22+$O22 -> 0.00083689535 | AJ22: =AI22*AE22 -> 16.253044 | AK22: ='2026-2030年盈利测算表'!R$79 -> 15358 | AL22: =AK22+$S22 -> 20420.641 | AM22: =息差测算表!E35 -> 0.019333333 | AN22: =AG22+AN$2 -> 0.0024317096 | AO22: =AN22*AL22 -> 49.657069 | AP22: =AM22+$Q22+$O22 -> 0.00085792896 | AQ22: =AP22*AL22 -> 17.519459 | AR22: ='2026-2030年盈利测算表'!T$79 -> 16358 | AS22: =AR22+$S22 -> 21420.641 | AT22: =息差测算表!F35 -> 0.019 | AU22: =AN22+AU$2 -> 0.0026036319 | AV22: =AU22*AS22 -> 55.771464 | AW22: =AT22+$Q22+$O22 -> 0.00052459562 | AX22: =AW22*AS22 -> 11.237175 | AY22: ='2026-2030年盈利测算表'!V$79 -> 17358 | AZ22: =AY22+$S22 -> 22420.641 | BA22: =息差测算表!G35 -> 0.018333333 | BB22: =AU22+BB$2 -> 0.0023686087 | BC22: =BB22*AZ22 -> 53.105725 | BD22: =BA22+$Q22+$O22 -> -0.00014207104 | BE22: =BD22*AZ22 -> -3.1853239
A23: 2.3.同业资产（时点，不含拆放非银） | B23: =('2025金市人民币'!$C$70)/10000 -> 607.86848 | C23: =('2025金市人民币'!$E$70+'2025金市人民币'!$E$72+'2025金市人民币'!$E$74)/10000 -> 411.7415 | D23: =('2025金市人民币'!$G$70+'2025金市人民币'!$G$72+'2025金市人民币'!$G$74)/10000 -> 10.279847 | E23: =D23/C23 -> 0.02496675 | H23: =('2025金市人民币'!$K$70+'2025金市人民币'!$K$72+'2025金市人民币'!$K$74)/10000 -> -0.039481 | I23: =H23/C23 -> -9.5887832e-05 | J23: =('2025金市人民币'!$B$70+'2025金市人民币'!$B$74)/10000 -> 552.71019 | K23: =('2025金市人民币'!$D$70+'2025金市人民币'!$D$72+'2025金市人民币'!$D$74)/10000 -> 323.52548 | L23: =('2025金市人民币'!$F$70+'2025金市人民币'!$F$72+'2025金市人民币'!$F$74)/10000 -> 1.502595 | M23: =L23/K23 -> 0.0046444409 | P23: =('2025金市人民币'!$J$70+'2025金市人民币'!$J$72+'2025金市人民币'!$J$74)/10000 -> -5.790394 | Q23: =P23/K23 -> -0.017897799 | R23: ='2026-2030年盈利测算表'!$L$88 -> 2415 | S23: =K23-R23 -> -2091.4745 | T23: =R23+S23 -> 323.52548 | U23: =M23 -> 0.0046444409 | V23: =U23*T23 -> 1.502595 | W23: ='2026-2030年盈利测算表'!N$88 -> 2617.2932 | X23: =W23+$S23 -> 525.8187 | Y23: =息差测算表!C41 -> 0.014897166 | Z23: =U23+Z$2 -> 0.0045696694 | AA23: =Z23*X23 -> 2.4028176 | AB23: =Y23+$Q23+$O23 -> -0.0030006326 | AC23: =AB23*X23 -> -1.5777887 | AD23: ='2026-2030年盈利测算表'!P$88 -> 4052.4939 | AE23: =AD23+$S23 -> 1961.0194 | AF23: =息差测算表!D41 -> 0.014506391 | AG23: =Z23+AG$2 -> 0.0042668085 | AH23: =AG23*AE23 -> 8.3672941 | AI23: =AF23+$Q23+$O23 -> -0.0033914078 | AJ23: =AI23*AE23 -> -6.6506164 | AK23: ='2026-2030年盈利测算表'!R$88 -> 4408.423 | AL23: =AK23+$S23 -> 2316.9485 | AM23: =息差测算表!E41 -> 0.014522166 | AN23: =AG23+AN$2 -> 0.0042844743 | AO23: =AN23*AL23 -> 9.9269064 | AP23: =AM23+$Q23+$O23 -> -0.0033756326 | AQ23: =AP23*AL23 -> -7.8211669 | AR23: ='2026-2030年盈利测算表'!T$88 -> 4699.644 | AS23: =AR23+$S23 -> 2608.1695 | AT23: =息差测算表!F41 -> 0.014147166 | AU23: =AN23+AU$2 -> 0.0044563965 | AV23: =AU23*AS23 -> 11.623038 | AW23: =AT23+$Q23+$O23 -> -0.0037506326 | AX23: =AW23*AS23 -> -9.7822855 | AY23: ='2026-2030年盈利测算表'!V$88 -> 4928.0609 | AZ23: =AY23+$S23 -> 2836.5864 | BA23: =息差测算表!G41 -> 0.013647166 | BB23: =AU23+BB$2 -> 0.0042213733 | BC23: =BB23*AZ23 -> 11.97429 | BD23: =BA23+$Q23+$O23 -> -0.0042506326 | BE23: =BD23*AZ23 -> -12.057287
A24: 3.1.外币债券 | B24: =('2025金市外币'!$C$75)/10000 -> 443.03218 | C24: =('2025金市外币'!$E$75)/10000 -> 420.68492 | D24: =('2025金市外币'!$G$75)/10000 -> 3.463919 | E24: =D24/C24 -> 0.0082339985 | H24: =('2025金市外币'!$K$75)/10000 -> -15.437191 | I24: =H24/C24 -> -0.036695375 | J24: =('2025金市外币'!$B$75)/10000 -> 416.76804 | K24: =('2025金市外币'!$D$75)/10000 -> 398.30212 | L24: =('2025金市外币'!$F$75)/10000 -> 2.899921 | M24: =L24/K23 -> 0.008963501 | P24: =('2025金市外币'!$J$75)/10000 -> -15.754947 | Q24: =P24/K24 -> -0.039555268 | R24: ='2026-2030年盈利测算表'!$L$106*7 -> 511 | S24: =K24-R24 -> -112.69788 | T24: =R24+S24 -> 398.30212 | U24: =M24 -> 0.008963501 | V24: =U24*T24 -> 3.5701814 | W24: ='2026-2030年盈利测算表'!N$106*7 -> 1099 | X24: =W24+$S24 -> 986.30212 | Z24: =U24+Z$2 -> 0.0088887295 | AA24: =Z24*X24 -> 8.7669727 | AB24: =U24 -> 0.008963501 | AC24: =AB24*X24 -> 8.84072 | AD24: ='2026-2030年盈利测算表'!P$106*7 -> 1596.07 | AE24: =AD24+$S24 -> 1483.3721 | AG24: =Z24+AG$2 -> 0.0085858685 | AH24: =AG24*AE24 -> 12.736038 | AI24: =AB24 -> 0.008963501 | AJ24: =AI24*AE24 -> 13.296207 | AK24: ='2026-2030年盈利测算表'!R$106*7 -> 1456.07 | AL24: =AK24+$S24 -> 1343.3721 | AN24: =AG24+AN$2 -> 0.0086035344 | AO24: =AN24*AL24 -> 11.557748 | AP24: =AI24 -> 0.008963501 | AQ24: =AP24*AL24 -> 12.041317 | AR24: ='2026-2030年盈利测算表'!T$106*7 -> 1141.07 | AS24: =AR24+$S24 -> 1028.3721 | AU24: =AN24+AU$2 -> 0.0087754566 | AV24: =AU24*AS24 -> 9.0244349 | AW24: =AP24 -> 0.008963501 | AX24: =AW24*AS24 -> 9.2178145 | AY24: ='2026-2030年盈利测算表'!V$106*7 -> 826.07 | AZ24: =AY24+$S24 -> 713.37212 | BB24: =AU24+BB$2 -> 0.0085404334 | BC24: =BB24*AZ24 -> 6.0925071 | BD24: =AW24 -> 0.008963501 | BE24: =BD24*AZ24 -> 6.3943117
A25: 3.2.外币同业资产 | B25: =('2025金市外币'!$C$69)/10000 -> -3.767966 | C25: =('2025金市外币'!$E$69)/10000 -> -2.064744 | D25: =('2025金市外币'!$G$69)/10000 -> -0.050311 | E25: =D25/C25 -> 0.024366701 | H25: =('2025金市外币'!$K$69)/10000 -> -0.050466 | I25: =H25/C25 -> 0.024441771 | J25: =('2025金市外币'!$B$69)/10000 -> 1.789414 | K25: =('2025金市外币'!$D$69)/10000 -> 1.82949 | L25: =('2025金市外币'!$F$69)/10000 -> -0.067437 | M25: =L25/K25 -> -0.036861092 | P25: =('2025金市外币'!$J$69)/10000 -> -0.072915 | Q25: =P25/K25 -> -0.03985537 | R25: ='2026-2030年盈利测算表'!$L$108*7 -> 609 | S25: =K25-R25 -> -607.17051 | T25: =R25+S25 -> 1.82949 | U25: 0 | V25: =U25*T25 -> 0 | W25: ='2026-2030年盈利测算表'!N$108*7 -> 679 | X25: =W25+$S25 -> 71.82949 | Z25: =U25+Z$2 -> -7.47715e-05 | AA25: =Z25*X25 -> -0.0053707987 | AB25: =U25 -> 0 | AC25: =AB25*X25 -> 0 | AD25: ='2026-2030年盈利测算表'!P$108*7 -> 679 | AE25: =AD25+$S25 -> 71.82949 | AG25: =Z25+AG$2 -> -0.00037763246 | AH25: =AG25*AE25 -> -0.027125147 | AI25: =AB25 -> 0 | AJ25: =AI25*AE25 -> 0 | AK25: ='2026-2030年盈利测算表'!R$108*7 -> 679 | AL25: =AK25+$S25 -> 71.82949 | AN25: =AG25+AN$2 -> -0.00035996663 | AO25: =AN25*AL25 -> -0.025856219 | AP25: =AI25 -> 0 | AQ25: =AP25*AL25 -> 0 | AR25: ='2026-2030年盈利测算表'!T$108*7 -> 679 | AS25: =AR25+$S25 -> 71.82949 | AU25: =AN25+AU$2 -> -0.00018804438 | AV25: =AU25*AS25 -> -0.013507132 | AW25: =AP25 -> 0 | AX25: =AW25*AS25 -> 0 | AY25: ='2026-2030年盈利测算表'!V$108*7 -> 679 | AZ25: =AY25+$S25 -> 71.82949 | BB25: =AU25+BB$2 -> -0.00042306759 | BC25: =BB25*AZ25 -> -0.030388729 | BD25: =AW25 -> 0 | BE25: =BD25*AZ25 -> 0
A26: 2.人民币市场化负债 | B26: =('2025金市人民币'!$C$37+'2025金市人民币'!$C$42+'2025司库人民币'!$C$43)/10000 -> 18515.426 | C26: =('2025金市人民币'!$E$37+'2025金市人民币'!$E$42+'2025司库人民币'!$E$43)/10000 -> 16906.659 | D26: =('2025金市人民币'!$G$37+'2025金市人民币'!$G$41+'2025金市人民币'!$G$42+'2025司库人民币'!$G$43)/10000 -> -136.26523 | E26: =D26/C26 -> -0.0080598554 | H26: =('2025金市人民币'!$K$37+'2025金市人民币'!$K$41+'2025金市人民币'!$K$42+'2025司库人民币'!$K$43)/10000 -> 212.93372 | I26: =H26/C26 -> 0.012594666 | J26: =('2025金市人民币'!$B$37+'2025金市人民币'!$B$42+'2025金市人民币'!$B$43)/10000 -> 18070.202 | K26: =('2025金市人民币'!$D$37+'2025金市人民币'!$D$42+'2025金市人民币'!$D$43)/10000 -> 18300.435 | L26: =('2025金市人民币'!$F$37+'2025金市人民币'!$F$41+'2025金市人民币'!$F$42+'2025金市人民币'!$F$43)/10000 -> 45.381175 | M26: =L26/K26 -> 0.0024797867 | P26: =('2025金市人民币'!$J$37+'2025金市人民币'!$J$41+'2025金市人民币'!$J$42+'2025金市人民币'!$J$43)/10000 -> 343.03254 | Q26: =P26/K26 -> 0.018744502 | R26: ='2026-2030年盈利测算表'!$L$140 -> 26688 | S26: =K26-R26 -> -8387.5652 | T26: =R26+S26 -> 18300.435 | U26: =M26 -> 0.0024797867 | V26: =U26*T26 -> 45.381175 | W26: ='2026-2030年盈利测算表'!N$140 -> 26475.655 | X26: =W26+$S26 -> 18088.09 | Y26: =息差测算表!C88 -> 0.016 | Z26: =U26+Z$2 -> 0.0024050152 | AA26: =Z26*X26 -> 43.502131 | AB26: =$Q26-Y26+$O26 -> 0.0027445022 | AC26: =AB26*X26 -> 49.642802 | AD26: ='2026-2030年盈利测算表'!P$140 -> 29713.563 | AE26: =AD26+$S26 -> 21325.998 | AF26: =息差测算表!D88 -> 0.015126448 | AG26: =Z26+AG$2 -> 0.0021021543 | AH26: =AG26*AE26 -> 44.830537 | AI26: =$Q26-AF26+$O26 -> 0.0036180537 | AJ26: =AI26*AE26 -> 77.158605 | AK26: ='2026-2030年盈利测算表'!R$140 -> 28799.304 | AL26: =AK26+$S26 -> 20411.739 | AM26: =息差测算表!E88 -> 0.015094028 | AN26: =AG26+AN$2 -> 0.0021198201 | AO26: =AN26*AL26 -> 43.269214 | AP26: =$Q26-AM26+$O26 -> 0.0036504737 | AQ26: =AP26*AL26 -> 74.512517 | AR26: ='2026-2030年盈利测算表'!T$140 -> 27694.949 | AS26: =AR26+$S26 -> 19307.384 | AT26: =息差测算表!F88 -> 0.014729805 | AU26: =AN26+AU$2 -> 0.0022917423 | AV26: =AU26*AS26 -> 44.247549 | AW26: =$Q26-AT26+$O26 -> 0.0040146968 | AX26: =AW26*AS26 -> 77.513291 | AY26: ='2026-2030年盈利测算表'!V$140 -> 26324.833 | AZ26: =AY26+$S26 -> 17937.268 | BA26: =息差测算表!G88 -> 0.014109661 | BB26: =AU26+BB$2 -> 0.0020567191 | BC26: =BB26*AZ26 -> 36.891922 | BD26: =$Q26-BA26+$O26 -> 0.0046348407 | BE26: =BD26*AZ26 -> 83.136379
A27: 2.外币市场化负债 | B27: =('2025金市外币'!$C$37)/10000 -> 0 | C27: =('2025金市外币'!$E$37)/10000 -> 0 | D27: 0 | E27: =D27/C27 -> #DIV/0! | H27: 0 | I27: =H27/C27 -> #DIV/0! | J27: =('2025金市外币'!$B$37)/10000 -> 132.09235 | K27: =('2025金市外币'!$D$37)/10000 -> 71.55598 | L27: =('2025金市外币'!$F$37)/10000 -> 0.189744 | M27: =L27/K27 -> 0.0026516861 | P27: =('2025金市外币'!$J$37)/10000 -> 3.431585 | Q27: =P27/K27 -> 0.047956649 | R27: ='2026-2030年盈利测算表'!$L$148*7 -> 364 | S27: =K27-R27 -> -292.44402 | T27: =R27+S27 -> 71.55598 | U27: =M27 -> 0.0026516861 | V27: =U27*T27 -> 0.189744 | W27: ='2026-2030年盈利测算表'!N$148*7 -> 364 | X27: =W27+$S27 -> 71.55598 | Z27: =U27+Z$2 -> 0.0025769146 | AA27: =Z27*X27 -> 0.18439365 | AB27: =$U$27 -> 0.0026516861 | AC27: =AB27*X27 -> 0.189744 | AD27: ='2026-2030年盈利测算表'!P$148*7 -> 364 | AE27: =AD27+$S27 -> 71.55598 | AG27: =Z27+AG$2 -> 0.0022740537 | AH27: =AG27*AE27 -> 0.16272214 | AI27: =$U$27 -> 0.0026516861 | AJ27: =AI27*AE27 -> 0.189744 | AK27: ='2026-2030年盈利测算表'!R$148*7 -> 364 | AL27: =AK27+$S27 -> 71.55598 | AN27: =AG27+AN$2 -> 0.0022917195 | AO27: =AN27*AL27 -> 0.16398623 | AP27: =$U$27 -> 0.0026516861 | AQ27: =AP27*AL27 -> 0.189744 | AR27: ='2026-2030年盈利测算表'!T$148*7 -> 364 | AS27: =AR27+$S27 -> 71.55598 | AU27: =AN27+AU$2 -> 0.0024636418 | AV27: =AU27*AS27 -> 0.1762883 | AW27: =$U$27 -> 0.0026516861 | AX27: =AW27*AS27 -> 0.189744 | AY27: ='2026-2030年盈利测算表'!V$148*7 -> 364 | AZ27: =AY27+$S27 -> 71.55598 | BB27: =AU27+BB$2 -> 0.0022286185 | BC27: =BB27*AZ27 -> 0.15947098 | BD27: =$U$27 -> 0.0026516861 | BE27: =BD27*AZ27 -> 0.189744
W32: 对公条线 | X32: 2025年 | Y32: 2026年 | Z32: 2027年 | AC32: 2028年 | AD32: 2029年 | AE32: 2030年
W33: 1.1.对公一般贷款 | X33: =#REF! -> #REF!
W34: 2.2.结构化融资 | X34: =#REF! -> #REF!
W35: 1.境内外币贷款 | X35: =#REF! -> #REF!
W36: 1.1.对公存款 | X36: =#REF! -> #REF!
W37: 其中：对公活期存款 | X37: =#REF! -> #REF!
W38: 其中：对公定期存款 | X38: =(#REF!*#REF!-#REF!*#REF!)/(#REF!-#REF!) -> #REF!
W39: 1.外币存款 | X39: =#REF! -> #REF!
W40: 零售条线
W41: 1.2.个人贷款 | X41: =#REF! -> #REF!
W42: 1.3.信用卡贷款 | X42: =#REF! -> #REF!
W43: 1.2.零售存款 | X43: =#REF! -> #REF!
W44: 其中：零售活期存款 | X44: =#REF! -> #REF!
W45: 其中：零售定期存款 | X45: =(#REF!*#REF!-#REF!*#REF!)/(#REF!-#REF!) -> #REF!
W46: 金市条线
W47: 1.4.票据贴现 | X47: =#REF! -> #REF!
W48: 1.5.非银贷款 | X48: =#REF! -> #REF!
W49: 2.1金市自营债券（人民币） | X49: =#REF! -> #REF!
W50: 2.3.同业资产（时点，不含拆放非银） | X50: =#REF! -> #REF!
W51: 3.1.外币债券
W52: 3.2.外币同业资产
W53: 2.人民币市场化负债 | X53: =#REF! -> #REF!
W54: 2.外币市场化负债

Sheet 板块-利息（积极-原版本）
U2: ='2026-2030年盈利测算表'!O30/2 -> -7.47715e-05 | Y2: ='2026-2030年盈利测算表'!Q30/2 -> -0.00030286096 | AC2: ='2026-2030年盈利测算表'!S30/2 -> 1.7665831e-05 | AG2: ='2026-2030年盈利测算表'!U30/2 -> 0.00017192225 | AK2: ='2026-2030年盈利测算表'!W30/2 -> -0.00023502321
A3: 项目 | B3: 2024年 | H3: 2025年 | N3: 2025年 | S3: 2026年 | W3: 2027年 | AA3: 2028年 | AE3: 2029年 | AI3: 2030年
B4: 时点 | C4: 平均余额 | D4: 利息净收入 | E4: FTP利差 | F4: 补贴 | G4: 补贴率 | H4: 时点 | I4: 平均余额 | J4: 利息净收入 | K4: FTP利差 | L4: 补贴 | M4: 补贴率 | N4: 平均余额 | O4: 调整量 | P4: 调整后日均 | Q4: FTP利差及补贴率 | R4: 利息净收入 | S4: 平均余额 | T4: 调整后日均 | U4: FTP利差及补贴率 | V4: 利息净收入 | W4: 平均余额 | X4: 调整后日均 | Y4: FTP利差及补贴率 | Z4: 利息净收入 | AA4: 平均余额 | AB4: 调整后日均 | AC4: FTP利差及补贴率 | AD4: 利息净收入 | AE4: 平均余额 | AF4: 调整后日均 | AG4: FTP利差及补贴率 | AH4: 利息净收入 | AI4: 平均余额 | AJ4: 调整后日均 | AK4: FTP利差及补贴率 | AL4: 利息净收入
A5: 对公条线 | D5: =D6+D7++D8+D9+D12 -> 678.33913 | F5: =SUM(F6:F12) -> 46.38375 | J5: =J6+J7++J8+J9+J12 -> 697.86592 | L5: =SUM(L6:L12) -> 51.986471 | R5: =R6+R7++R8+R9+R12 -> 749.85239 | V5: =V6+V7++V8+V9+V12 -> 779.79014 | Z5: =Z6+Z7++Z8+Z9+Z12 -> 808.67305 | AD5: =AD6+AD7++AD8+AD9+AD12 -> 862.50791 | AH5: =AH6+AH7++AH8+AH9+AH12 -> 928.04319 | AL5: =AL6+AL7++AL8+AL9+AL12 -> 956.6628 | AM5: =AL5-AH5 -> 28.619609
A6: 1.1.对公一般贷款 | B6: =('2025对公人民币'!$C$50)/10000 -> 25889.737 | C6: =('2025对公人民币'!$E$50)/10000 -> 25660.363 | D6: =('2025对公人民币'!$G$48)/10000 -> 205.47597 | E6: =D6/C6 -> 0.0080075242 | F6: =('2025对公人民币'!$G$92+'2025对公人民币'!$G$97)/10000 -> 45.384394 | G6: =F6/C6 -> 0.0017686575 | H6: =('2025对公人民币'!$B$50)/10000 -> 29273.308 | I6: =('2025对公人民币'!$D$50)/10000 -> 28333.814 | J6: =('2025对公人民币'!$F$49)/10000 -> 232.01934 | K6: =J6/I6 -> 0.008188779 | L6: =('2025对公人民币'!$F$92+'2025对公人民币'!$F$97)/10000 -> 50.797726 | M6: =L6/I6 -> 0.0017928305 | N6: ='2026-2030年盈利测算表'!$L$61 -> 28337.351 | O6: =I6-N6 -> -3.5375403 | P6: =N6+O6 -> 28333.814 | Q6: =K6+M6 -> 0.0099816095 | R6: =Q6*P6 -> 282.81707 | S6: ='2026-2030年盈利测算表'!N$61 -> 31337.351 | T6: =S6+$O6 -> 31333.814 | U6: =Q6+U$2 -> 0.009906838 | V6: =U6*T6 -> 310.41902 | W6: ='2026-2030年盈利测算表'!P$61 -> 34017.351 | X6: =W6+$O6 -> 34013.814 | Y6: =U6+Y$2 -> 0.0096039771 | Z6: =Y6*X6 -> 326.66789 | AA6: ='2026-2030年盈利测算表'!R$61 -> 36457.351 | AB6: =AA6+$O6 -> 36453.814 | AC6: =Y6+AC$2 -> 0.0096216429 | AD6: =AC6*AB6 -> 350.74558 | AE6: ='2026-2030年盈利测算表'!T$61 -> 38647.351 | AF6: =AE6+$O6 -> 38643.814 | AG6: =AC6+AG$2 -> 0.0097935651 | AH6: =AG6*AF6 -> 378.46071 | AI6: ='2026-2030年盈利测算表'!V$61 -> 40617.351 | AJ6: =AI6+$O6 -> 40613.814 | AK6: =AG6+AK$2 -> 0.0095585419 | AL6: =AK6*AJ6 -> 388.20884 | AM6: =AL6-AH6 -> 9.7481345
A7: 2.2.结构化融资 | B7: =('2025对公人民币'!$C$65)/10000 -> 1585.2996 | C7: =('2025对公人民币'!$E$65)/10000 -> 1623.7424 | D7: =('2025对公人民币'!$G$65)/10000 -> 21.234315 | E7: =D7/C7 -> 0.013077392 | H7: =('2025对公人民币'!$B$65)/10000 -> 1557.0979 | I7: =('2025对公人民币'!$D$65)/10000 -> 1562.0869 | J7: =('2025对公人民币'!$F$65)/10000 -> 20.08368 | K7: =J7/I7 -> 0.012856954 | N7: ='2026-2030年盈利测算表'!$L$85 -> 2102 | O7: =I7-N7 -> -539.91306 | P7: =N7+O7 -> 1562.0869 | Q7: =K7 -> 0.012856954 | R7: =Q7*P7 -> 20.08368 | S7: ='2026-2030年盈利测算表'!N$85 -> 2043 | T7: =S7+$O7 -> 1503.0869 | U7: =Q7+U$2 -> 0.012782183 | V7: =U7*T7 -> 19.212732 | W7: ='2026-2030年盈利测算表'!P$85 -> 2043 | X7: =W7+$O7 -> 1503.0869 | Y7: =U7+Y$2 -> 0.012479322 | Z7: =Y7*X7 -> 18.757505 | AA7: ='2026-2030年盈利测算表'!R$85 -> 2043 | AB7: =AA7+$O7 -> 1503.0869 | AC7: =Y7+AC$2 -> 0.012496987 | AD7: =AC7*AB7 -> 18.784059 | AE7: ='2026-2030年盈利测算表'!T$85 -> 2043 | AF7: =AE7+$O7 -> 1503.0869 | AG7: =AC7+AG$2 -> 0.01266891 | AH7: =AG7*AF7 -> 19.042473 | AI7: ='2026-2030年盈利测算表'!V$85 -> 2043 | AJ7: =AI7+$O7 -> 1503.0869 | AK7: =AG7+AK$2 -> 0.012433886 | AL7: =AK7*AJ7 -> 18.689212 | AM7: =AL7-AH7 -> -0.35326031
A8: 1.境内外币贷款 | B8: =('2025对公外币'!$C$49)/10000 -> 756.18197 | C8: =('2025对公外币'!$E$49)/10000 -> 717.6423 | D8: =('2025对公外币'!$G$49)/10000 -> 5.510139 | E8: =D8/C8 -> 0.0076781134 | F8: =('2025对公外币'!$G$92+'2025对公外币'!$G$97)/10000 -> 0.999356 | H8: =('2025对公外币'!$B$49)/10000 -> 834.05625 | I8: =('2025对公外币'!$D$49)/10000 -> 851.44728 | J8: =('2025对公外币'!$F$49)/10000 -> 5.046905 | K8: =J8/I8 -> 0.0059274427 | L8: =('2025对公外币'!$F$92+'2025对公外币'!$F$97)/10000 -> 1.188745 | M8: =L8/I8 -> 0.0013961463 | N8: ='2026-2030年盈利测算表'!$L$101*7 -> 1008 | O8: =I8-N8 -> -156.55272 | P8: =N8+O8 -> 851.44728 | Q8: =K8+M8 -> 0.007323589 | R8: =Q8*P8 -> 6.23565 | S8: ='2026-2030年盈利测算表'!N$101*7 -> 1159.2 | T8: =S8+$O8 -> 1002.6473 | U8: =Q8+U$2 -> 0.0072488175 | V8: =U8*T8 -> 7.2680072 | W8: ='2026-2030年盈利测算表'!P$101*7 -> 1320.13 | X8: =W8+$O8 -> 1163.5773 | Y8: =U8+Y$2 -> 0.0069459566 | Z8: =Y8*X8 -> 8.0821573 | AA8: ='2026-2030年盈利测算表'!R$101*7 -> 1670.13 | AB8: =AA8+$O8 -> 1513.5773 | AC8: =Y8+AC$2 -> 0.0069636224 | AD8: =AC8*AB8 -> 10.539981 | AE8: ='2026-2030年盈利测算表'!T$101*7 -> 2020.13 | AF8: =AE8+$O8 -> 1863.5773 | AG8: =AC8+AG$2 -> 0.0071355447 | AH8: =AG8*AF8 -> 13.297639 | AI8: ='2026-2030年盈利测算表'!V$101*7 -> 2370.13 | AJ8: =AI8+$O8 -> 2213.5773 | AK8: =AG8+AK$2 -> 0.0069005215 | AL8: =AK8*AJ8 -> 15.274838 | AM8: =AL8-AH8 -> 1.9771986
A9: 1.1.对公存款 | B9: =('2025对公人民币'!$C$9)/10000 -> 37521.175 | C9: =('2025对公人民币'!$E$9)/10000 -> 36404.754 | D9: =('2025对公人民币'!$G$9)/10000 -> 424.65036 | E9: =D9/C9 -> 0.011664695 | H9: =('2025对公人民币'!$B$9)/10000 -> 38895.76 | I9: =('2025对公人民币'!$D$9)/10000 -> 38001.257 | J9: =('2025对公人民币'!$F$9)/10000 -> 421.94727 | K9: =J9/I9 -> 0.011103508 | N9: ='2026-2030年盈利测算表'!$L$128 -> 38055.867 | O9: =I9-N9 -> -54.609378 | P9: =N9+O9 -> 38001.257 | Q9: =K9 -> 0.011103508 | R9: =Q9*P9 -> 421.94727 | S9: ='2026-2030年盈利测算表'!N$128 -> 39355.867 | T9: =S9+$O9 -> 39301.257 | U9: =V9/T9 -> 0.010737667 | V9: =V10+V11 -> 422.00382 | W9: ='2026-2030年盈利测算表'!P$128 -> 41055.867 | X9: =W9+$O9 -> 41001.257 | Y9: =Z9/X9 -> 0.010468392 | Z9: =Z10+Z11 -> 429.21722 | AA9: ='2026-2030年盈利测算表'!R$128 -> 42955.867 | AB9: =AA9+$O9 -> 42901.257 | AC9: =AD9/AB9 -> 0.010520444 | AD9: =AD10+AD11 -> 451.34028 | AE9: ='2026-2030年盈利测算表'!T$128 -> 44855.867 | AF9: =AE9+$O9 -> 44801.257 | AG9: =AH9/AF9 -> 0.010723836 | AH9: =AH10+AH11 -> 480.44135 | AI9: ='2026-2030年盈利测算表'!V$128 -> 46955.867 | AJ9: =AI9+$O9 -> 46901.257 | AK9: =AL9/AJ9 -> 0.010520629 | AL9: =AL10+AL11 -> 493.43074 | AM9: =AL9-AH9 -> 12.989391
A10: 其中：对公活期存款 | B10: =('2025对公人民币'!$C$10)/10000 -> 18987.111 | C10: =('2025对公人民币'!$E$10)/10000 -> 19160.377 | D10: =('2025对公人民币'!$G$10)/10000 -> 323.20839 | E10: =D10/C10 -> 0.016868582 | H10: =('2025对公人民币'!$B$10)/10000 -> 18838.786 | I10: =('2025对公人民币'!$D$10)/10000 -> 17388.973 | J10: =('2025对公人民币'!$F$10)/10000 -> 308.49187 | K10: =J10/I10 -> 0.01774066 | N10: ='2026-2030年盈利测算表'!$L$131 -> 17433 | O10: =I10-N10 -> -44.026546 | P10: =N10+O10 -> 17388.973 | Q10: =K10 -> 0.01774066 | R10: =Q10*P10 -> 308.49187 | S10: ='2026-2030年盈利测算表'!N$131 -> 17093 | T10: =S10+$O10 -> 17048.973 | U10: =Q10+U$2 -> 0.017665888 | V10: =U10*T10 -> 301.18526 | W10: ='2026-2030年盈利测算表'!P$131 -> 17943 | X10: =W10+$O10 -> 17898.973 | Y10: =U10+Y$2 -> 0.017363027 | Z10: =Y10*X10 -> 310.78037 | AA10: ='2026-2030年盈利测算表'!R$131 -> 18893 | AB10: =AA10+$O10 -> 18848.973 | AC10: =Y10+AC$2 -> 0.017380693 | AD10: =AC10*AB10 -> 327.60823 | AE10: ='2026-2030年盈利测算表'!T$131 -> 19843 | AF10: =AE10+$O10 -> 19798.973 | AG10: =AC10+AG$2 -> 0.017552616 | AH10: =AG10*AF10 -> 347.52377 | AI10: ='2026-2030年盈利测算表'!V$131 -> 20893 | AJ10: =AI10+$O10 -> 20848.973 | AK10: =AG10+AK$2 -> 0.017317592 | AL10: =AK10*AJ10 -> 361.05402 | AM10: =AL10-AH10 -> 13.530254
A11: 其中：对公定期存款 | B11: =B9-B10 -> 18534.064 | C11: =C9-C10 -> 17244.377 | D11: =D9-D10 -> 101.44197 | E11: =D11/C11 -> 0.0058826117 | H11: =H9-H10 -> 20056.974 | I11: =I9-I10 -> 20612.284 | J11: =J9-J10 -> 113.45541 | K11: =J11/I11 -> 0.0055042619 | N11: =N9-N10 -> 20622.867 | O11: =I11-N11 -> -10.582832 | P11: =N11+O11 -> 20612.284 | Q11: =K11 -> 0.0055042619 | R11: =Q11*P11 -> 113.45541 | S11: =S9-S10 -> 22262.867 | T11: =S11+$O11 -> 22252.284 | U11: =Q11+U$2 -> 0.0054294904 | V11: =U11*T11 -> 120.81856 | W11: =W9-W10 -> 23112.867 | X11: =W11+$O11 -> 23102.284 | Y11: =U11+Y$2 -> 0.0051266294 | Z11: =Y11*X11 -> 118.43685 | AA11: =AA9-AA10 -> 24062.867 | AB11: =AA11+$O11 -> 24052.284 | AC11: =Y11+AC$2 -> 0.0051442952 | AD11: =AC11*AB11 -> 123.73205 | AE11: =AE9-AE10 -> 25012.867 | AF11: =AE11+$O11 -> 25002.284 | AG11: =AC11+AG$2 -> 0.0053162175 | AH11: =AG11*AF11 -> 132.91758 | AI11: =AI9-AI10 -> 26062.867 | AJ11: =AI11+$O11 -> 26052.284 | AK11: =AG11+AK$2 -> 0.0050811943 | AL11: =AK11*AJ11 -> 132.37672 | AM11: =AL11-AH11 -> -0.54086294
A12: 1.外币存款 | B12: =('2025对公外币'!$C$22)/10000 -> 1691.3803 | C12: =('2025对公外币'!$E$22)/10000 -> 1441.9937 | D12: =('2025对公外币'!$G$8)/10000 -> 21.468342 | E12: =D12/C12 -> 0.014887958 | H12: =('2025对公外币'!$B$22)/10000 -> 1784.1836 | I12: =('2025对公外币'!$D$22)/10000 -> 1741.1196 | J12: =('2025对公外币'!$F$8)/10000 -> 18.768717 | K12: =J12/I12 -> 0.010779683 | N12: ='2026-2030年盈利测算表'!$L$145*7 -> 1743 | O12: =I12-N12 -> -1.880388 | P12: =N12+O12 -> 1741.1196 | Q12: =K12 -> 0.010779683 | R12: =Q12*P12 -> 18.768717 | S12: ='2026-2030年盈利测算表'!N$145*7 -> 1953 | T12: =S12+$O12 -> 1951.1196 | U12: =Q12+U$2 -> 0.010704911 | V12: =U12*T12 -> 20.886562 | W12: ='2026-2030年盈利测算表'!P$145*7 -> 2496.4158 | X12: =W12+$O12 -> 2494.5354 | Y12: =U12+Y$2 -> 0.01040205 | Z12: =Y12*X12 -> 25.948283 | AA12: ='2026-2030年盈利测算表'!R$145*7 -> 2986.4158 | AB12: =AA12+$O12 -> 2984.5354 | AC12: =Y12+AC$2 -> 0.010419716 | AD12: =AC12*AB12 -> 31.098012 | AE12: ='2026-2030年盈利测算表'!T$145*7 -> 3476.4158 | AF12: =AE12+$O12 -> 3474.5354 | AG12: =AC12+AG$2 -> 0.010591638 | AH12: =AG12*AF12 -> 36.801023 | AI12: ='2026-2030年盈利测算表'!V$145*7 -> 3966.4158 | AJ12: =AI12+$O12 -> 3964.5354 | AK12: =AG12+AK$2 -> 0.010356615 | AL12: =AK12*AJ12 -> 41.059168 | AM12: =AL12-AH12 -> 4.258145
A13: 零售条线 | D13: =D14+D15+D16 -> 509.44867 | F13: =F14+F15+F16 -> 21.955088 | J13: =J14+J15+J16 -> 466.36133 | L13: =SUM(L14:L18) -> 25.005626 | R13: =R14+R15+R16 -> 491.36696 | V13: =V14+V15+V16 -> 493.62669 | Z13: =Z14+Z15+Z16 -> 489.94628 | AD13: =AD14+AD15+AD16 -> 502.3437 | AH13: =AH14+AH15+AH16 -> 525.29615 | AL13: =AL14+AL15+AL16 -> 532.12944 | AM13: =AL13-AH13 -> 6.8332843
A14: 1.2.个人贷款 | B14: =('2025零售人民币'!$C$58)/10000 -> 18154.514 | C14: =('2025零售人民币'!$E$58)/10000 -> 17635.736 | D14: =('2025零售人民币'!$G$58)/10000 -> 120.22383 | E14: =D14/C14 -> 0.0068170573 | F14: =('2025零售人民币'!$G$94+'2025零售人民币'!$G$99)/10000 -> 21.955088 | G14: =F14/C14 -> 0.0012449204 | H14: =('2025零售人民币'!$B$58)/10000 -> 18409.542 | I14: =('2025零售人民币'!$D$58)/10000 -> 18261.902 | J14: =('2025零售人民币'!$F$58)/10000 -> 105.83204 | K14: =J14/I14 -> 0.0057952362 | L14: =('2025零售人民币'!$F$94+'2025零售人民币'!$F$99)/10000 -> 25.005626 | M14: =L14/I14 -> 0.0013692783 | N14: ='2026-2030年盈利测算表'!$L$64 -> 18261.238 | O14: =I14-N14 -> 0.66401072 | P14: =N14+O14 -> 18261.902 | Q14: =M14+K14 -> 0.0071645145 | R14: =Q14*P14 -> 130.83766 | S14: ='2026-2030年盈利测算表'!N$64 -> 18161.238 | T14: =S14+$O14 -> 18161.902 | U14: =Q14+U$2 -> 0.007089743 | V14: =U14*T14 -> 128.76322 | W14: ='2026-2030年盈利测算表'!P$64 -> 18184.921 | X14: =W14+$O14 -> 18185.585 | Y14: =U14+Y$2 -> 0.0067868821 | Z14: =Y14*X14 -> 123.42342 | AA14: ='2026-2030年盈利测算表'!R$64 -> 18234.921 | AB14: =AA14+$O14 -> 18235.585 | AC14: =Y14+AC$2 -> 0.0068045479 | AD14: =AC14*AB14 -> 124.08491 | AE14: ='2026-2030年盈利测算表'!T$64 -> 18334.921 | AF14: =AE14+$O14 -> 18335.585 | AG14: =AC14+AG$2 -> 0.0069764702 | AH14: =AG14*AF14 -> 127.91766 | AI14: ='2026-2030年盈利测算表'!V$64 -> 18434.921 | AJ14: =AI14+$O14 -> 18435.585 | AK14: =AG14+AK$2 -> 0.0067414469 | AL14: =AK14*AJ14 -> 124.28252 | AM14: =AL14-AH14 -> -3.6351432
A15: 1.3.信用卡贷款 | B15: =('2025零售人民币'!$C$64)/10000 -> 4874.8621 | C15: =('2025零售人民币'!$E$64)/10000 -> 4972.7642 | D15: =('2025零售人民币'!$G$64)/10000 -> 264.80783 | E15: =D15/C15 -> 0.053251637 | H15: =('2025零售人民币'!$B$64)/10000 -> 4615.1746 | I15: =('2025零售人民币'!$D$64)/10000 -> 4564.3988 | J15: =('2025零售人民币'!$F$64)/10000 -> 235.69213 | K15: =J15/I15 -> 0.051637059 | N15: ='2026-2030年盈利测算表'!$L$67 -> 4568.4939 | O15: =I15-N15 -> -4.0951731 | P15: =N15+O15 -> 4564.3988 | Q15: =K15 -> 0.051637059 | R15: =Q15*P15 -> 235.69213 | S15: ='2026-2030年盈利测算表'!N$67 -> 4482.4939 | T15: =S15+$O15 -> 4478.3988 | U15: =Q15+U$2 -> 0.051562287 | V15: =U15*T15 -> 230.91648 | W15: ='2026-2030年盈利测算表'!P$67 -> 4365.1776 | X15: =W15+$O15 -> 4361.0824 | Y15: =U15+Y$2 -> 0.051259426 | Z15: =Y15*X15 -> 223.54658 | AA15: ='2026-2030年盈利测算表'!R$67 -> 4315.1776 | AB15: =AA15+$O15 -> 4311.0824 | AC15: =Y15+AC$2 -> 0.051277092 | AD15: =AC15*AB15 -> 221.05977 | AE15: ='2026-2030年盈利测算表'!T$67 -> 4315.1776 | AF15: =AE15+$O15 -> 4311.0824 | AG15: =AC15+AG$2 -> 0.051449015 | AH15: =AG15*AF15 -> 221.80094 | AI15: ='2026-2030年盈利测算表'!V$67 -> 4315.1776 | AJ15: =AI15+$O15 -> 4311.0824 | AK15: =AG15+AK$2 -> 0.051213991 | AL15: =AK15*AJ15 -> 220.78774 | AM15: =AL15-AH15 -> -1.0132044
A16: 1.2.零售存款 | B16: =('2025零售人民币'!$C$25)/10000 -> 14313.876 | C16: =('2025零售人民币'!$E$25)/10000 -> 13306.346 | D16: =('2025零售人民币'!$G$25)/10000 -> 124.41701 | E16: =D16/C16 -> 0.009350201 | H16: =('2025零售人民币'!$B$25)/10000 -> 15535.015 | I16: =('2025零售人民币'!$D$25)/10000 -> 14926.463 | J16: =('2025零售人民币'!$F$25)/10000 -> 124.83717 | K16: =J16/I16 -> 0.0083634796 | N16: ='2026-2030年盈利测算表'!$L$134 -> 15327.216 | O16: =I16-N16 -> -400.75336 | P16: =N16+O16 -> 14926.463 | Q16: =K16 -> 0.0083634796 | R16: =Q16*P16 -> 124.83717 | S16: ='2026-2030年盈利测算表'!N$134 -> 16427.216 | T16: =S16+$O16 -> 16026.463 | U16: =V16/T16 -> 0.0083578632 | V16: =V17+V18 -> 133.94699 | W16: ='2026-2030年盈利测算表'!P$134 -> 18027.216 | X16: =W16+$O16 -> 17626.463 | Y16: =Z16/X16 -> 0.0081114561 | Z16: =Z17+Z18 -> 142.97628 | AA16: ='2026-2030年盈利测算表'!R$134 -> 19627.216 | AB16: =AA16+$O16 -> 19226.463 | AC16: =AD16/AB16 -> 0.0081761797 | AD16: =AD17+AD18 -> 157.19902 | AE16: ='2026-2030年盈利测算表'!T$134 -> 21327.216 | AF16: =AE16+$O16 -> 20926.463 | AG16: =AH16/AF16 -> 0.0083902163 | AH16: =AH17+AH18 -> 175.57755 | AI16: ='2026-2030年盈利测算表'!V$134 -> 23227.216 | AJ16: =AI16+$O16 -> 22826.463 | AK16: =AL16/AJ16 -> 0.0081948387 | AL16: =AL17+AL18 -> 187.05918 | AM16: =AL16-AH16 -> 11.481632
A17: 其中：零售活期存款 | B17: =('2025零售人民币'!$C$26)/10000 -> 3949.8559 | C17: =('2025零售人民币'!$E$26)/10000 -> 3447.6015 | D17: =('2025零售人民币'!$G$26)/10000 -> 85.506221 | E17: =D17/C17 -> 0.024801654 | H17: =('2025零售人民币'!$B$26)/10000 -> 4205.9755 | I17: =('2025零售人民币'!$D$26)/10000 -> 3913.2434 | J17: =('2025零售人民币'!$F$26)/10000 -> 85.47143 | K17: =J17/I17 -> 0.021841583 | N17: ='2026-2030年盈利测算表'!$L$137 -> 4152 | O17: =I17-N17 -> -238.75662 | P17: =N17+O17 -> 3913.2434 | Q17: =K17 -> 0.021841583 | R17: =Q17*P17 -> 85.47143 | S17: ='2026-2030年盈利测算表'!N$137 -> 4501.0573 | T17: =S17+$O17 -> 4262.3007 | U17: =Q17+U$2 -> 0.021766811 | V17: =U17*T17 -> 92.776695 | W17: ='2026-2030年盈利测算表'!P$137 -> 4981.0573 | X17: =W17+$O17 -> 4742.3007 | Y17: =U17+Y$2 -> 0.021463951 | Z17: =Y17*X17 -> 101.78851 | AA17: ='2026-2030年盈利测算表'!R$137 -> 5461.0573 | AB17: =AA17+$O17 -> 5222.3007 | AC17: =Y17+AC$2 -> 0.021481616 | AD17: =AC17*AB17 -> 112.18346 | AE17: ='2026-2030年盈利测算表'!T$137 -> 5971.0573 | AF17: =AE17+$O17 -> 5732.3007 | AG17: =AC17+AG$2 -> 0.021653539 | AH17: =AG17*AF17 -> 124.12459 | AI17: ='2026-2030年盈利测算表'!V$137 -> 6541.0573 | AJ17: =AI17+$O17 -> 6302.3007 | AK17: =AG17+AK$2 -> 0.021418515 | AL17: =AK17*AJ17 -> 134.98592 | AM17: =AL17-AH17 -> 10.86133
A18: 其中：零售定期存款 | B18: =B16-B17 -> 10364.02 | C18: =C16-C17 -> 9858.7442 | D18: =D16-D17 -> 38.910786 | E18: =D18/C18 -> 0.0039468299 | H18: =H16-H17 -> 11329.039 | I18: =I16-I17 -> 11013.22 | J18: =J16-J17 -> 39.365739 | K18: =J18/I18 -> 0.0035744079 | N18: =N16-N17 -> 11175.216 | O18: =I18-N18 -> -161.99673 | P18: =N18+O18 -> 11013.22 | Q18: =K18 -> 0.0035744079 | R18: =Q18*P18 -> 39.365739 | S18: =S16-S17 -> 11926.159 | T18: =S18+$O18 -> 11764.162 | U18: =Q18+U$2 -> 0.0034996364 | V18: =U18*T18 -> 41.17029 | W18: =W16-W17 -> 13046.159 | X18: =W18+$O18 -> 12884.162 | Y18: =U18+Y$2 -> 0.0031967754 | Z18: =Y18*X18 -> 41.187773 | AA18: =AA16-AA17 -> 14166.159 | AB18: =AA18+$O18 -> 14004.162 | AC18: =Y18+AC$2 -> 0.0032144412 | AD18: =AC18*AB18 -> 45.015557 | AE18: =AE16-AE17 -> 15356.159 | AF18: =AE18+$O18 -> 15194.162 | AG18: =AC18+AG$2 -> 0.0033863635 | AH18: =AG18*AF18 -> 51.452957 | AI18: =AI16-AI17 -> 16686.159 | AJ18: =AI18+$O18 -> 16524.162 | AK18: =AG18+AK$2 -> 0.0031513403 | AL18: =AK18*AJ18 -> 52.073259 | AM18: =AL18-AH18 -> 0.62030182
A19: 金市条线 | D19: =SUM(D20:D27) -> 79.244517 | F19: =SUM(F20:F27) -> 32.418629 | J19: =SUM(J20:J27) -> 114.69477 | R19: =SUM(R20:R27) -> 115.43247 | V19: =SUM(V20:V27) -> 111.11513 | Z19: =SUM(Z20:Z27) -> 120.87032 | AD19: =SUM(AD20:AD27) -> 120.96726 | AH19: =SUM(AH20:AH27) -> 127.19526 | AL19: =SUM(AL20:AL27) -> 115.31928 | AM19: =AL19-AH19 -> -11.875978
A20: 1.4.票据贴现 | B20: =('2025金市人民币'!$C$57)/10000 -> 4476.6428 | C20: =('2025金市人民币'!$E$57)/10000 -> 3959.448 | D20: =('2025金市人民币'!$G$57)/10000 -> 54.867785 | E20: =D20/C20 -> 0.013857433 | F20: =('2025金市人民币'!$G$93+'2025金市人民币'!$G$98)/10000 -> 32.418629 | G20: =F20/C20 -> 0.0081876638 | H20: =('2025金市人民币'!$B$57)/10000 -> 2004.0633 | I20: =('2025金市人民币'!$D$57)/10000 -> 2618.7728 | J20: =('2025金市人民币'!$F$57)/10000 -> 4.810082 | K20: =J20/I20 -> 0.0018367695 | N20: ='2026-2030年盈利测算表'!$L$70 -> 2620.9618 | O20: =I20-N20 -> -2.1890577 | P20: =N20+O20 -> 2618.7728 | Q20: =K20 -> 0.0018367695 | R20: =Q20*P20 -> 4.810082 | S20: ='2026-2030年盈利测算表'!N$70 -> 1567.9618 | T20: =S20+$O20 -> 1565.7728 | U20: =Q20+U$2 -> 0.001761998 | V20: =U20*T20 -> 2.7588885 | W20: ='2026-2030年盈利测算表'!P$70 -> 1467.9618 | X20: =W20+$O20 -> 1465.7728 | Y20: =U20+Y$2 -> 0.0014591371 | Z20: =Y20*X20 -> 2.1387634 | AA20: ='2026-2030年盈利测算表'!R$70 -> 1467.9618 | AB20: =AA20+$O20 -> 1465.7728 | AC20: =Y20+AC$2 -> 0.0014768029 | AD20: =AC20*AB20 -> 2.1646575 | AE20: ='2026-2030年盈利测算表'!T$70 -> 1467.9618 | AF20: =AE20+$O20 -> 1465.7728 | AG20: =AC20+AG$2 -> 0.0016487251 | AH20: =AG20*AF20 -> 2.4166564 | AI20: ='2026-2030年盈利测算表'!V$70 -> 1467.9618 | AJ20: =AI20+$O20 -> 1465.7728 | AK20: =AG20+AK$2 -> 0.0014137019 | AL20: =AK20*AJ20 -> 2.0721658 | AM20: =AL20-AH20 -> -0.34449061
A21: 1.5.非银贷款 | B21: =('2025金市人民币'!$C$73)/10000 -> 2629.2 | C21: =('2025金市人民币'!$E$73)/10000 -> 2119.9462 | D21: =('2025金市人民币'!$G$73)/10000 -> 63.08885 | E21: =D21/C21 -> 0.029759647 | H21: =('2025金市人民币'!$B$73)/10000 -> 3483 | I21: =('2025金市人民币'!$D$73)/10000 -> 3381.2532 | J21: =('2025金市人民币'!$F$73)/10000 -> 15.053249 | K21: =J21/I21 -> 0.0044519734 | N21: ='2026-2030年盈利测算表'!$L$72 -> 3413.31 | O21: =I21-N21 -> -32.056849 | P21: =N21+O21 -> 3381.2532 | Q21: =K21 -> 0.0044519734 | R21: =Q21*P21 -> 15.053249 | S21: ='2026-2030年盈利测算表'!N$72 -> 3181.31 | T21: =S21+$O21 -> 3149.2532 | U21: =Q21+U$2 -> 0.0043772019 | V21: =U21*T21 -> 13.784917 | W21: ='2026-2030年盈利测算表'!P$72 -> 2809.7825 | X21: =W21+$O21 -> 2777.7257 | Y21: =U21+Y$2 -> 0.0040743409 | Z21: =Y21*X21 -> 11.317401 | AA21: ='2026-2030年盈利测算表'!R$72 -> 2434.7825 | AB21: =AA21+$O21 -> 2402.7257 | AC21: =Y21+AC$2 -> 0.0040920067 | AD21: =AC21*AB21 -> 9.8319696 | AE21: ='2026-2030年盈利测算表'!T$72 -> 2359.7825 | AF21: =AE21+$O21 -> 2327.7257 | AG21: =AC21+AG$2 -> 0.004263929 | AH21: =AG21*AF21 -> 9.9252569 | AI21: ='2026-2030年盈利测算表'!V$72 -> 2634.7825 | AJ21: =AI21+$O21 -> 2602.7257 | AK21: =AG21+AK$2 -> 0.0040289058 | AL21: =AK21*AJ21 -> 10.486136 | AM21: =AL21-AH21 -> 0.56087954
